Workbook
Name Acq_Financing_Type_Switch: 'Debt Input'!$F$3
Name acquisition_cost: Import!$C$50
Name adr: Import!$C$51
Name adr_pro_forma: Import!$C$52
Name AF_Amort_P_Adj: AF_Amort_Periods - AF_Interest_Only
Name AF_Amort_Periods: AF_Amort*12
Name AF_Amort_Periods: AF_Amort*12
Name AF_Annual_Debt_Service: AF_Loan_Payment*12
Name AF_CUMPRINC: IFERROR(CUMPRINC(AF_I_Adj,AF_Amort_P_Adj, AF_Orig_Loan_Amount,1, AF_Int_Only_Period,0),0)
Name AF_FV: FV(AF_I_Adj, AF_Orig_Term*12, AF_PMT, AF_Orig_Loan_Amount)
Name AF_I_Adj: (AF_Interest_Rate/AF_Rate_Compounding_Switch + 1) ^ (AF_Rate_Compounding_Switch/12)-1
Name AF_Int_Only_Period: AF_Rate_Period_Switch-(AF_Interest_Only/12 )*AF_Rate_Compounding_Switch
Name AF_IPMT: IPMT(AF_I_Adj,1,AF_Amort_P_Adj, AF_Orig_Loan_Amount,0)
Name AF_Loan_Constant: -AF_Loan_Payment/AF_Orig_Loan_Amount*12
Name AF_Loan_Due_Date: EDATE(AF_Origination_Date, AF_Orig_Term*12-1)
Name AF_Loan_Payment: IF(AF_Int_Only_Period<0, AF_IPMT,AF_PMT)
Name AF_PMT: PMT(AF_I_Adj, AF_Amort_P_Adj, AF_Orig_Loan_Amount)
Name AF_PPMT: PPMT(AF_I_Adj,1, AF_Amort_P_Adj, AF_Orig_Loan_Amount,0)
Name AF_Rate_Compounding_Switch: _xlfn.SWITCH(AF_Compounding_Switch, "Monthly", 12, "Semi-Annually", 2)
Name AF_Rate_Compounding_Switch: _xlfn.SWITCH(AF_Compounding_Switch, "Monthly", 12, "Semi-Annually", 2)
Name AF_Time_Remaining: ROUNDUP(YEARFRAC(AF_Origination_Date, AF_Loan_Due_Date)*12,0)+1
Name Annualized_Rents_OS_Type: 'Annualized Rents'!$C$1:$C$4
Name Annualized_Total_Rents: 'Annualized Rents'!$B$1:$B$4
Name buildable_sq_ft: Import!$C$36
Name buildable_units: Import!$C$37
Name cap_over_lease: Import!$C$59
Name cap_rate: Import!$C$2
Name cap_rate_pro_forma: Import!$C$3
Name CapEx_1: Input!$E$27
Name CapEx_10: Input!$N$27
Name CapEx_2: Input!$F$27
Name CapEx_3: Input!$G$27
Name CapEx_4: Input!$H$27
Name CapEx_5: Input!$I$27
Name CapEx_6: Input!$J$27
Name CapEx_7: Input!$K$27
Name CapEx_8: Input!$L$27
Name CapEx_9: Input!$M$27
Name cash_on_cash: Import!$C$14
Name cash_on_cash_pro_forma: Import!$C$15
Name Cost_of_Sale: Input!$B$30
Name Current_Amort: IF(Acq_Financing_Type_Switch="Financed - Assumed Loan", SED_Amort,NEW_Amort)
Name Current_GAR: 'Rent Roll Calculations'!$K$33
Name Current_Interest_Rate: IF(Acq_Financing_Type_Switch="Financed - Assumed Loan", SED_Interest_Rate,NEW_Interest_Rate)
Name Current_Loan_Balance: Calculations!$F$11
Name Current_Loan_Origination_Fee: Calculations!$F$26
Name Current_PMT: Calculations!$F$14
Name Current_Term: IF(Acq_Financing_Type_Switch="Financed - Assumed Loan", SED_Term,NEW_Term)
Name Date_of_Analysis: Input!$B$8
Name ddl_OpColumns: OFFSET(Calculations!$Y$3,5-Calculations!$Y$2,0,Calculations!$Y$2,1)
Name debt_service: Import!$C$4
Name debt_service_pro_forma: Import!$C$5
Name density: Import!$C$38
Name development_type: Import!$C$35
Name down_payment: Import!$C$6
Name Equity_Returns_Input: 'Equity Returns Input'!$B$12:$L$27
Name Equity_Returns_Input_Headers: 'Equity Returns Input'!$B$12:$L$12
Name Equity_Returns_List: 'Data Validation'!$L$1:$L$4
Name ER_Exchange: 'Equity Returns Input'!$B$12:$C$27
Name ER_Hold: 'Equity Returns Input'!$E$12:$F$27

Sheet Import
A1: Named Range | B1: UI Name | C1: Values | E1: Unit mix
A2: cap_rate | B2: Cap Rate | C2: =ROUND('Pricing Detail'!G13*100,2) -> 0 | E2: count | F2: unit_type | G2: size | H2: rent
A3: cap_rate_pro_forma | B3: Cap Rate (Pro Forma) | C3: ='Pricing Detail'!H13 -> 0
A4: debt_service | B4: Debt Service (Current) | C4: =ROUND('Pricing Detail'!N15,0) -> 0
A5: debt_service_pro_forma | B5: Debt Service (Pro Forma) | C5: =debt_service -> 0
A6: down_payment | B6: Down Payment | C6: =ROUND('Pricing Detail'!G5,0) -> 0
A7: net_operating_income | B7: Net Operating Income (Current) | C7: =ROUND('Pricing Detail'!N13,0) -> 0
A8: net_operating_income_pro_forma | B8: Net Operating Income (Pro Forma) | C8: ='Pricing Detail'!P13 -> 0
A9: operating_expenses | B9: Expenses (Current) | C9: =ROUND('Pricing Detail'!N12,0) -> 0
A10: operating_expenses_pro_forma | B10: Expenses (Pro Forma) | C10: ='Pricing Detail'!P12 -> 0
A11: principal_reduction_yr_1 | B11: Principal Reduction (Current) | C11: =ROUND('Pricing Detail'!N17,0) -> 0
A12: principal_reduction_pro_forma | B12: Principal Reduction (Pro Forma) | C12: ='Debt Input'!U31 -> 0
A13: sale_price | B13: Proposal Price / Listing Price | C13: =sale_price -> 0
A14: cash_on_cash | B14: Total Return $ (Current) | C14: =ROUND('Pricing Detail'!N18,0) -> 0
A15: cash_on_cash_pro_forma | B15: Total Return $ (Pro Forma) | C15: =ROUND('Pricing Detail'!P18,0) -> 0
A16: total_return | B16: Total Return % (Current) | C16: =ROUND('Pricing Detail'!M18*100,2) -> 0
A17: total_return_pro_forma | B17: Total Return % (Pro Forma) | C17: =ROUND('Pricing Detail'!O18*100,2) -> 0
A18: loan_type | B18: Loan Type | C18: =IF(Acq_Financing_Type_Switch="All Cash","All Cash",IF(Acq_Financing_Type_Switch="Financed - Assumed Loan","Loan Assumption","New Loan")) -> New Loan
A19: gross_scheduled_income | B19: Gross Potential Rent (Current) | C19: =ROUND('Pricing Detail'!N7,0) -> 0
A20: gross_scheduled_income_pro_forma | B20: Gross Potential Rent (Pro Forma) | C20: =ROUND('Pricing Detail'!P7,0) -> 0
A21: other_income | B21: Total Other Income (Current) | C21: =ROUND('Pricing Detail'!N10,0) -> 0
A22: other_income_pro_forma | B22: Total Other Income (Pro Forma) | C22: =ROUND('Pricing Detail'!P10,0) -> 0
A23: vacancy_cost | B23: Total Vacancy Cost (Current) | C23: =ROUND('Pricing Detail'!N8,0) -> 0
A24: vacancy_cost_pro_forma | B24: Total Vacancy Cost (Pro Forma) | C24: =ROUND('Pricing Detail'!P8,0) -> 0
A25: vacancy_percent | B25: Occupancy (Current)
A26: vacancy_percent_pro_forma | B26: Occupancy (Pro Forma)
A27: unit_count | B27: Number of Units
A28: exp_reimbursement | B28: Expense Reimbursement (Current)
A29: exp_reimbursement_pro_forma | B29: Expense Reimbursement (Pro Forma)
A30: leasing_commissions | B30: Leasing Commissions (Current)
A31: leasing_commissions_pro_forma | B31: Leasing Commissions (Pro Forma)
A32: tenant_improvements | B32: Tenant Improvements (Current) | E32: Tenant
A33: tenant_improvements_pro_forma | B33: Tenant Improvements (Pro Forma)
A34: number_of_lots | B34: Number of Lots | E34: tenant_name | F34: anchor_tenant | G34: tenant_type
A35: development_type | B35: Development Type
A36: buildable_sq_ft | B36: Buildable Square Feet
A37: buildable_units | B37: Buildable Units
A38: density | B38: Density
A39: floor_area_ratio | B39: Floor Area Ratio (FAR)
A40: home_inventory_cost | B40: Home Inventory Cost
A41: home_rent | B41: Gross Potential Home Rent (Current)
A42: home_rent_pro_forma | B42: Gross Potential Home Rent (Pro Forma)
A43: tenant_type | B43: Tenant Type
A44: guarantor | B44: Guarantor
A45: lease_end | B45: Lease Expiration
A46: lease_term | B46: Lease Expiration
... A59: cap_over_lease | B59: Cap Over Lease

Sheet Input
A1: Marcus & Millichap - NMHG - Financial Model
A5: Property Information | D5: {=IF(IFERROR(_xlfn.SEQUENCE(1,1,1,1),FALSE)=1, "This model is compatible with your version of Excel", "This model is NOT compatible with your version of Excel, please upgrade to Office 365")} -> This model is compatible with your version of Excel
A6: Price
A7: Priced or Unpriced Listing | B7: Priced
A8: Date of Analysis/Acquisition
A9: Proposal Purchase Price Increments
A10: Property Description Input
A11: Property Name
A12: Property Address
A13: Property City
A14: Property State
A15: Year Built
A16: Net Residual Value
A17: 10 year Cash Flow analysis/IRR calculation?
A18: Rent Roll
A19: Rent Roll Analysis Start Date
A20: Rent Roll Input Type
A21: Include Loss/Gain to Lease | Q21: =Input!B6 -> 0
A22: Total Units | S22: Initial Cash-
A23: Total Occupied Units | R23: Year One | S23: on-Cash | T23: Unleveraged | U23: Leveraged | V23: Price | W23: Price | X23: Year One
A24: Year 1 Rent Growth | Q24: Price | R24: Cap Rate | S24: Return | T24: IRR | U24: IRR | V24: Per SF | W24: Per Unit | X24: GRM
A25: Capital Expenditures (ie. Renovation Costs, major replacement, etc.) | D25: CapEx Schedule | R25: ='Pricing Detail'!$H$13 -> 0 | S25: ='Pricing Detail'!$G$15 -> 0 | T25: ='Cash Flow'!$P$45 -> 0 | U25: ='Cash Flow'!$P$46 -> 0 | V25: ='Pricing Detail'!$G$8 -> 0 | W25: ='Pricing Detail'!$G$7 -> 0 | X25: ='Pricing Detail'!H14 -> 0
A26: If using capital expenditure, then select Yes | D26: Years | E26: 1 | F26: 2 | G26: 3 | H26: 4 | I26: 5 | J26: 6 | K26: 7 | L26: 8 | M26: 9 | N26: 10 | Q26: =Q27+Price_Increments -> 0 | R26: 0 | S26: 0 | T26: 0 | U26: 0 | V26: 0 | W26: 0 | X26: 0
D27: Annual Amount | Q27: =Q28+Price_Increments -> 0 | R27: 0 | S27: 0 | T27: 0 | U27: 0 | V27: 0 | W27: 0 | X27: 0
A28: Net Residual Value | Q28: =Q29+Price_Increments -> 0 | R28: 0 | S28: 0 | T28: 0 | U28: 0 | V28: 0 | W28: 0 | X28: 0
A29: Exit Capitalization Rate | Q29: =Q30+Price_Increments -> 0 | R29: 0 | S29: 0 | T29: 0 | U29: 0 | V29: 0 | W29: 0 | X29: 0
A30: Cost of Sale | Q30: =Q31+Price_Increments -> 0 | R30: 0 | S30: 0 | T30: 0 | U30: 0 | V30: 0 | W30: 0 | X30: 0
Q31: {=Price} -> 0 | R31: 0 | S31: 0 | T31: 0 | U31: 0 | V31: 0 | W31: 0 | X31: 0
Q32: =Q31-Price_Increments -> 0 | R32: 0 | S32: 0 | T32: 0 | U32: 0 | V32: 0 | W32: 0 | X32: 0
Q33: =Q32-Price_Increments -> 0 | R33: 0 | S33: 0 | T33: 0 | U33: 0 | V33: 0 | W33: 0 | X33: 0
Q34: =Q33-Price_Increments -> 0 | R34: 0 | S34: 0 | T34: 0 | U34: 0 | V34: 0 | W34: 0 | X34: 0
Q35: =Q34-Price_Increments -> 0 | R35: 0 | S35: 0 | T35: 0 | U35: 0 | V35: 0 | W35: 0 | X35: 0
Q36: =Q35-Price_Increments -> 0 | R36: 0 | S36: 0 | T36: 0 | U36: 0 | V36: 0 | W36: 0 | X36: 0

Sheet Loan Amort Table
A3: Seller's Existing Debt | D3: =SED_Loan_Name -> 0 | J3: New Loan | M3: =NEW_Loan_Name -> 0 | S3: Mezzanine Loan | V3: =NEW_Loan_Name -> 0 | AB3: Refinanced Loan | AE3: =Refi_Loan_Name -> 0
A4: Loan | D4: Beginning | H4: Ending | J4: Loan | M4: Beginning | Q4: Ending | S4: Loan | V4: Beginning | Z4: Ending | AB4: Loan | AE4: Beginning | AI4: Ending
A5: Year | B5: PMT | C5: Date | D5: Loan Balance | E5: Payment | F5: Principal | G5: Interest | H5: Loan Balance | J5: Year | K5: PMT | L5: Date | M5: Loan Balance | N5: Payment | O5: Principal | P5: Interest | Q5: Loan Balance | S5: Year | T5: PMT | U5: Date | V5: Loan Balance | W5: Payment | X5: Principal | Y5: Interest | Z5: Loan Balance | AB5: Year | AC5: PMT | AD5: Date | AE5: Loan Balance | AF5: Payment | AG5: Principal | AH5: Interest | AI5: Loan Balance
A6: =IFERROR(ROUNDUP((DATEDIF(SED_Origination_Date,C6,"m")+1)/12,0),"") -> 1 | B6: =IF(C6>=SED_Begin_PMT,1,0) -> 1 | C6: =DATE(YEAR(SED_Origination_Date), MONTH(SED_Origination_Date),1) -> 1 | D6: =SED_Orig_Loan_Amount -> 0 | E6: =F6+G6 -> 0 | F6: =IFERROR(IF(OR(B6=0, C6>=Refi_Origination_Date),0, PPMT(SED_I_Adj,'Loan Amort Table'!B6,SED_Amort_Periods,SED_Orig_Loan_Amount)),0) -> 0 | G6: {=IFERROR(_xlfn.IFS(C6>=Refi_Origination_Date, 0, SED_Amort = 0, -D6 * SED_I_Adj, 1, IPMT(SED_I_Adj,IF(B6 = 0, 1, B6),SED_Amort_Periods,SED_Orig_Loan_Amount)),0)} -> 0 | H6: =D6+F6 -> 0 | J6: =IFERROR(ROUNDUP((DATEDIF(NEW_Origination_Date,L6,"m")+1)/12,0),"") -> 1 | K6: =IF(L6>=NEW_Begin_PMT,1,0) -> 1 | L6: =DATE(YEAR(NEW_Origination_Date), MONTH(NEW_Origination_Date),1) -> 1 | M6: =NEW_Orig_Loan_Amount -> 0 | N6: =O6+P6 -> 0 | O6: =IFERROR(IF(K6=0,0, PPMT(NEW_I_Adj,'Loan Amort Table'!K6,NEW_Amort_Periods,NEW_Orig_Loan_Amount)),0) -> 0 | P6: =IFERROR(IF(NEW_Amort = 0, -M6* NEW_I_Adj,IPMT(NEW_I_Adj,IF(K6 = 0, 1, K6),NEW_Amort_Periods,NEW_Orig_Loan_Amount)),0) -> 0 | Q6: =M6+O6 -> 0 | S6: =IFERROR(ROUNDUP((DATEDIF(Mezz_Origination_Date,U6,"m")+1)/12,0),"") -> 1 | T6: =IF(U6>=Mezz_Begin_PMT,1,0) -> 1 | U6: =DATE(YEAR(Mezz_Origination_Date), MONTH(Mezz_Origination_Date),1) -> 1 | V6: =Mezz_Loan_Balance -> 0 | W6: =X6+Y6 -> 0 | X6: =IFERROR(IF(OR(T6=0, U6>=Refi_Origination_Date),0, PPMT(Mezz_I_Adj,'Loan Amort Table'!T6,Mezz_Amort_Periods,Mezz_Orig_Loan_Amount)),0) -> 0 | Y6: {=IFERROR(_xlfn.IFS(U6>=Refi_Origination_Date,0, Mezz_Amort = 0, -V6 * Mezz_I_Adj, 1, IPMT(Mezz_I_Adj,IF(T6 = 0, 1, T6),Mezz_Amort_Periods,Mezz_Orig_Loan_Amount)),0)} -> 0 | Z6: =V6+X6 -> 0 | AB6: =IFERROR(ROUNDUP((DATEDIF(Refi_Origination_Date,AD6,"m")+1)/12,0),"") -> 1 | AC6: =IF(AD6>=Refi_Begin_PMT,1,0) -> 1 | AD6: =DATE(YEAR(Refi_Origination_Date), MONTH(Refi_Origination_Date),1) -> 1 | AE6: =Refi_Loan_Balance -> 0 | AF6: =AG6+AH6 -> 0 | AG6: =IFERROR(IF(AC6=0,0, PPMT(Refi_I_Adj,'Loan Amort Table'!AC6,Refi_Amort_Periods,Refi_Orig_Loan_Amount)),0) -> 0 | AH6: =IFERROR(IF(Refi_Amort = 0, -AE6 * Refi_I_Adj, IPMT(Refi_I_Adj,IF(AC6 = 0, 1, AC6),Refi_Amort_Periods,Refi_Orig_Loan_Amount)),0) -> 0 | AI6: =AE6+AG6 -> 0
A7: =IFERROR(ROUNDUP((DATEDIF(SED_Origination_Date,C7,"m")+1)/12,0),"") -> 1 | B7: =IF(C7<SED_Begin_PMT,0, B6+1) -> 2 | C7: =EDATE(C6,1) -> 32 | D7: =IF(C7>EDATE(DATE(YEAR(SED_Origination_Date)+ SED_Amort, MONTH(SED_Origination_Date), DAY(SED_Origination_Date)),SED_Interest_Only),0,H6) -> 0 | E7: =F7+G7 -> 0 | F7: =IFERROR(IF(OR(B7=0, C7>=Refi_Origination_Date),0, PPMT(SED_I_Adj,'Loan Amort Table'!B7,SED_Amort_Periods,SED_Orig_Loan_Amount)),0) -> 0 | G7: {=IFERROR(_xlfn.IFS(C7>=Refi_Origination_Date, 0, SED_Amort = 0, -D7 * SED_I_Adj, 1, IPMT(SED_I_Adj,IF(B7 = 0, 1, B7),SED_Amort_Periods,SED_Orig_Loan_Amount)),0)} -> 0 | H7: =D7+F7 -> 0 | J7: =IFERROR(ROUNDUP((DATEDIF(NEW_Origination_Date,L7,"m")+1)/12,0),"") -> 1 | K7: =IF(L7<NEW_Begin_PMT,0, K6+1) -> 2 | L7: =EDATE(L6,1) -> 32 | M7: =IF(L7>EDATE(DATE(YEAR(NEW_Origination_Date)+ NEW_Amort, MONTH(NEW_Origination_Date), DAY(NEW_Origination_Date)),NEW_Interest_Only),0,Q6) -> 0 | N7: =O7+P7 -> 0 | O7: =IFERROR(IF(K7=0,0, PPMT(NEW_I_Adj,'Loan Amort Table'!K7,NEW_Amort_Periods,NEW_Orig_Loan_Amount)),0) -> 0 | P7: =IFERROR(IF(NEW_Amort = 0, -M7* NEW_I_Adj,IPMT(NEW_I_Adj,IF(K7 = 0, 1, K7),NEW_Amort_Periods,NEW_Orig_Loan_Amount)),0) -> 0 | Q7: =M7+O7 -> 0 | S7: =IFERROR(ROUNDUP((DATEDIF(Mezz_Origination_Date,U7,"m")+1)/12,0),"") -> 1 | T7: =IF(U7<Mezz_Begin_PMT,0, T6+1) -> 2 | U7: =EDATE(U6,1) -> 32 | V7: =IF(U7>EDATE(DATE(YEAR(Mezz_Origination_Date)+ Mezz_Amort, MONTH(Mezz_Origination_Date), DAY(Mezz_Origination_Date)),Mezz_Interest_Only),0,Z6) -> 0 | W7: =X7+Y7 -> 0 | X7: =IFERROR(IF(OR(T7=0, U7>=Refi_Origination_Date),0, PPMT(Mezz_I_Adj,'Loan Amort Table'!T7,Mezz_Amort_Periods,Mezz_Orig_Loan_Amount)),0) -> 0 | Y7: {=IFERROR(_xlfn.IFS(U7>=Refi_Origination_Date,0, Mezz_Amort = 0, -V7 * Mezz_I_Adj, 1, IPMT(Mezz_I_Adj,IF(T7 = 0, 1, T7),Mezz_Amort_Periods,Mezz_Orig_Loan_Amount)),0)} -> 0 | Z7: =V7+X7 -> 0 | AB7: =IFERROR(ROUNDUP((DATEDIF(Refi_Origination_Date,AD7,"m")+1)/12,0),"") -> 1 | AC7: =IF(AD7<Refi_Begin_PMT,0, AC6+1) -> 2 | AD7: =EDATE(AD6,1) -> 32 | AE7: =IF(AD7>EDATE(DATE(YEAR(Refi_Origination_Date)+ Refi_Amort, MONTH(Refi_Origination_Date), DAY(Refi_Origination_Date)),Refi_Interest_Only),0,AI6) -> 0 | AF7: =AG7+AH7 -> 0 | AG7: =IFERROR(IF(AC7=0,0, PPMT(Refi_I_Adj,'Loan Amort Table'!AC7,Refi_Amort_Periods,Refi_Orig_Loan_Amount)),0) -> 0 | AH7: =IFERROR(IF(Refi_Amort = 0, -AE7 * Refi_I_Adj, IPMT(Refi_I_Adj,IF(AC7 = 0, 1, AC7),Refi_Amort_Periods,Refi_Orig_Loan_Amount)),0) -> 0 | AI7: =AE7+AG7 -> 0
A8: =IFERROR(ROUNDUP((DATEDIF(SED_Origination_Date,C8,"m")+1)/12,0),"") -> 1 | B8: =IF(C8<SED_Begin_PMT,0, B7+1) -> 3 | C8: =EDATE(C7,1) -> 61 | D8: =IF(C8>EDATE(DATE(YEAR(SED_Origination_Date)+ SED_Amort, MONTH(SED_Origination_Date), DAY(SED_Origination_Date)),SED_Interest_Only),0,H7) -> 0 | E8: =F8+G8 -> 0 | F8: =IFERROR(IF(OR(B8=0, C8>=Refi_Origination_Date),0, PPMT(SED_I_Adj,'Loan Amort Table'!B8,SED_Amort_Periods,SED_Orig_Loan_Amount)),0) -> 0 | G8: {=IFERROR(_xlfn.IFS(C8>=Refi_Origination_Date, 0, SED_Amort = 0, -D8 * SED_I_Adj, 1, IPMT(SED_I_Adj,IF(B8 = 0, 1, B8),SED_Amort_Periods,SED_Orig_Loan_Amount)),0)} -> 0 | H8: =D8+F8 -> 0 | J8: =IFERROR(ROUNDUP((DATEDIF(NEW_Origination_Date,L8,"m")+1)/12,0),"") -> 1 | K8: =IF(L8<NEW_Begin_PMT,0, K7+1) -> 3 | L8: =EDATE(L7,1) -> 61 | M8: =IF(L8>EDATE(DATE(YEAR(NEW_Origination_Date)+ NEW_Amort, MONTH(NEW_Origination_Date), DAY(NEW_Origination_Date)),NEW_Interest_Only),0,Q7) -> 0 | N8: =O8+P8 -> 0 | O8: =IFERROR(IF(K8=0,0, PPMT(NEW_I_Adj,'Loan Amort Table'!K8,NEW_Amort_Periods,NEW_Orig_Loan_Amount)),0) -> 0 | P8: =IFERROR(IF(NEW_Amort = 0, -M8* NEW_I_Adj,IPMT(NEW_I_Adj,IF(K8 = 0, 1, K8),NEW_Amort_Periods,NEW_Orig_Loan_Amount)),0) -> 0 | Q8: =M8+O8 -> 0 | S8: =IFERROR(ROUNDUP((DATEDIF(Mezz_Origination_Date,U8,"m")+1)/12,0),"") -> 1 | T8: =IF(U8<Mezz_Begin_PMT,0, T7+1) -> 3 | U8: =EDATE(U7,1) -> 61 | V8: =IF(U8>EDATE(DATE(YEAR(Mezz_Origination_Date)+ Mezz_Amort, MONTH(Mezz_Origination_Date), DAY(Mezz_Origination_Date)),Mezz_Interest_Only),0,Z7) -> 0 | W8: =X8+Y8 -> 0 | X8: =IFERROR(IF(OR(T8=0, U8>=Refi_Origination_Date),0, PPMT(Mezz_I_Adj,'Loan Amort Table'!T8,Mezz_Amort_Periods,Mezz_Orig_Loan_Amount)),0) -> 0 | Y8: {=IFERROR(_xlfn.IFS(U8>=Refi_Origination_Date,0, Mezz_Amort = 0, -V8 * Mezz_I_Adj, 1, IPMT(Mezz_I_Adj,IF(T8 = 0, 1, T8),Mezz_Amort_Periods,Mezz_Orig_Loan_Amount)),0)} -> 0 | Z8: =V8+X8 -> 0 | AB8: =IFERROR(ROUNDUP((DATEDIF(Refi_Origination_Date,AD8,"m")+1)/12,0),"") -> 1 | AC8: =IF(AD8<Refi_Begin_PMT,0, AC7+1) -> 3 | AD8: =EDATE(AD7,1) -> 61 | AE8: =IF(AD8>EDATE(DATE(YEAR(Refi_Origination_Date)+ Refi_Amort, MONTH(Refi_Origination_Date), DAY(Refi_Origination_Date)),Refi_Interest_Only),0,AI7) -> 0 | AF8: =AG8+AH8 -> 0 | AG8: =IFERROR(IF(AC8=0,0, PPMT(Refi_I_Adj,'Loan Amort Table'!AC8,Refi_Amort_Periods,Refi_Orig_Loan_Amount)),0) -> 0 | AH8: =IFERROR(IF(Refi_Amort = 0, -AE8 * Refi_I_Adj, IPMT(Refi_I_Adj,IF(AC8 = 0, 1, AC8),Refi_Amort_Periods,Refi_Orig_Loan_Amount)),0) -> 0 | AI8: =AE8+AG8 -> 0
A9: =IFERROR(ROUNDUP((DATEDIF(SED_Origination_Date,C9,"m")+1)/12,0),"") -> 1 | B9: =IF(C9<SED_Begin_PMT,0, B8+1) -> 4 | C9: =EDATE(C8,1) -> 92 | D9: =IF(C9>EDATE(DATE(YEAR(SED_Origination_Date)+ SED_Amort, MONTH(SED_Origination_Date), DAY(SED_Origination_Date)),SED_Interest_Only),0,H8) -> 0 | E9: =F9+G9 -> 0 | F9: =IFERROR(IF(OR(B9=0, C9>=Refi_Origination_Date),0, PPMT(SED_I_Adj,'Loan Amort Table'!B9,SED_Amort_Periods,SED_Orig_Loan_Amount)),0) -> 0 | G9: {=IFERROR(_xlfn.IFS(C9>=Refi_Origination_Date, 0, SED_Amort = 0, -D9 * SED_I_Adj, 1, IPMT(SED_I_Adj,IF(B9 = 0, 1, B9),SED_Amort_Periods,SED_Orig_Loan_Amount)),0)} -> 0 | H9: =D9+F9 -> 0 | J9: =IFERROR(ROUNDUP((DATEDIF(NEW_Origination_Date,L9,"m")+1)/12,0),"") -> 1 | K9: =IF(L9<NEW_Begin_PMT,0, K8+1) -> 4 | L9: =EDATE(L8,1) -> 92 | M9: =IF(L9>EDATE(DATE(YEAR(NEW_Origination_Date)+ NEW_Amort, MONTH(NEW_Origination_Date), DAY(NEW_Origination_Date)),NEW_Interest_Only),0,Q8) -> 0 | N9: =O9+P9 -> 0 | O9: =IFERROR(IF(K9=0,0, PPMT(NEW_I_Adj,'Loan Amort Table'!K9,NEW_Amort_Periods,NEW_Orig_Loan_Amount)),0) -> 0 | P9: =IFERROR(IF(NEW_Amort = 0, -M9* NEW_I_Adj,IPMT(NEW_I_Adj,IF(K9 = 0, 1, K9),NEW_Amort_Periods,NEW_Orig_Loan_Amount)),0) -> 0 | Q9: =M9+O9 -> 0 | S9: =IFERROR(ROUNDUP((DATEDIF(Mezz_Origination_Date,U9,"m")+1)/12,0),"") -> 1 | T9: =IF(U9<Mezz_Begin_PMT,0, T8+1) -> 4 | U9: =EDATE(U8,1) -> 92 | V9: =IF(U9>EDATE(DATE(YEAR(Mezz_Origination_Date)+ Mezz_Amort, MONTH(Mezz_Origination_Date), DAY(Mezz_Origination_Date)),Mezz_Interest_Only),0,Z8) -> 0 | W9: =X9+Y9 -> 0 | X9: =IFERROR(IF(OR(T9=0, U9>=Refi_Origination_Date),0, PPMT(Mezz_I_Adj,'Loan Amort Table'!T9,Mezz_Amort_Periods,Mezz_Orig_Loan_Amount)),0) -> 0 | Y9: {=IFERROR(_xlfn.IFS(U9>=Refi_Origination_Date,0, Mezz_Amort = 0, -V9 * Mezz_I_Adj, 1, IPMT(Mezz_I_Adj,IF(T9 = 0, 1, T9),Mezz_Amort_Periods,Mezz_Orig_Loan_Amount)),0)} -> 0 | Z9: =V9+X9 -> 0 | AB9: =IFERROR(ROUNDUP((DATEDIF(Refi_Origination_Date,AD9,"m")+1)/12,0),"") -> 1 | AC9: =IF(AD9<Refi_Begin_PMT,0, AC8+1) -> 4 | AD9: =EDATE(AD8,1) -> 92 | AE9: =IF(AD9>EDATE(DATE(YEAR(Refi_Origination_Date)+ Refi_Amort, MONTH(Refi_Origination_Date), DAY(Refi_Origination_Date)),Refi_Interest_Only),0,AI8) -> 0 | AF9: =AG9+AH9 -> 0 | AG9: =IFERROR(IF(AC9=0,0, PPMT(Refi_I_Adj,'Loan Amort Table'!AC9,Refi_Amort_Periods,Refi_Orig_Loan_Amount)),0) -> 0 | AH9: =IFERROR(IF(Refi_Amort = 0, -AE9 * Refi_I_Adj, IPMT(Refi_I_Adj,IF(AC9 = 0, 1, AC9),Refi_Amort_Periods,Refi_Orig_Loan_Amount)),0) -> 0 | AI9: =AE9+AG9 -> 0
A10: =IFERROR(ROUNDUP((DATEDIF(SED_Origination_Date,C10,"m")+1)/12,0),"") -> 1 | B10: =IF(C10<SED_Begin_PMT,0, B9+1) -> 5 | C10: =EDATE(C9,1) -> 122 | D10: =IF(C10>EDATE(DATE(YEAR(SED_Origination_Date)+ SED_Amort, MONTH(SED_Origination_Date), DAY(SED_Origination_Date)),SED_Interest_Only),0,H9) -> 0 | E10: =F10+G10 -> 0 | F10: =IFERROR(IF(OR(B10=0, C10>=Refi_Origination_Date),0, PPMT(SED_I_Adj,'Loan Amort Table'!B10,SED_Amort_Periods,SED_Orig_Loan_Amount)),0) -> 0 | G10: {=IFERROR(_xlfn.IFS(C10>=Refi_Origination_Date, 0, SED_Amort = 0, -D10 * SED_I_Adj, 1, IPMT(SED_I_Adj,IF(B10 = 0, 1, B10),SED_Amort_Periods,SED_Orig_Loan_Amount)),0)} -> 0 | H10: =D10+F10 -> 0 | J10: =IFERROR(ROUNDUP((DATEDIF(NEW_Origination_Date,L10,"m")+1)/12,0),"") -> 1 | K10: =IF(L10<NEW_Begin_PMT,0, K9+1) -> 5 | L10: =EDATE(L9,1) -> 122 | M10: =IF(L10>EDATE(DATE(YEAR(NEW_Origination_Date)+ NEW_Amort, MONTH(NEW_Origination_Date), DAY(NEW_Origination_Date)),NEW_Interest_Only),0,Q9) -> 0 | N10: =O10+P10 -> 0 | O10: =IFERROR(IF(K10=0,0, PPMT(NEW_I_Adj,'Loan Amort Table'!K10,NEW_Amort_Periods,NEW_Orig_Loan_Amount)),0) -> 0 | P10: =IFERROR(IF(NEW_Amort = 0, -M10* NEW_I_Adj,IPMT(NEW_I_Adj,IF(K10 = 0, 1, K10),NEW_Amort_Periods,NEW_Orig_Loan_Amount)),0) -> 0 | Q10: =M10+O10 -> 0 | S10: =IFERROR(ROUNDUP((DATEDIF(Mezz_Origination_Date,U10,"m")+1)/12,0),"") -> 1 | T10: =IF(U10<Mezz_Begin_PMT,0, T9+1) -> 5 | U10: =EDATE(U9,1) -> 122 | V10: =IF(U10>EDATE(DATE(YEAR(Mezz_Origination_Date)+ Mezz_Amort, MONTH(Mezz_Origination_Date), DAY(Mezz_Origination_Date)),Mezz_Interest_Only),0,Z9) -> 0 | W10: =X10+Y10 -> 0 | X10: =IFERROR(IF(OR(T10=0, U10>=Refi_Origination_Date),0, PPMT(Mezz_I_Adj,'Loan Amort Table'!T10,Mezz_Amort_Periods,Mezz_Orig_Loan_Amount)),0) -> 0 | Y10: {=IFERROR(_xlfn.IFS(U10>=Refi_Origination_Date,0, Mezz_Amort = 0, -V10 * Mezz_I_Adj, 1, IPMT(Mezz_I_Adj,IF(T10 = 0, 1, T10),Mezz_Amort_Periods,Mezz_Orig_Loan_Amount)),0)} -> 0 | Z10: =V10+X10 -> 0 | AB10: =IFERROR(ROUNDUP((DATEDIF(Refi_Origination_Date,AD10,"m")+1)/12,0),"") -> 1 | AC10: =IF(AD10<Refi_Begin_PMT,0, AC9+1) -> 5 | AD10: =EDATE(AD9,1) -> 122 | AE10: =IF(AD10>EDATE(DATE(YEAR(Refi_Origination_Date)+ Refi_Amort, MONTH(Refi_Origination_Date), DAY(Refi_Origination_Date)),Refi_Interest_Only),0,AI9) -> 0 | AF10: =AG10+AH10 -> 0 | AG10: =IFERROR(IF(AC10=0,0, PPMT(Refi_I_Adj,'Loan Amort Table'!AC10,Refi_Amort_Periods,Refi_Orig_Loan_Amount)),0) -> 0 | AH10: =IFERROR(IF(Refi_Amort = 0, -AE10 * Refi_I_Adj, IPMT(Refi_I_Adj,IF(AC10 = 0, 1, AC10),Refi_Amort_Periods,Refi_Orig_Loan_Amount)),0) -> 0 | AI10: =AE10+AG10 -> 0
A11: =IFERROR(ROUNDUP((DATEDIF(SED_Origination_Date,C11,"m")+1)/12,0),"") -> 1 | B11: =IF(C11<SED_Begin_PMT,0, B10+1) -> 6 | C11: =EDATE(C10,1) -> 153 | D11: =IF(C11>EDATE(DATE(YEAR(SED_Origination_Date)+ SED_Amort, MONTH(SED_Origination_Date), DAY(SED_Origination_Date)),SED_Interest_Only),0,H10) -> 0 | E11: =F11+G11 -> 0 | F11: =IFERROR(IF(OR(B11=0, C11>=Refi_Origination_Date),0, PPMT(SED_I_Adj,'Loan Amort Table'!B11,SED_Amort_Periods,SED_Orig_Loan_Amount)),0) -> 0 | G11: {=IFERROR(_xlfn.IFS(C11>=Refi_Origination_Date, 0, SED_Amort = 0, -D11 * SED_I_Adj, 1, IPMT(SED_I_Adj,IF(B11 = 0, 1, B11),SED_Amort_Periods,SED_Orig_Loan_Amount)),0)} -> 0 | H11: =D11+F11 -> 0 | J11: =IFERROR(ROUNDUP((DATEDIF(NEW_Origination_Date,L11,"m")+1)/12,0),"") -> 1 | K11: =IF(L11<NEW_Begin_PMT,0, K10+1) -> 6 | L11: =EDATE(L10,1) -> 153 | M11: =IF(L11>EDATE(DATE(YEAR(NEW_Origination_Date)+ NEW_Amort, MONTH(NEW_Origination_Date), DAY(NEW_Origination_Date)),NEW_Interest_Only),0,Q10) -> 0 | N11: =O11+P11 -> 0 | O11: =IFERROR(IF(K11=0,0, PPMT(NEW_I_Adj,'Loan Amort Table'!K11,NEW_Amort_Periods,NEW_Orig_Loan_Amount)),0) -> 0 | P11: =IFERROR(IF(NEW_Amort = 0, -M11* NEW_I_Adj,IPMT(NEW_I_Adj,IF(K11 = 0, 1, K11),NEW_Amort_Periods,NEW_Orig_Loan_Amount)),0) -> 0 | Q11: =M11+O11 -> 0 | S11: =IFERROR(ROUNDUP((DATEDIF(Mezz_Origination_Date,U11,"m")+1)/12,0),"") -> 1 | T11: =IF(U11<Mezz_Begin_PMT,0, T10+1) -> 6 | U11: =EDATE(U10,1) -> 153 | V11: =IF(U11>EDATE(DATE(YEAR(Mezz_Origination_Date)+ Mezz_Amort, MONTH(Mezz_Origination_Date), DAY(Mezz_Origination_Date)),Mezz_Interest_Only),0,Z10) -> 0 | W11: =X11+Y11 -> 0 | X11: =IFERROR(IF(OR(T11=0, U11>=Refi_Origination_Date),0, PPMT(Mezz_I_Adj,'Loan Amort Table'!T11,Mezz_Amort_Periods,Mezz_Orig_Loan_Amount)),0) -> 0 | Y11: {=IFERROR(_xlfn.IFS(U11>=Refi_Origination_Date,0, Mezz_Amort = 0, -V11 * Mezz_I_Adj, 1, IPMT(Mezz_I_Adj,IF(T11 = 0, 1, T11),Mezz_Amort_Periods,Mezz_Orig_Loan_Amount)),0)} -> 0 | Z11: =V11+X11 -> 0 | AB11: =IFERROR(ROUNDUP((DATEDIF(Refi_Origination_Date,AD11,"m")+1)/12,0),"") -> 1 | AC11: =IF(AD11<Refi_Begin_PMT,0, AC10+1) -> 6 | AD11: =EDATE(AD10,1) -> 153 | AE11: =IF(AD11>EDATE(DATE(YEAR(Refi_Origination_Date)+ Refi_Amort, MONTH(Refi_Origination_Date), DAY(Refi_Origination_Date)),Refi_Interest_Only),0,AI10) -> 0 | AF11: =AG11+AH11 -> 0 | AG11: =IFERROR(IF(AC11=0,0, PPMT(Refi_I_Adj,'Loan Amort Table'!AC11,Refi_Amort_Periods,Refi_Orig_Loan_Amount)),0) -> 0 | AH11: =IFERROR(IF(Refi_Amort = 0, -AE11 * Refi_I_Adj, IPMT(Refi_I_Adj,IF(AC11 = 0, 1, AC11),Refi_Amort_Periods,Refi_Orig_Loan_Amount)),0) -> 0 | AI11: =AE11+AG11 -> 0
A12: =IFERROR(ROUNDUP((DATEDIF(SED_Origination_Date,C12,"m")+1)/12,0),"") -> 1 | B12: =IF(C12<SED_Begin_PMT,0, B11+1) -> 7 | C12: =EDATE(C11,1) -> 183 | D12: =IF(C12>EDATE(DATE(YEAR(SED_Origination_Date)+ SED_Amort, MONTH(SED_Origination_Date), DAY(SED_Origination_Date)),SED_Interest_Only),0,H11) -> 0 | E12: =F12+G12 -> 0 | F12: =IFERROR(IF(OR(B12=0, C12>=Refi_Origination_Date),0, PPMT(SED_I_Adj,'Loan Amort Table'!B12,SED_Amort_Periods,SED_Orig_Loan_Amount)),0) -> 0 | G12: {=IFERROR(_xlfn.IFS(C12>=Refi_Origination_Date, 0, SED_Amort = 0, -D12 * SED_I_Adj, 1, IPMT(SED_I_Adj,IF(B12 = 0, 1, B12),SED_Amort_Periods,SED_Orig_Loan_Amount)),0)} -> 0 | H12: =D12+F12 -> 0 | J12: =IFERROR(ROUNDUP((DATEDIF(NEW_Origination_Date,L12,"m")+1)/12,0),"") -> 1 | K12: =IF(L12<NEW_Begin_PMT,0, K11+1) -> 7 | L12: =EDATE(L11,1) -> 183 | M12: =IF(L12>EDATE(DATE(YEAR(NEW_Origination_Date)+ NEW_Amort, MONTH(NEW_Origination_Date), DAY(NEW_Origination_Date)),NEW_Interest_Only),0,Q11) -> 0 | N12: =O12+P12 -> 0 | O12: =IFERROR(IF(K12=0,0, PPMT(NEW_I_Adj,'Loan Amort Table'!K12,NEW_Amort_Periods,NEW_Orig_Loan_Amount)),0) -> 0 | P12: =IFERROR(IF(NEW_Amort = 0, -M12* NEW_I_Adj,IPMT(NEW_I_Adj,IF(K12 = 0, 1, K12),NEW_Amort_Periods,NEW_Orig_Loan_Amount)),0) -> 0 | Q12: =M12+O12 -> 0 | S12: =IFERROR(ROUNDUP((DATEDIF(Mezz_Origination_Date,U12,"m")+1)/12,0),"") -> 1 | T12: =IF(U12<Mezz_Begin_PMT,0, T11+1) -> 7 | U12: =EDATE(U11,1) -> 183 | V12: =IF(U12>EDATE(DATE(YEAR(Mezz_Origination_Date)+ Mezz_Amort, MONTH(Mezz_Origination_Date), DAY(Mezz_Origination_Date)),Mezz_Interest_Only),0,Z11) -> 0 | W12: =X12+Y12 -> 0 | X12: =IFERROR(IF(OR(T12=0, U12>=Refi_Origination_Date),0, PPMT(Mezz_I_Adj,'Loan Amort Table'!T12,Mezz_Amort_Periods,Mezz_Orig_Loan_Amount)),0) -> 0 | Y12: {=IFERROR(_xlfn.IFS(U12>=Refi_Origination_Date,0, Mezz_Amort = 0, -V12 * Mezz_I_Adj, 1, IPMT(Mezz_I_Adj,IF(T12 = 0, 1, T12),Mezz_Amort_Periods,Mezz_Orig_Loan_Amount)),0)} -> 0 | Z12: =V12+X12 -> 0 | AB12: =IFERROR(ROUNDUP((DATEDIF(Refi_Origination_Date,AD12,"m")+1)/12,0),"") -> 1 | AC12: =IF(AD12<Refi_Begin_PMT,0, AC11+1) -> 7 | AD12: =EDATE(AD11,1) -> 183 | AE12: =IF(AD12>EDATE(DATE(YEAR(Refi_Origination_Date)+ Refi_Amort, MONTH(Refi_Origination_Date), DAY(Refi_Origination_Date)),Refi_Interest_Only),0,AI11) -> 0 | AF12: =AG12+AH12 -> 0 | AG12: =IFERROR(IF(AC12=0,0, PPMT(Refi_I_Adj,'Loan Amort Table'!AC12,Refi_Amort_Periods,Refi_Orig_Loan_Amount)),0) -> 0 | AH12: =IFERROR(IF(Refi_Amort = 0, -AE12 * Refi_I_Adj, IPMT(Refi_I_Adj,IF(AC12 = 0, 1, AC12),Refi_Amort_Periods,Refi_Orig_Loan_Amount)),0) -> 0 | AI12: =AE12+AG12 -> 0
A13: =IFERROR(ROUNDUP((DATEDIF(SED_Origination_Date,C13,"m")+1)/12,0),"") -> 1 | B13: =IF(C13<SED_Begin_PMT,0, B12+1) -> 8 | C13: =EDATE(C12,1) -> 214 | D13: =IF(C13>EDATE(DATE(YEAR(SED_Origination_Date)+ SED_Amort, MONTH(SED_Origination_Date), DAY(SED_Origination_Date)),SED_Interest_Only),0,H12) -> 0 | E13: =F13+G13 -> 0 | F13: =IFERROR(IF(OR(B13=0, C13>=Refi_Origination_Date),0, PPMT(SED_I_Adj,'Loan Amort Table'!B13,SED_Amort_Periods,SED_Orig_Loan_Amount)),0) -> 0 | G13: {=IFERROR(_xlfn.IFS(C13>=Refi_Origination_Date, 0, SED_Amort = 0, -D13 * SED_I_Adj, 1, IPMT(SED_I_Adj,IF(B13 = 0, 1, B13),SED_Amort_Periods,SED_Orig_Loan_Amount)),0)} -> 0 | H13: =D13+F13 -> 0 | J13: =IFERROR(ROUNDUP((DATEDIF(NEW_Origination_Date,L13,"m")+1)/12,0),"") -> 1 | K13: =IF(L13<NEW_Begin_PMT,0, K12+1) -> 8 | L13: =EDATE(L12,1) -> 214 | M13: =IF(L13>EDATE(DATE(YEAR(NEW_Origination_Date)+ NEW_Amort, MONTH(NEW_Origination_Date), DAY(NEW_Origination_Date)),NEW_Interest_Only),0,Q12) -> 0 | N13: =O13+P13 -> 0 | O13: =IFERROR(IF(K13=0,0, PPMT(NEW_I_Adj,'Loan Amort Table'!K13,NEW_Amort_Periods,NEW_Orig_Loan_Amount)),0) -> 0 | P13: =IFERROR(IF(NEW_Amort = 0, -M13* NEW_I_Adj,IPMT(NEW_I_Adj,IF(K13 = 0, 1, K13),NEW_Amort_Periods,NEW_Orig_Loan_Amount)),0) -> 0 | Q13: =M13+O13 -> 0 | S13: =IFERROR(ROUNDUP((DATEDIF(Mezz_Origination_Date,U13,"m")+1)/12,0),"") -> 1 | T13: =IF(U13<Mezz_Begin_PMT,0, T12+1) -> 8 | U13: =EDATE(U12,1) -> 214 | V13: =IF(U13>EDATE(DATE(YEAR(Mezz_Origination_Date)+ Mezz_Amort, MONTH(Mezz_Origination_Date), DAY(Mezz_Origination_Date)),Mezz_Interest_Only),0,Z12) -> 0 | W13: =X13+Y13 -> 0 | X13: =IFERROR(IF(OR(T13=0, U13>=Refi_Origination_Date),0, PPMT(Mezz_I_Adj,'Loan Amort Table'!T13,Mezz_Amort_Periods,Mezz_Orig_Loan_Amount)),0) -> 0 | Y13: {=IFERROR(_xlfn.IFS(U13>=Refi_Origination_Date,0, Mezz_Amort = 0, -V13 * Mezz_I_Adj, 1, IPMT(Mezz_I_Adj,IF(T13 = 0, 1, T13),Mezz_Amort_Periods,Mezz_Orig_Loan_Amount)),0)} -> 0 | Z13: =V13+X13 -> 0 | AB13: =IFERROR(ROUNDUP((DATEDIF(Refi_Origination_Date,AD13,"m")+1)/12,0),"") -> 1 | AC13: =IF(AD13<Refi_Begin_PMT,0, AC12+1) -> 8 | AD13: =EDATE(AD12,1) -> 214 | AE13: =IF(AD13>EDATE(DATE(YEAR(Refi_Origination_Date)+ Refi_Amort, MONTH(Refi_Origination_Date), DAY(Refi_Origination_Date)),Refi_Interest_Only),0,AI12) -> 0 | AF13: =AG13+AH13 -> 0 | AG13: =IFERROR(IF(AC13=0,0, PPMT(Refi_I_Adj,'Loan Amort Table'!AC13,Refi_Amort_Periods,Refi_Orig_Loan_Amount)),0) -> 0 | AH13: =IFERROR(IF(Refi_Amort = 0, -AE13 * Refi_I_Adj, IPMT(Refi_I_Adj,IF(AC13 = 0, 1, AC13),Refi_Amort_Periods,Refi_Orig_Loan_Amount)),0) -> 0 | AI13: =AE13+AG13 -> 0
A14: =IFERROR(ROUNDUP((DATEDIF(SED_Origination_Date,C14,"m")+1)/12,0),"") -> 1 | B14: =IF(C14<SED_Begin_PMT,0, B13+1) -> 9 | C14: =EDATE(C13,1) -> 245 | D14: =IF(C14>EDATE(DATE(YEAR(SED_Origination_Date)+ SED_Amort, MONTH(SED_Origination_Date), DAY(SED_Origination_Date)),SED_Interest_Only),0,H13) -> 0 | E14: =F14+G14 -> 0 | F14: =IFERROR(IF(OR(B14=0, C14>=Refi_Origination_Date),0, PPMT(SED_I_Adj,'Loan Amort Table'!B14,SED_Amort_Periods,SED_Orig_Loan_Amount)),0) -> 0 | G14: {=IFERROR(_xlfn.IFS(C14>=Refi_Origination_Date, 0, SED_Amort = 0, -D14 * SED_I_Adj, 1, IPMT(SED_I_Adj,IF(B14 = 0, 1, B14),SED_Amort_Periods,SED_Orig_Loan_Amount)),0)} -> 0 | H14: =D14+F14 -> 0 | J14: =IFERROR(ROUNDUP((DATEDIF(NEW_Origination_Date,L14,"m")+1)/12,0),"") -> 1 | K14: =IF(L14<NEW_Begin_PMT,0, K13+1) -> 9 | L14: =EDATE(L13,1) -> 245 | M14: =IF(L14>EDATE(DATE(YEAR(NEW_Origination_Date)+ NEW_Amort, MONTH(NEW_Origination_Date), DAY(NEW_Origination_Date)),NEW_Interest_Only),0,Q13) -> 0 | N14: =O14+P14 -> 0 | O14: =IFERROR(IF(K14=0,0, PPMT(NEW_I_Adj,'Loan Amort Table'!K14,NEW_Amort_Periods,NEW_Orig_Loan_Amount)),0) -> 0 | P14: =IFERROR(IF(NEW_Amort = 0, -M14* NEW_I_Adj,IPMT(NEW_I_Adj,IF(K14 = 0, 1, K14),NEW_Amort_Periods,NEW_Orig_Loan_Amount)),0) -> 0 | Q14: =M14+O14 -> 0 | S14: =IFERROR(ROUNDUP((DATEDIF(Mezz_Origination_Date,U14,"m")+1)/12,0),"") -> 1 | T14: =IF(U14<Mezz_Begin_PMT,0, T13+1) -> 9 | U14: =EDATE(U13,1) -> 245 | V14: =IF(U14>EDATE(DATE(YEAR(Mezz_Origination_Date)+ Mezz_Amort, MONTH(Mezz_Origination_Date), DAY(Mezz_Origination_Date)),Mezz_Interest_Only),0,Z13) -> 0 | W14: =X14+Y14 -> 0 | X14: =IFERROR(IF(OR(T14=0, U14>=Refi_Origination_Date),0, PPMT(Mezz_I_Adj,'Loan Amort Table'!T14,Mezz_Amort_Periods,Mezz_Orig_Loan_Amount)),0) -> 0 | Y14: {=IFERROR(_xlfn.IFS(U14>=Refi_Origination_Date,0, Mezz_Amort = 0, -V14 * Mezz_I_Adj, 1, IPMT(Mezz_I_Adj,IF(T14 = 0, 1, T14),Mezz_Amort_Periods,Mezz_Orig_Loan_Amount)),0)} -> 0 | Z14: =V14+X14 -> 0 | AB14: =IFERROR(ROUNDUP((DATEDIF(Refi_Origination_Date,AD14,"m")+1)/12,0),"") -> 1 | AC14: =IF(AD14<Refi_Begin_PMT,0, AC13+1) -> 9 | AD14: =EDATE(AD13,1) -> 245 | AE14: =IF(AD14>EDATE(DATE(YEAR(Refi_Origination_Date)+ Refi_Amort, MONTH(Refi_Origination_Date), DAY(Refi_Origination_Date)),Refi_Interest_Only),0,AI13) -> 0 | AF14: =AG14+AH14 -> 0 | AG14: =IFERROR(IF(AC14=0,0, PPMT(Refi_I_Adj,'Loan Amort Table'!AC14,Refi_Amort_Periods,Refi_Orig_Loan_Amount)),0) -> 0 | AH14: =IFERROR(IF(Refi_Amort = 0, -AE14 * Refi_I_Adj, IPMT(Refi_I_Adj,IF(AC14 = 0, 1, AC14),Refi_Amort_Periods,Refi_Orig_Loan_Amount)),0) -> 0 | AI14: =AE14+AG14 -> 0
A15: =IFERROR(ROUNDUP((DATEDIF(SED_Origination_Date,C15,"m")+1)/12,0),"") -> 1 | B15: =IF(C15<SED_Begin_PMT,0, B14+1) -> 10 | C15: =EDATE(C14,1) -> 275 | D15: =IF(C15>EDATE(DATE(YEAR(SED_Origination_Date)+ SED_Amort, MONTH(SED_Origination_Date), DAY(SED_Origination_Date)),SED_Interest_Only),0,H14) -> 0 | E15: =F15+G15 -> 0 | F15: =IFERROR(IF(OR(B15=0, C15>=Refi_Origination_Date),0, PPMT(SED_I_Adj,'Loan Amort Table'!B15,SED_Amort_Periods,SED_Orig_Loan_Amount)),0) -> 0 | G15: {=IFERROR(_xlfn.IFS(C15>=Refi_Origination_Date, 0, SED_Amort = 0, -D15 * SED_I_Adj, 1, IPMT(SED_I_Adj,IF(B15 = 0, 1, B15),SED_Amort_Periods,SED_Orig_Loan_Amount)),0)} -> 0 | H15: =D15+F15 -> 0 | J15: =IFERROR(ROUNDUP((DATEDIF(NEW_Origination_Date,L15,"m")+1)/12,0),"") -> 1 | K15: =IF(L15<NEW_Begin_PMT,0, K14+1) -> 10 | L15: =EDATE(L14,1) -> 275 | M15: =IF(L15>EDATE(DATE(YEAR(NEW_Origination_Date)+ NEW_Amort, MONTH(NEW_Origination_Date), DAY(NEW_Origination_Date)),NEW_Interest_Only),0,Q14) -> 0 | N15: =O15+P15 -> 0 | O15: =IFERROR(IF(K15=0,0, PPMT(NEW_I_Adj,'Loan Amort Table'!K15,NEW_Amort_Periods,NEW_Orig_Loan_Amount)),0) -> 0 | P15: =IFERROR(IF(NEW_Amort = 0, -M15* NEW_I_Adj,IPMT(NEW_I_Adj,IF(K15 = 0, 1, K15),NEW_Amort_Periods,NEW_Orig_Loan_Amount)),0) -> 0 | Q15: =M15+O15 -> 0 | S15: =IFERROR(ROUNDUP((DATEDIF(Mezz_Origination_Date,U15,"m")+1)/12,0),"") -> 1 | T15: =IF(U15<Mezz_Begin_PMT,0, T14+1) -> 10 | U15: =EDATE(U14,1) -> 275 | V15: =IF(U15>EDATE(DATE(YEAR(Mezz_Origination_Date)+ Mezz_Amort, MONTH(Mezz_Origination_Date), DAY(Mezz_Origination_Date)),Mezz_Interest_Only),0,Z14) -> 0 | W15: =X15+Y15 -> 0 | X15: =IFERROR(IF(OR(T15=0, U15>=Refi_Origination_Date),0, PPMT(Mezz_I_Adj,'Loan Amort Table'!T15,Mezz_Amort_Periods,Mezz_Orig_Loan_Amount)),0) -> 0 | Y15: {=IFERROR(_xlfn.IFS(U15>=Refi_Origination_Date,0, Mezz_Amort = 0, -V15 * Mezz_I_Adj, 1, IPMT(Mezz_I_Adj,IF(T15 = 0, 1, T15),Mezz_Amort_Periods,Mezz_Orig_Loan_Amount)),0)} -> 0 | Z15: =V15+X15 -> 0 | AB15: =IFERROR(ROUNDUP((DATEDIF(Refi_Origination_Date,AD15,"m")+1)/12,0),"") -> 1 | AC15: =IF(AD15<Refi_Begin_PMT,0, AC14+1) -> 10 | AD15: =EDATE(AD14,1) -> 275 | AE15: =IF(AD15>EDATE(DATE(YEAR(Refi_Origination_Date)+ Refi_Amort, MONTH(Refi_Origination_Date), DAY(Refi_Origination_Date)),Refi_Interest_Only),0,AI14) -> 0 | AF15: =AG15+AH15 -> 0 | AG15: =IFERROR(IF(AC15=0,0, PPMT(Refi_I_Adj,'Loan Amort Table'!AC15,Refi_Amort_Periods,Refi_Orig_Loan_Amount)),0) -> 0 | AH15: =IFERROR(IF(Refi_Amort = 0, -AE15 * Refi_I_Adj, IPMT(Refi_I_Adj,IF(AC15 = 0, 1, AC15),Refi_Amort_Periods,Refi_Orig_Loan_Amount)),0) -> 0 | AI15: =AE15+AG15 -> 0
A16: =IFERROR(ROUNDUP((DATEDIF(SED_Origination_Date,C16,"m")+1)/12,0),"") -> 1 | B16: =IF(C16<SED_Begin_PMT,0, B15+1) -> 11 | C16: =EDATE(C15,1) -> 306 | D16: =IF(C16>EDATE(DATE(YEAR(SED_Origination_Date)+ SED_Amort, MONTH(SED_Origination_Date), DAY(SED_Origination_Date)),SED_Interest_Only),0,H15) -> 0 | E16: =F16+G16 -> 0 | F16: =IFERROR(IF(OR(B16=0, C16>=Refi_Origination_Date),0, PPMT(SED_I_Adj,'Loan Amort Table'!B16,SED_Amort_Periods,SED_Orig_Loan_Amount)),0) -> 0 | G16: {=IFERROR(_xlfn.IFS(C16>=Refi_Origination_Date, 0, SED_Amort = 0, -D16 * SED_I_Adj, 1, IPMT(SED_I_Adj,IF(B16 = 0, 1, B16),SED_Amort_Periods,SED_Orig_Loan_Amount)),0)} -> 0 | H16: =D16+F16 -> 0 | J16: =IFERROR(ROUNDUP((DATEDIF(NEW_Origination_Date,L16,"m")+1)/12,0),"") -> 1 | K16: =IF(L16<NEW_Begin_PMT,0, K15+1) -> 11 | L16: =EDATE(L15,1) -> 306 | M16: =IF(L16>EDATE(DATE(YEAR(NEW_Origination_Date)+ NEW_Amort, MONTH(NEW_Origination_Date), DAY(NEW_Origination_Date)),NEW_Interest_Only),0,Q15) -> 0 | N16: =O16+P16 -> 0 | O16: =IFERROR(IF(K16=0,0, PPMT(NEW_I_Adj,'Loan Amort Table'!K16,NEW_Amort_Periods,NEW_Orig_Loan_Amount)),0) -> 0 | P16: =IFERROR(IF(NEW_Amort = 0, -M16* NEW_I_Adj,IPMT(NEW_I_Adj,IF(K16 = 0, 1, K16),NEW_Amort_Periods,NEW_Orig_Loan_Amount)),0) -> 0 | Q16: =M16+O16 -> 0 | S16: =IFERROR(ROUNDUP((DATEDIF(Mezz_Origination_Date,U16,"m")+1)/12,0),"") -> 1 | T16: =IF(U16<Mezz_Begin_PMT,0, T15+1) -> 11 | U16: =EDATE(U15,1) -> 306 | V16: =IF(U16>EDATE(DATE(YEAR(Mezz_Origination_Date)+ Mezz_Amort, MONTH(Mezz_Origination_Date), DAY(Mezz_Origination_Date)),Mezz_Interest_Only),0,Z15) -> 0 | W16: =X16+Y16 -> 0 | X16: =IFERROR(IF(OR(T16=0, U16>=Refi_Origination_Date),0, PPMT(Mezz_I_Adj,'Loan Amort Table'!T16,Mezz_Amort_Periods,Mezz_Orig_Loan_Amount)),0) -> 0 | Y16: {=IFERROR(_xlfn.IFS(U16>=Refi_Origination_Date,0, Mezz_Amort = 0, -V16 * Mezz_I_Adj, 1, IPMT(Mezz_I_Adj,IF(T16 = 0, 1, T16),Mezz_Amort_Periods,Mezz_Orig_Loan_Amount)),0)} -> 0 | Z16: =V16+X16 -> 0 | AB16: =IFERROR(ROUNDUP((DATEDIF(Refi_Origination_Date,AD16,"m")+1)/12,0),"") -> 1 | AC16: =IF(AD16<Refi_Begin_PMT,0, AC15+1) -> 11 | AD16: =EDATE(AD15,1) -> 306 | AE16: =IF(AD16>EDATE(DATE(YEAR(Refi_Origination_Date)+ Refi_Amort, MONTH(Refi_Origination_Date), DAY(Refi_Origination_Date)),Refi_Interest_Only),0,AI15) -> 0 | AF16: =AG16+AH16 -> 0 | AG16: =IFERROR(IF(AC16=0,0, PPMT(Refi_I_Adj,'Loan Amort Table'!AC16,Refi_Amort_Periods,Refi_Orig_Loan_Amount)),0) -> 0 | AH16: =IFERROR(IF(Refi_Amort = 0, -AE16 * Refi_I_Adj, IPMT(Refi_I_Adj,IF(AC16 = 0, 1, AC16),Refi_Amort_Periods,Refi_Orig_Loan_Amount)),0) -> 0 | AI16: =AE16+AG16 -> 0
A17: =IFERROR(ROUNDUP((DATEDIF(SED_Origination_Date,C17,"m")+1)/12,0),"") -> 1 | B17: =IF(C17<SED_Begin_PMT,0, B16+1) -> 12 | C17: =EDATE(C16,1) -> 336 | D17: =IF(C17>EDATE(DATE(YEAR(SED_Origination_Date)+ SED_Amort, MONTH(SED_Origination_Date), DAY(SED_Origination_Date)),SED_Interest_Only),0,H16) -> 0 | E17: =F17+G17 -> 0 | F17: =IFERROR(IF(OR(B17=0, C17>=Refi_Origination_Date),0, PPMT(SED_I_Adj,'Loan Amort Table'!B17,SED_Amort_Periods,SED_Orig_Loan_Amount)),0) -> 0 | G17: {=IFERROR(_xlfn.IFS(C17>=Refi_Origination_Date, 0, SED_Amort = 0, -D17 * SED_I_Adj, 1, IPMT(SED_I_Adj,IF(B17 = 0, 1, B17),SED_Amort_Periods,SED_Orig_Loan_Amount)),0)} -> 0 | H17: =D17+F17 -> 0 | J17: =IFERROR(ROUNDUP((DATEDIF(NEW_Origination_Date,L17,"m")+1)/12,0),"") -> 1 | K17: =IF(L17<NEW_Begin_PMT,0, K16+1) -> 12 | L17: =EDATE(L16,1) -> 336 | M17: =IF(L17>EDATE(DATE(YEAR(NEW_Origination_Date)+ NEW_Amort, MONTH(NEW_Origination_Date), DAY(NEW_Origination_Date)),NEW_Interest_Only),0,Q16) -> 0 | N17: =O17+P17 -> 0 | O17: =IFERROR(IF(K17=0,0, PPMT(NEW_I_Adj,'Loan Amort Table'!K17,NEW_Amort_Periods,NEW_Orig_Loan_Amount)),0) -> 0 | P17: =IFERROR(IF(NEW_Amort = 0, -M17* NEW_I_Adj,IPMT(NEW_I_Adj,IF(K17 = 0, 1, K17),NEW_Amort_Periods,NEW_Orig_Loan_Amount)),0) -> 0 | Q17: =M17+O17 -> 0 | S17: =IFERROR(ROUNDUP((DATEDIF(Mezz_Origination_Date,U17,"m")+1)/12,0),"") -> 1 | T17: =IF(U17<Mezz_Begin_PMT,0, T16+1) -> 12 | U17: =EDATE(U16,1) -> 336 | V17: =IF(U17>EDATE(DATE(YEAR(Mezz_Origination_Date)+ Mezz_Amort, MONTH(Mezz_Origination_Date), DAY(Mezz_Origination_Date)),Mezz_Interest_Only),0,Z16) -> 0 | W17: =X17+Y17 -> 0 | X17: =IFERROR(IF(OR(T17=0, U17>=Refi_Origination_Date),0, PPMT(Mezz_I_Adj,'Loan Amort Table'!T17,Mezz_Amort_Periods,Mezz_Orig_Loan_Amount)),0) -> 0 | Y17: {=IFERROR(_xlfn.IFS(U17>=Refi_Origination_Date,0, Mezz_Amort = 0, -V17 * Mezz_I_Adj, 1, IPMT(Mezz_I_Adj,IF(T17 = 0, 1, T17),Mezz_Amort_Periods,Mezz_Orig_Loan_Amount)),0)} -> 0 | Z17: =V17+X17 -> 0 | AB17: =IFERROR(ROUNDUP((DATEDIF(Refi_Origination_Date,AD17,"m")+1)/12,0),"") -> 1 | AC17: =IF(AD17<Refi_Begin_PMT,0, AC16+1) -> 12 | AD17: =EDATE(AD16,1) -> 336 | AE17: =IF(AD17>EDATE(DATE(YEAR(Refi_Origination_Date)+ Refi_Amort, MONTH(Refi_Origination_Date), DAY(Refi_Origination_Date)),Refi_Interest_Only),0,AI16) -> 0 | AF17: =AG17+AH17 -> 0 | AG17: =IFERROR(IF(AC17=0,0, PPMT(Refi_I_Adj,'Loan Amort Table'!AC17,Refi_Amort_Periods,Refi_Orig_Loan_Amount)),0) -> 0 | AH17: =IFERROR(IF(Refi_Amort = 0, -AE17 * Refi_I_Adj, IPMT(Refi_I_Adj,IF(AC17 = 0, 1, AC17),Refi_Amort_Periods,Refi_Orig_Loan_Amount)),0) -> 0 | AI17: =AE17+AG17 -> 0
A18: =IFERROR(ROUNDUP((DATEDIF(SED_Origination_Date,C18,"m")+1)/12,0),"") -> 2 | B18: =IF(C18<SED_Begin_PMT,0, B17+1) -> 13 | C18: =EDATE(C17,1) -> 367 | D18: =IF(C18>EDATE(DATE(YEAR(SED_Origination_Date)+ SED_Amort, MONTH(SED_Origination_Date), DAY(SED_Origination_Date)),SED_Interest_Only),0,H17) -> 0 | E18: =F18+G18 -> 0 | F18: =IFERROR(IF(OR(B18=0, C18>=Refi_Origination_Date),0, PPMT(SED_I_Adj,'Loan Amort Table'!B18,SED_Amort_Periods,SED_Orig_Loan_Amount)),0) -> 0 | G18: {=IFERROR(_xlfn.IFS(C18>=Refi_Origination_Date, 0, SED_Amort = 0, -D18 * SED_I_Adj, 1, IPMT(SED_I_Adj,IF(B18 = 0, 1, B18),SED_Amort_Periods,SED_Orig_Loan_Amount)),0)} -> 0 | H18: =D18+F18 -> 0 | J18: =IFERROR(ROUNDUP((DATEDIF(NEW_Origination_Date,L18,"m")+1)/12,0),"") -> 2 | K18: =IF(L18<NEW_Begin_PMT,0, K17+1) -> 13 | L18: =EDATE(L17,1) -> 367 | M18: =IF(L18>EDATE(DATE(YEAR(NEW_Origination_Date)+ NEW_Amort, MONTH(NEW_Origination_Date), DAY(NEW_Origination_Date)),NEW_Interest_Only),0,Q17) -> 0 | N18: =O18+P18 -> 0 | O18: =IFERROR(IF(K18=0,0, PPMT(NEW_I_Adj,'Loan Amort Table'!K18,NEW_Amort_Periods,NEW_Orig_Loan_Amount)),0) -> 0 | P18: =IFERROR(IF(NEW_Amort = 0, -M18* NEW_I_Adj,IPMT(NEW_I_Adj,IF(K18 = 0, 1, K18),NEW_Amort_Periods,NEW_Orig_Loan_Amount)),0) -> 0 | Q18: =M18+O18 -> 0 | S18: =IFERROR(ROUNDUP((DATEDIF(Mezz_Origination_Date,U18,"m")+1)/12,0),"") -> 2 | T18: =IF(U18<Mezz_Begin_PMT,0, T17+1) -> 13 | U18: =EDATE(U17,1) -> 367 | V18: =IF(U18>EDATE(DATE(YEAR(Mezz_Origination_Date)+ Mezz_Amort, MONTH(Mezz_Origination_Date), DAY(Mezz_Origination_Date)),Mezz_Interest_Only),0,Z17) -> 0 | W18: =X18+Y18 -> 0 | X18: =IFERROR(IF(OR(T18=0, U18>=Refi_Origination_Date),0, PPMT(Mezz_I_Adj,'Loan Amort Table'!T18,Mezz_Amort_Periods,Mezz_Orig_Loan_Amount)),0) -> 0 | Y18: {=IFERROR(_xlfn.IFS(U18>=Refi_Origination_Date,0, Mezz_Amort = 0, -V18 * Mezz_I_Adj, 1, IPMT(Mezz_I_Adj,IF(T18 = 0, 1, T18),Mezz_Amort_Periods,Mezz_Orig_Loan_Amount)),0)} -> 0 | Z18: =V18+X18 -> 0 | AB18: =IFERROR(ROUNDUP((DATEDIF(Refi_Origination_Date,AD18,"m")+1)/12,0),"") -> 2 | AC18: =IF(AD18<Refi_Begin_PMT,0, AC17+1) -> 13 | AD18: =EDATE(AD17,1) -> 367 | AE18: =IF(AD18>EDATE(DATE(YEAR(Refi_Origination_Date)+ Refi_Amort, MONTH(Refi_Origination_Date), DAY(Refi_Origination_Date)),Refi_Interest_Only),0,AI17) -> 0 | AF18: =AG18+AH18 -> 0 | AG18: =IFERROR(IF(AC18=0,0, PPMT(Refi_I_Adj,'Loan Amort Table'!AC18,Refi_Amort_Periods,Refi_Orig_Loan_Amount)),0) -> 0 | AH18: =IFERROR(IF(Refi_Amort = 0, -AE18 * Refi_I_Adj, IPMT(Refi_I_Adj,IF(AC18 = 0, 1, AC18),Refi_Amort_Periods,Refi_Orig_Loan_Amount)),0) -> 0 | AI18: =AE18+AG18 -> 0
... A500: =IFERROR(ROUNDUP((DATEDIF(SED_Origination_Date,C500,"m")+1)/12,0),"") -> 42 | B500: =IF(C500<SED_Begin_PMT,0, B499+1) -> 495 | C500: =EDATE(C499,1) -> 15036 | D500: =IF(C500>EDATE(DATE(YEAR(SED_Origination_Date)+ SED_Amort, MONTH(SED_Origination_Date), DAY(SED_Origination_Date)),SED_Interest_Only),0,H499) -> 0 | E500: =F500+G500 -> 0 | F500: =IFERROR(IF(OR(B500=0, C500>=Refi_Origination_Date),0, PPMT(SED_I_Adj,'Loan Amort Table'!B500,SED_Amort_Periods,SED_Orig_Loan_Amount)),0) -> 0 | G500: {=IFERROR(_xlfn.IFS(C500>=Refi_Origination_Date, 0, SED_Amort = 0, -D500 * SED_I_Adj, 1, IPMT(SED_I_Adj,IF(B500 = 0, 1, B500),SED_Amort_Periods,SED_Orig_Loan_Amount)),0)} -> 0 | H500: =D500+F500 -> 0 | J500: =IFERROR(ROUNDUP((DATEDIF(NEW_Origination_Date,L500,"m")+1)/12,0),"") -> 42 | K500: =IF(L500<NEW_Begin_PMT,0, K499+1) -> 495 | L500: =EDATE(L499,1) -> 15036 | M500: =IF(L500>EDATE(DATE(YEAR(NEW_Origination_Date)+ NEW_Amort, MONTH(NEW_Origination_Date), DAY(NEW_Origination_Date)),NEW_Interest_Only),0,Q499) -> 0 | N500: =O500+P500 -> 0 | O500: =IFERROR(IF(K500=0,0, PPMT(NEW_I_Adj,'Loan Amort Table'!K500,NEW_Amort_Periods,NEW_Orig_Loan_Amount)),0) -> 0 | P500: =IFERROR(IF(NEW_Amort = 0, -M500* NEW_I_Adj,IPMT(NEW_I_Adj,IF(K500 = 0, 1, K500),NEW_Amort_Periods,NEW_Orig_Loan_Amount)),0) -> 0 | Q500: =M500+O500 -> 0 | S500: =IFERROR(ROUNDUP((DATEDIF(Mezz_Origination_Date,U500,"m")+1)/12,0),"") -> 42 | T500: =IF(U500<Mezz_Begin_PMT,0, T499+1) -> 495 | U500: =EDATE(U499,1) -> 15036 | V500: =IF(U500>EDATE(DATE(YEAR(Mezz_Origination_Date)+ Mezz_Amort, MONTH(Mezz_Origination_Date), DAY(Mezz_Origination_Date)),Mezz_Interest_Only),0,Z499) -> 0 | W500: =X500+Y500 -> 0 | X500: =IFERROR(IF(OR(T500=0, U500>=Refi_Origination_Date),0, PPMT(Mezz_I_Adj,'Loan Amort Table'!T500,Mezz_Amort_Periods,Mezz_Orig_Loan_Amount)),0) -> 0 | Y500: {=IFERROR(_xlfn.IFS(U500>=Refi_Origination_Date,0, Mezz_Amort = 0, -V500 * Mezz_I_Adj, 1, IPMT(Mezz_I_Adj,IF(T500 = 0, 1, T500),Mezz_Amort_Periods,Mezz_Orig_Loan_Amount)),0)} -> 0 | Z500: =V500+X500 -> 0 | AB500: =IFERROR(ROUNDUP((DATEDIF(Refi_Origination_Date,AD500,"m")+1)/12,0),"") -> 42 | AC500: =IF(AD500<Refi_Begin_PMT,0, AC499+1) -> 495 | AD500: =EDATE(AD499,1) -> 15036 | AE500: =IF(AD500>EDATE(DATE(YEAR(Refi_Origination_Date)+ Refi_Amort, MONTH(Refi_Origination_Date), DAY(Refi_Origination_Date)),Refi_Interest_Only),0,AI499) -> 0 | AF500: =AG500+AH500 -> 0 | AG500: =IFERROR(IF(AC500=0,0, PPMT(Refi_I_Adj,'Loan Amort Table'!AC500,Refi_Amort_Periods,Refi_Orig_Loan_Amount)),0) -> 0 | AH500: =IFERROR(IF(Refi_Amort = 0, -AE500 * Refi_I_Adj, IPMT(Refi_I_Adj,IF(AC500 = 0, 1, AC500),Refi_Amort_Periods,Refi_Orig_Loan_Amount)),0) -> 0 | AI500: =AE500+AG500 -> 0
A501: - | B501: - | C501: - | D501: - | E501: - | F501: - | G501: - | H501: - | I501: - | J501: - | K501: - | L501: - | M501: - | N501: - | O501: - | P501: - | Q501: - | S501: - | T501: - | U501: - | V501: - | W501: - | X501: - | Y501: - | Z501: - | AB501: - | AC501: - | AD501: - | AE501: - | AF501: - | AG501: - | AH501: - | AI501: -

Sheet Debt Input
D2: Buyer's Acquisition Financing
D3: Acquisition Financing Type | F3: Financed - New Loan
A4: Navigation Bar | D4: Mezzanine Financing | F4: Yes
A5: Input | D5: Include Refinancing? | F5: Yes
A6: Debt Input | D6: Seller's Existing Debt
A7: Rent Roll Input | D7: Does The Seller Have Existing Debt | F7: No
A12: Equity Returns Input
A13: Rent Roll Detail | D13: DEBT FINANCING | S13: Loan Cash Flow Summary
A14: Rent Roll Summary
A15: Operating Statement | F15: Existing Debt | H15: New Loan | J15: Mezzanine Loan | L15: Refinance Loan | N15: Refinance Loan Options | S15: Year | T15: =EDATE(DATE(YEAR(Date_of_Analysis)+1,MONTH(Date_of_Analysis),DAY(EOMONTH(Date_of_Analysis,0))),-1) -> 366 | U15: =DATE(YEAR(T15)+1, MONTH(T15), 1) -> 701 | V15: =DATE(YEAR(U15)+1, MONTH(U15), 1) -> 1066 | W15: =DATE(YEAR(V15)+1, MONTH(V15), 1) -> 1431 | X15: =DATE(YEAR(W15)+1, MONTH(W15), 1) -> 1797 | Y15: =DATE(YEAR(X15)+1, MONTH(X15), 1) -> 2162 | Z15: =DATE(YEAR(Y15)+1, MONTH(Y15), 1) -> 2527 | AA15: =DATE(YEAR(Z15)+1, MONTH(Z15), 1) -> 2892 | AB15: =DATE(YEAR(AA15)+1, MONTH(AA15), 1) -> 3258 | AC15: =DATE(YEAR(AB15)+1, MONTH(AB15), 1) -> 3623
A16: Notes
A17: Pricing Detail | D17: Loan Name/Type* | N17: Refinance Ballon Amount from Loan(s) | S17: Existing Debt
A18: Growth Rates | D18: Origination Date | H18: =Date_of_Analysis -> 0 | J18: =Date_of_Analysis -> 0 | N18: =IF(L15=0,"","As of "&TEXT(L15,"mmmm-yyyy")&":") -> As of Refinance Loan: | S18: Interest | T18: {=IF(Acq_Financing_Type_Switch = "Financed - Assumed Loan", IFERROR(SUM(_xlfn._xlws.FILTER(INDEX(SED_Table,0,7), (INDEX(SED_Table,0,3) <= T$15) * (INDEX(SED_Table,0,3) >= EDATE(T$15,-12)))),0),0)} -> 0 | U18: {=IF(Acq_Financing_Type_Switch = "Financed - Assumed Loan", IFERROR(SUM(_xlfn._xlws.FILTER(INDEX(SED_Table,0,7), (INDEX(SED_Table,0,3) <= U$15) * (INDEX(SED_Table,0,3) >= EDATE(U$15,-11)))),0),0)} -> 0 | V18: {=IF(Acq_Financing_Type_Switch = "Financed - Assumed Loan", IFERROR(SUM(_xlfn._xlws.FILTER(INDEX(SED_Table,0,7), (INDEX(SED_Table,0,3) <= V$15) * (INDEX(SED_Table,0,3) >= EDATE(V$15,-11)))),0),0)} -> 0 | W18: {=IF(Acq_Financing_Type_Switch = "Financed - Assumed Loan", IFERROR(SUM(_xlfn._xlws.FILTER(INDEX(SED_Table,0,7), (INDEX(SED_Table,0,3) <= W$15) * (INDEX(SED_Table,0,3) >= EDATE(W$15,-11)))),0),0)} -> 0 | X18: {=IF(Acq_Financing_Type_Switch = "Financed - Assumed Loan", IFERROR(SUM(_xlfn._xlws.FILTER(INDEX(SED_Table,0,7), (INDEX(SED_Table,0,3) <= X$15) * (INDEX(SED_Table,0,3) >= EDATE(X$15,-11)))),0),0)} -> 0 | Y18: {=IF(Acq_Financing_Type_Switch = "Financed - Assumed Loan", IFERROR(SUM(_xlfn._xlws.FILTER(INDEX(SED_Table,0,7), (INDEX(SED_Table,0,3) <= Y$15) * (INDEX(SED_Table,0,3) >= EDATE(Y$15,-11)))),0),0)} -> 0 | Z18: {=IF(Acq_Financing_Type_Switch = "Financed - Assumed Loan", IFERROR(SUM(_xlfn._xlws.FILTER(INDEX(SED_Table,0,7), (INDEX(SED_Table,0,3) <= Z$15) * (INDEX(SED_Table,0,3) >= EDATE(Z$15,-11)))),0),0)} -> 0 | AA18: {=IF(Acq_Financing_Type_Switch = "Financed - Assumed Loan", IFERROR(SUM(_xlfn._xlws.FILTER(INDEX(SED_Table,0,7), (INDEX(SED_Table,0,3) <= AA$15) * (INDEX(SED_Table,0,3) >= EDATE(AA$15,-11)))),0),0)} -> 0 | AB18: {=IF(Acq_Financing_Type_Switch = "Financed - Assumed Loan", IFERROR(SUM(_xlfn._xlws.FILTER(INDEX(SED_Table,0,7), (INDEX(SED_Table,0,3) <= AB$15) * (INDEX(SED_Table,0,3) >= EDATE(AB$15,-11)))),0),0)} -> 0 | AC18: {=IF(Acq_Financing_Type_Switch = "Financed - Assumed Loan", IFERROR(SUM(_xlfn._xlws.FILTER(INDEX(SED_Table,0,7), (INDEX(SED_Table,0,3) <= AC$15) * (INDEX(SED_Table,0,3) >= EDATE(AC$15,-11)))),0),0)} -> 0
A19: Cash Flow | D19: Original Loan Amount | H19: =NEW_Orig_Loan_Amount -> 0 | J19: =Mezz_Orig_Loan_Amount -> 0 | L19: =IFERROR(IF(N17="LTV using User Defined Cap Rate on NOI in Year of Refinance", L20*O19,Calculations!E9),0) | N19: =IF(L15=0,"","Asset Value") -> Asset Value | O19: =IFERROR(HLOOKUP(Refi_Origination_Date,'Cash Flow'!G4:P31,26)/O23,"") | S19: Principal | T19: {=IF(Acq_Financing_Type_Switch = "Financed - Assumed Loan", IFERROR(SUM(_xlfn._xlws.FILTER(INDEX(SED_Table,0,6), (INDEX(SED_Table,0,3) <= T$15) * (INDEX(SED_Table,0,3) >= EDATE(T$15,-12)))),0), 0)} -> 0 | U19: {=IF(Acq_Financing_Type_Switch = "Financed - Assumed Loan", IFERROR(SUM(_xlfn._xlws.FILTER(INDEX(SED_Table,0,6), (INDEX(SED_Table,0,3) <= U$15) * (INDEX(SED_Table,0,3) >= EDATE(U$15,-11)))),0), 0)} -> 0 | V19: {=IF(Acq_Financing_Type_Switch = "Financed - Assumed Loan", IFERROR(SUM(_xlfn._xlws.FILTER(INDEX(SED_Table,0,6), (INDEX(SED_Table,0,3) <= V$15) * (INDEX(SED_Table,0,3) >= EDATE(V$15,-11)))),0), 0)} -> 0 | W19: {=IF(Acq_Financing_Type_Switch = "Financed - Assumed Loan", IFERROR(SUM(_xlfn._xlws.FILTER(INDEX(SED_Table,0,6), (INDEX(SED_Table,0,3) <= W$15) * (INDEX(SED_Table,0,3) >= EDATE(W$15,-11)))),0), 0)} -> 0 | X19: {=IF(Acq_Financing_Type_Switch = "Financed - Assumed Loan", IFERROR(SUM(_xlfn._xlws.FILTER(INDEX(SED_Table,0,6), (INDEX(SED_Table,0,3) <= X$15) * (INDEX(SED_Table,0,3) >= EDATE(X$15,-11)))),0), 0)} -> 0 | Y19: {=IF(Acq_Financing_Type_Switch = "Financed - Assumed Loan", IFERROR(SUM(_xlfn._xlws.FILTER(INDEX(SED_Table,0,6), (INDEX(SED_Table,0,3) <= Y$15) * (INDEX(SED_Table,0,3) >= EDATE(Y$15,-11)))),0), 0)} -> 0 | Z19: {=IF(Acq_Financing_Type_Switch = "Financed - Assumed Loan", IFERROR(SUM(_xlfn._xlws.FILTER(INDEX(SED_Table,0,6), (INDEX(SED_Table,0,3) <= Z$15) * (INDEX(SED_Table,0,3) >= EDATE(Z$15,-11)))),0), 0)} -> 0 | AA19: {=IF(Acq_Financing_Type_Switch = "Financed - Assumed Loan", IFERROR(SUM(_xlfn._xlws.FILTER(INDEX(SED_Table,0,6), (INDEX(SED_Table,0,3) <= AA$15) * (INDEX(SED_Table,0,3) >= EDATE(AA$15,-11)))),0), 0)} -> 0 | AB19: {=IF(Acq_Financing_Type_Switch = "Financed - Assumed Loan", IFERROR(SUM(_xlfn._xlws.FILTER(INDEX(SED_Table,0,6), (INDEX(SED_Table,0,3) <= AB$15) * (INDEX(SED_Table,0,3) >= EDATE(AB$15,-11)))),0), 0)} -> 0 | AC19: {=IF(Acq_Financing_Type_Switch = "Financed - Assumed Loan", IFERROR(SUM(_xlfn._xlws.FILTER(INDEX(SED_Table,0,6), (INDEX(SED_Table,0,3) <= AC$15) * (INDEX(SED_Table,0,3) >= EDATE(AC$15,-11)))),0), 0)} -> 0
A20: Proposal Price IRR | D20: LTV | F20: =SED_Orig_Loan_Amount/sale_price -> #DIV/0! | N20: =IF(L15=0,"","Existing Debt") -> Existing Debt | O20: =Calculations!E9 | P20: =IFERROR(VLOOKUP(DATE(YEAR(Refi_Origination_Date),MONTH(Refi_Origination_Date),1),'Loan Amort Table'!AD6:AI500,6),"") -> 0 | S20: New Loan
A21: Equity Returns Options | D21: Loan Balance | F21: =SED_Loan_Balance -> 0 | H21: =NEW_Loan_Balance -> 0 | J21: =Mezz_Loan_Balance -> 0 | L21: =Refi_Loan_Balance -> 0 | N21: =IF(L15=0,"","LTV") -> LTV | O21: =IFERROR(O20/O19,"") | S21: Interest | T21: {=IF(Acq_Financing_Type_Switch = "Financed - New Loan", IFERROR(SUM(_xlfn._xlws.FILTER(INDEX(NEW_Table,0,7), (INDEX(NEW_Table,0,3) <= T$15) * (INDEX(NEW_Table,0,3) >= EDATE(T$15,-12)))),0), 0)} -> 0 | U21: {=IF(Acq_Financing_Type_Switch = "Financed - New Loan", IFERROR(SUM(_xlfn._xlws.FILTER(INDEX(NEW_Table,0,7), (INDEX(NEW_Table,0,3) <= U$15) * (INDEX(NEW_Table,0,3) >= EDATE(U$15,-11)))),0), 0)} -> 0 | V21: {=IF(Acq_Financing_Type_Switch = "Financed - New Loan", IFERROR(SUM(_xlfn._xlws.FILTER(INDEX(NEW_Table,0,7), (INDEX(NEW_Table,0,3) <= V$15) * (INDEX(NEW_Table,0,3) >= EDATE(V$15,-11)))),0), 0)} -> 0 | W21: {=IF(Acq_Financing_Type_Switch = "Financed - New Loan", IFERROR(SUM(_xlfn._xlws.FILTER(INDEX(NEW_Table,0,7), (INDEX(NEW_Table,0,3) <= W$15) * (INDEX(NEW_Table,0,3) >= EDATE(W$15,-11)))),0), 0)} -> 0 | X21: {=IF(Acq_Financing_Type_Switch = "Financed - New Loan", IFERROR(SUM(_xlfn._xlws.FILTER(INDEX(NEW_Table,0,7), (INDEX(NEW_Table,0,3) <= X$15) * (INDEX(NEW_Table,0,3) >= EDATE(X$15,-11)))),0), 0)} -> 0 | Y21: {=IF(Acq_Financing_Type_Switch = "Financed - New Loan", IFERROR(SUM(_xlfn._xlws.FILTER(INDEX(NEW_Table,0,7), (INDEX(NEW_Table,0,3) <= Y$15) * (INDEX(NEW_Table,0,3) >= EDATE(Y$15,-11)))),0), 0)} -> 0 | Z21: {=IF(Acq_Financing_Type_Switch = "Financed - New Loan", IFERROR(SUM(_xlfn._xlws.FILTER(INDEX(NEW_Table,0,7), (INDEX(NEW_Table,0,3) <= Z$15) * (INDEX(NEW_Table,0,3) >= EDATE(Z$15,-11)))),0), 0)} -> 0 | AA21: {=IF(Acq_Financing_Type_Switch = "Financed - New Loan", IFERROR(SUM(_xlfn._xlws.FILTER(INDEX(NEW_Table,0,7), (INDEX(NEW_Table,0,3) <= AA$15) * (INDEX(NEW_Table,0,3) >= EDATE(AA$15,-11)))),0), 0)} -> 0 | AB21: {=IF(Acq_Financing_Type_Switch = "Financed - New Loan", IFERROR(SUM(_xlfn._xlws.FILTER(INDEX(NEW_Table,0,7), (INDEX(NEW_Table,0,3) <= AB$15) * (INDEX(NEW_Table,0,3) >= EDATE(AB$15,-11)))),0), 0)} -> 0 | AC21: {=IF(Acq_Financing_Type_Switch = "Financed - New Loan", IFERROR(SUM(_xlfn._xlws.FILTER(INDEX(NEW_Table,0,7), (INDEX(NEW_Table,0,3) <= AC$15) * (INDEX(NEW_Table,0,3) >= EDATE(AC$15,-11)))),0), 0)} -> 0
A22: Equity Returns Chart | D22: Interest Rate | N22: =IF(L15=0,"","DSCR") -> DSCR | O22: =IFERROR(HLOOKUP(Refi_Origination_Date,'Cash Flow'!G4:P31,26)/-L31,"") | S22: Principal | T22: {=IF(Acq_Financing_Type_Switch = "Financed - New Loan", IFERROR(SUM(_xlfn._xlws.FILTER(INDEX(NEW_Table,0,6), (INDEX(NEW_Table,0,3) <= T$15) * (INDEX(NEW_Table,0,3) >= EDATE(T$15,-12)))),0), 0)} -> 0 | U22: {=IF(Acq_Financing_Type_Switch = "Financed - New Loan", IFERROR(SUM(_xlfn._xlws.FILTER(INDEX(NEW_Table,0,6), (INDEX(NEW_Table,0,3) <= U$15) * (INDEX(NEW_Table,0,3) >= EDATE(U$15,-11)))),0), 0)} -> 0 | V22: {=IF(Acq_Financing_Type_Switch = "Financed - New Loan", IFERROR(SUM(_xlfn._xlws.FILTER(INDEX(NEW_Table,0,6), (INDEX(NEW_Table,0,3) <= V$15) * (INDEX(NEW_Table,0,3) >= EDATE(V$15,-11)))),0), 0)} -> 0 | W22: {=IF(Acq_Financing_Type_Switch = "Financed - New Loan", IFERROR(SUM(_xlfn._xlws.FILTER(INDEX(NEW_Table,0,6), (INDEX(NEW_Table,0,3) <= W$15) * (INDEX(NEW_Table,0,3) >= EDATE(W$15,-11)))),0), 0)} -> 0 | X22: {=IF(Acq_Financing_Type_Switch = "Financed - New Loan", IFERROR(SUM(_xlfn._xlws.FILTER(INDEX(NEW_Table,0,6), (INDEX(NEW_Table,0,3) <= X$15) * (INDEX(NEW_Table,0,3) >= EDATE(X$15,-11)))),0), 0)} -> 0 | Y22: {=IF(Acq_Financing_Type_Switch = "Financed - New Loan", IFERROR(SUM(_xlfn._xlws.FILTER(INDEX(NEW_Table,0,6), (INDEX(NEW_Table,0,3) <= Y$15) * (INDEX(NEW_Table,0,3) >= EDATE(Y$15,-11)))),0), 0)} -> 0 | Z22: {=IF(Acq_Financing_Type_Switch = "Financed - New Loan", IFERROR(SUM(_xlfn._xlws.FILTER(INDEX(NEW_Table,0,6), (INDEX(NEW_Table,0,3) <= Z$15) * (INDEX(NEW_Table,0,3) >= EDATE(Z$15,-11)))),0), 0)} -> 0 | AA22: {=IF(Acq_Financing_Type_Switch = "Financed - New Loan", IFERROR(SUM(_xlfn._xlws.FILTER(INDEX(NEW_Table,0,6), (INDEX(NEW_Table,0,3) <= AA$15) * (INDEX(NEW_Table,0,3) >= EDATE(AA$15,-11)))),0), 0)} -> 0 | AB22: {=IF(Acq_Financing_Type_Switch = "Financed - New Loan", IFERROR(SUM(_xlfn._xlws.FILTER(INDEX(NEW_Table,0,6), (INDEX(NEW_Table,0,3) <= AB$15) * (INDEX(NEW_Table,0,3) >= EDATE(AB$15,-11)))),0), 0)} -> 0 | AC22: {=IF(Acq_Financing_Type_Switch = "Financed - New Loan", IFERROR(SUM(_xlfn._xlws.FILTER(INDEX(NEW_Table,0,6), (INDEX(NEW_Table,0,3) <= AC$15) * (INDEX(NEW_Table,0,3) >= EDATE(AC$15,-11)))),0), 0)} -> 0
D23: Compounding | N23: Cap Rate at Refi | S23: Mezzanine Loan
D24: Term (Years) | J24: =Mezz_Term -> #NUM! | S24: Interest | T24: {=IF(Mezz_Switch = "Yes", IFERROR(SUM(_xlfn._xlws.FILTER(INDEX(Mezz_Table,0,7), (INDEX(Mezz_Table,0,3) <= T$15) * (INDEX(Mezz_Table,0,3) >= EDATE(T$15,-12)))),0), 0)} -> 0 | U24: {=IF(Mezz_Switch = "Yes", IFERROR(SUM(_xlfn._xlws.FILTER(INDEX(Mezz_Table,0,7), (INDEX(Mezz_Table,0,3) <= U$15) * (INDEX(Mezz_Table,0,3) >= EDATE(U$15,-11)))),0), 0)} -> 0 | V24: {=IF(Mezz_Switch = "Yes", IFERROR(SUM(_xlfn._xlws.FILTER(INDEX(Mezz_Table,0,7), (INDEX(Mezz_Table,0,3) <= V$15) * (INDEX(Mezz_Table,0,3) >= EDATE(V$15,-11)))),0), 0)} -> 0 | W24: {=IF(Mezz_Switch = "Yes", IFERROR(SUM(_xlfn._xlws.FILTER(INDEX(Mezz_Table,0,7), (INDEX(Mezz_Table,0,3) <= W$15) * (INDEX(Mezz_Table,0,3) >= EDATE(W$15,-11)))),0), 0)} -> 0 | X24: {=IF(Mezz_Switch = "Yes", IFERROR(SUM(_xlfn._xlws.FILTER(INDEX(Mezz_Table,0,7), (INDEX(Mezz_Table,0,3) <= X$15) * (INDEX(Mezz_Table,0,3) >= EDATE(X$15,-11)))),0), 0)} -> 0 | Y24: {=IF(Mezz_Switch = "Yes", IFERROR(SUM(_xlfn._xlws.FILTER(INDEX(Mezz_Table,0,7), (INDEX(Mezz_Table,0,3) <= Y$15) * (INDEX(Mezz_Table,0,3) >= EDATE(Y$15,-11)))),0), 0)} -> 0 | Z24: {=IF(Mezz_Switch = "Yes", IFERROR(SUM(_xlfn._xlws.FILTER(INDEX(Mezz_Table,0,7), (INDEX(Mezz_Table,0,3) <= Z$15) * (INDEX(Mezz_Table,0,3) >= EDATE(Z$15,-11)))),0), 0)} -> 0 | AA24: {=IF(Mezz_Switch = "Yes", IFERROR(SUM(_xlfn._xlws.FILTER(INDEX(Mezz_Table,0,7), (INDEX(Mezz_Table,0,3) <= AA$15) * (INDEX(Mezz_Table,0,3) >= EDATE(AA$15,-11)))),0), 0)} -> 0 | AB24: {=IF(Mezz_Switch = "Yes", IFERROR(SUM(_xlfn._xlws.FILTER(INDEX(Mezz_Table,0,7), (INDEX(Mezz_Table,0,3) <= AB$15) * (INDEX(Mezz_Table,0,3) >= EDATE(AB$15,-11)))),0), 0)} -> 0 | AC24: {=IF(Mezz_Switch = "Yes", IFERROR(SUM(_xlfn._xlws.FILTER(INDEX(Mezz_Table,0,7), (INDEX(Mezz_Table,0,3) <= AC$15) * (INDEX(Mezz_Table,0,3) >= EDATE(AC$15,-11)))),0), 0)} -> 0
D25: Maturity Date | F25: =IFERROR(SED_Loan_Due_Date,"") | H25: =NEW_Loan_Due_Date -> #NUM! | J25: =Mezz_Loan_Due_Date -> #NUM! | L25: =Refi_Loan_Due_Date | N25: Cash Out | O25: =IF(Refi_Orig_Loan_Amount>O20,Refi_Orig_Loan_Amount-O20,"") | S25: Principal | T25: {=IF(Mezz_Switch = "Yes", IFERROR(SUM(_xlfn._xlws.FILTER(INDEX(Mezz_Table,0,6), (INDEX(Mezz_Table,0,3) <= T$15) * (INDEX(Mezz_Table,0,3) >= EDATE(T$15,-12)))),0), 0)} -> 0 | U25: {=IF(Mezz_Switch = "Yes", IFERROR(SUM(_xlfn._xlws.FILTER(INDEX(Mezz_Table,0,6), (INDEX(Mezz_Table,0,3) <= U$15) * (INDEX(Mezz_Table,0,3) >= EDATE(U$15,-11)))),0), 0)} -> 0 | V25: {=IF(Mezz_Switch = "Yes", IFERROR(SUM(_xlfn._xlws.FILTER(INDEX(Mezz_Table,0,6), (INDEX(Mezz_Table,0,3) <= V$15) * (INDEX(Mezz_Table,0,3) >= EDATE(V$15,-11)))),0), 0)} -> 0 | W25: {=IF(Mezz_Switch = "Yes", IFERROR(SUM(_xlfn._xlws.FILTER(INDEX(Mezz_Table,0,6), (INDEX(Mezz_Table,0,3) <= W$15) * (INDEX(Mezz_Table,0,3) >= EDATE(W$15,-11)))),0), 0)} -> 0 | X25: {=IF(Mezz_Switch = "Yes", IFERROR(SUM(_xlfn._xlws.FILTER(INDEX(Mezz_Table,0,6), (INDEX(Mezz_Table,0,3) <= X$15) * (INDEX(Mezz_Table,0,3) >= EDATE(X$15,-11)))),0), 0)} -> 0 | Y25: {=IF(Mezz_Switch = "Yes", IFERROR(SUM(_xlfn._xlws.FILTER(INDEX(Mezz_Table,0,6), (INDEX(Mezz_Table,0,3) <= Y$15) * (INDEX(Mezz_Table,0,3) >= EDATE(Y$15,-11)))),0), 0)} -> 0 | Z25: {=IF(Mezz_Switch = "Yes", IFERROR(SUM(_xlfn._xlws.FILTER(INDEX(Mezz_Table,0,6), (INDEX(Mezz_Table,0,3) <= Z$15) * (INDEX(Mezz_Table,0,3) >= EDATE(Z$15,-11)))),0), 0)} -> 0 | AA25: {=IF(Mezz_Switch = "Yes", IFERROR(SUM(_xlfn._xlws.FILTER(INDEX(Mezz_Table,0,6), (INDEX(Mezz_Table,0,3) <= AA$15) * (INDEX(Mezz_Table,0,3) >= EDATE(AA$15,-11)))),0), 0)} -> 0 | AB25: {=IF(Mezz_Switch = "Yes", IFERROR(SUM(_xlfn._xlws.FILTER(INDEX(Mezz_Table,0,6), (INDEX(Mezz_Table,0,3) <= AB$15) * (INDEX(Mezz_Table,0,3) >= EDATE(AB$15,-11)))),0), 0)} -> 0 | AC25: {=IF(Mezz_Switch = "Yes", IFERROR(SUM(_xlfn._xlws.FILTER(INDEX(Mezz_Table,0,6), (INDEX(Mezz_Table,0,3) <= AC$15) * (INDEX(Mezz_Table,0,3) >= EDATE(AC$15,-11)))),0), 0)} -> 0
D26: Interest Only Period (Months) | S26: Refinance Loan
D27: Amortization Period (Years) | S27: Interest | T27: {=IF(Refi_Switch = "Yes", IFERROR(SUM(_xlfn._xlws.FILTER(INDEX(Refi_Table,0,7), (INDEX(Refi_Table,0,3) <= T$15) * (INDEX(Refi_Table,0,3) >= EDATE(T$15,-12)))),0),0)} -> 0 | U27: {=IF(Refi_Switch = "Yes", IFERROR(SUM(_xlfn._xlws.FILTER(INDEX(Refi_Table,0,7), (INDEX(Refi_Table,0,3) <= U$15) * (INDEX(Refi_Table,0,3) >= EDATE(U$15,-11)))),0),0)} -> 0 | V27: {=IF(Refi_Switch = "Yes", IFERROR(SUM(_xlfn._xlws.FILTER(INDEX(Refi_Table,0,7), (INDEX(Refi_Table,0,3) <= V$15) * (INDEX(Refi_Table,0,3) >= EDATE(V$15,-11)))),0),0)} -> 0 | W27: {=IF(Refi_Switch = "Yes", IFERROR(SUM(_xlfn._xlws.FILTER(INDEX(Refi_Table,0,7), (INDEX(Refi_Table,0,3) <= W$15) * (INDEX(Refi_Table,0,3) >= EDATE(W$15,-11)))),0),0)} -> 0 | X27: {=IF(Refi_Switch = "Yes", IFERROR(SUM(_xlfn._xlws.FILTER(INDEX(Refi_Table,0,7), (INDEX(Refi_Table,0,3) <= X$15) * (INDEX(Refi_Table,0,3) >= EDATE(X$15,-11)))),0),0)} -> 0 | Y27: {=IF(Refi_Switch = "Yes", IFERROR(SUM(_xlfn._xlws.FILTER(INDEX(Refi_Table,0,7), (INDEX(Refi_Table,0,3) <= Y$15) * (INDEX(Refi_Table,0,3) >= EDATE(Y$15,-11)))),0),0)} -> 0 | Z27: {=IF(Refi_Switch = "Yes", IFERROR(SUM(_xlfn._xlws.FILTER(INDEX(Refi_Table,0,7), (INDEX(Refi_Table,0,3) <= Z$15) * (INDEX(Refi_Table,0,3) >= EDATE(Z$15,-11)))),0),0)} -> 0 | AA27: {=IF(Refi_Switch = "Yes", IFERROR(SUM(_xlfn._xlws.FILTER(INDEX(Refi_Table,0,7), (INDEX(Refi_Table,0,3) <= AA$15) * (INDEX(Refi_Table,0,3) >= EDATE(AA$15,-11)))),0),0)} -> 0 | AB27: {=IF(Refi_Switch = "Yes", IFERROR(SUM(_xlfn._xlws.FILTER(INDEX(Refi_Table,0,7), (INDEX(Refi_Table,0,3) <= AB$15) * (INDEX(Refi_Table,0,3) >= EDATE(AB$15,-11)))),0),0)} -> 0 | AC27: {=IF(Refi_Switch = "Yes", IFERROR(SUM(_xlfn._xlws.FILTER(INDEX(Refi_Table,0,7), (INDEX(Refi_Table,0,3) <= AC$15) * (INDEX(Refi_Table,0,3) >= EDATE(AC$15,-11)))),0),0)} -> 0
D28: Loan Constant | F28: =IFERROR(SED_Loan_Constant,0) -> 0 | H28: =IFERROR(NEW_Loan_Constant,0) -> 0 | J28: =IFERROR(Mezz_Loan_Constant,0) -> 0 | L28: =IFERROR(Refi_Loan_Constant,0) -> 0 | S28: Principal | T28: {=IF(Refi_Switch = "Yes", IFERROR(SUM(_xlfn._xlws.FILTER(INDEX(Refi_Table,0,6), (INDEX(Refi_Table,0,3) <= T$15) * (INDEX(Refi_Table,0,3) >= EDATE(T$15,-12)))),0), 0)} -> 0 | U28: {=IF(Refi_Switch = "Yes", IFERROR(SUM(_xlfn._xlws.FILTER(INDEX(Refi_Table,0,6), (INDEX(Refi_Table,0,3) <= U$15) * (INDEX(Refi_Table,0,3) >= EDATE(U$15,-11)))),0), 0)} -> 0 | V28: {=IF(Refi_Switch = "Yes", IFERROR(SUM(_xlfn._xlws.FILTER(INDEX(Refi_Table,0,6), (INDEX(Refi_Table,0,3) <= V$15) * (INDEX(Refi_Table,0,3) >= EDATE(V$15,-11)))),0), 0)} -> 0 | W28: {=IF(Refi_Switch = "Yes", IFERROR(SUM(_xlfn._xlws.FILTER(INDEX(Refi_Table,0,6), (INDEX(Refi_Table,0,3) <= W$15) * (INDEX(Refi_Table,0,3) >= EDATE(W$15,-11)))),0), 0)} -> 0 | X28: {=IF(Refi_Switch = "Yes", IFERROR(SUM(_xlfn._xlws.FILTER(INDEX(Refi_Table,0,6), (INDEX(Refi_Table,0,3) <= X$15) * (INDEX(Refi_Table,0,3) >= EDATE(X$15,-11)))),0), 0)} -> 0 | Y28: {=IF(Refi_Switch = "Yes", IFERROR(SUM(_xlfn._xlws.FILTER(INDEX(Refi_Table,0,6), (INDEX(Refi_Table,0,3) <= Y$15) * (INDEX(Refi_Table,0,3) >= EDATE(Y$15,-11)))),0), 0)} -> 0 | Z28: {=IF(Refi_Switch = "Yes", IFERROR(SUM(_xlfn._xlws.FILTER(INDEX(Refi_Table,0,6), (INDEX(Refi_Table,0,3) <= Z$15) * (INDEX(Refi_Table,0,3) >= EDATE(Z$15,-11)))),0), 0)} -> 0 | AA28: {=IF(Refi_Switch = "Yes", IFERROR(SUM(_xlfn._xlws.FILTER(INDEX(Refi_Table,0,6), (INDEX(Refi_Table,0,3) <= AA$15) * (INDEX(Refi_Table,0,3) >= EDATE(AA$15,-11)))),0), 0)} -> 0 | AB28: {=IF(Refi_Switch = "Yes", IFERROR(SUM(_xlfn._xlws.FILTER(INDEX(Refi_Table,0,6), (INDEX(Refi_Table,0,3) <= AB$15) * (INDEX(Refi_Table,0,3) >= EDATE(AB$15,-11)))),0), 0)} -> 0 | AC28: {=IF(Refi_Switch = "Yes", IFERROR(SUM(_xlfn._xlws.FILTER(INDEX(Refi_Table,0,6), (INDEX(Refi_Table,0,3) <= AC$15) * (INDEX(Refi_Table,0,3) >= EDATE(AC$15,-11)))),0), 0)} -> 0
D29: Monthly Payment (After Interest Only Period) | F29: =IFERROR(PMT(F22/12,F27*12,SED_Orig_Loan_Amount),0) -> 0 | H29: =IFERROR(NEW_PMT,0) -> 0 | J29: =IFERROR(PMT(J22/12,J27*12,J19),0) -> 0 | L29: =IFERROR(PMT(L22/12,L27*12,L19),0) -> 0
D30: Monthly Payment (Interest Only) | F30: =IF(SED_Amort = 0, -F19*(F22/12), SED_IPMT) -> 0 | H30: =IF(NEW_Amort = 0, -H19*(H22/12), NEW_IPMT) -> 0 | J30: =IF(Mezz_Amort = 0, -J19*(J22/12), Mezz_IPMT) -> 0 | L30: =IF(Refi_Amort = 0, -L19*(L22/12), Refi_IPMT) -> #VALUE! | S30: Total Interest | T30: =T18+T21+T24+T27 -> 0 | U30: =U18+U21+U24+U27 -> 0 | V30: =V18+V21+V24+V27 -> 0 | W30: =W18+W21+W24+W27 -> 0 | X30: =X18+X21+X24+X27 -> 0 | Y30: =Y18+Y21+Y24+Y27 -> 0 | Z30: =Z18+Z21+Z24+Z27 -> 0 | AA30: =AA18+AA21+AA24+AA27 -> 0 | ... AC30: =AC18+AC21+AC24+AC27 -> 0
D31: Annual Debt Service Payment (P&I only) | F31: =F29*12 -> 0 | H31: =H29*12 -> 0 | J31: =J29*12 -> 0 | L31: =L29*12 -> 0 | S31: Total Principal | T31: =T19+T22+T25+T28 -> 0 | U31: =U19+U22+U25+U28 -> 0 | V31: =V19+V22+V25+V28 -> 0 | W31: =W19+W22+W25+W28 -> 0 | X31: =X19+X22+X25+X28 -> 0 | Y31: =Y19+Y22+Y25+Y28 -> 0 | Z31: =Z19+Z22+Z25+Z28 -> 0 | AA31: =AA19+AA22+AA25+AA28 -> 0 | ... AC31: =AC19+AC22+AC25+AC28 -> 0
D32: Outstanding Loan Balance at Maturity | F32: =IF(F27 = 0, -F21,SED_FV) -> 0 | H32: =IF(H27 = 0, -H21,NEW_FV) -> 0 | J32: =IF(J27 = 0, -J21,Mezz_FV) -> 0 | L32: =IF(L27 = 0, -L21,Refi_FV) -> 0 | S32: Take-Out Loan | T32: =IF(YEAR(Refi_Origination_Date) = YEAR(T15),Refi_Orig_Loan_Amount,0) | U32: =IF(YEAR(Refi_Origination_Date) = YEAR(U15),Refi_Orig_Loan_Amount,0) -> 0 | V32: =IF(YEAR(Refi_Origination_Date) = YEAR(V15),Refi_Orig_Loan_Amount,0) -> 0 | W32: =IF(YEAR(Refi_Origination_Date) = YEAR(W15),Refi_Orig_Loan_Amount,0) -> 0 | X32: =IF(YEAR(Refi_Origination_Date) = YEAR(X15),Refi_Orig_Loan_Amount,0) -> 0 | Y32: =IF(YEAR(Refi_Origination_Date) = YEAR(Y15),Refi_Orig_Loan_Amount,0) -> 0 | Z32: =IF(YEAR(Refi_Origination_Date) = YEAR(Z15),Refi_Orig_Loan_Amount,0) -> 0 | AA32: =IF(YEAR(Refi_Origination_Date) = YEAR(AA15),Refi_Orig_Loan_Amount,0) -> 0 | ... AC32: =IF(YEAR(Refi_Origination_Date) = YEAR(AC15),Refi_Orig_Loan_Amount,0) -> 0
D33: Term Remaining (Months) | F33: =IFERROR(SED_TIme_Remaining,0) -> 0 | H33: =IFERROR(NEW_Time_Remaining,0) -> 0 | J33: =Mezz_Time_Remaining -> #NUM! | L33: =IFERROR(Refi_Time_Remaining,0) -> 0 | S33: Remaining Balance | T33: {=IFERROR(IF(YEAR(SED_Loan_Due_Date) = YEAR(T15), IFERROR(-MIN(_xlfn._xlws.FILTER(INDEX(SED_Table,0,8),INDEX(SED_Table,0,8)<>0)),0),0),0) + IFERROR(IF(YEAR(Mezz_Loan_Due_Date) = YEAR(T15),IFERROR(-MIN(_xlfn._xlws.FILTER(INDEX(Mezz_Table,0,8),INDEX(Mezz_Table,0,8)<>0)),0),0),0)} -> 0 | U33: {=IFERROR(IF(YEAR(SED_Loan_Due_Date) = YEAR(U15), IFERROR(-MIN(_xlfn._xlws.FILTER(INDEX(SED_Table,0,8),INDEX(SED_Table,0,8)<>0)),0),0),0) + IFERROR(IF(YEAR(Mezz_Loan_Due_Date) = YEAR(U15),IFERROR(-MIN(_xlfn._xlws.FILTER(INDEX(Mezz_Table,0,8),INDEX(Mezz_Table,0,8)<>0)),0),0),0)} -> 0 | V33: {=IFERROR(IF(YEAR(SED_Loan_Due_Date) = YEAR(V15), IFERROR(-MIN(_xlfn._xlws.FILTER(INDEX(SED_Table,0,8),INDEX(SED_Table,0,8)<>0)),0),0),0) + IFERROR(IF(YEAR(Mezz_Loan_Due_Date) = YEAR(V15),IFERROR(-MIN(_xlfn._xlws.FILTER(INDEX(Mezz_Table,0,8),INDEX(Mezz_Table,0,8)<>0)),0),0),0)} -> 0 | W33: {=IFERROR(IF(YEAR(SED_Loan_Due_Date) = YEAR(W15), IFERROR(-MIN(_xlfn._xlws.FILTER(INDEX(SED_Table,0,8),INDEX(SED_Table,0,8)<>0)),0),0),0) + IFERROR(IF(YEAR(Mezz_Loan_Due_Date) = YEAR(W15),IFERROR(-MIN(_xlfn._xlws.FILTER(INDEX(Mezz_Table,0,8),INDEX(Mezz_Table,0,8)<>0)),0),0),0)} -> 0 | X33: {=IFERROR(IF(YEAR(SED_Loan_Due_Date) = YEAR(X15), IFERROR(-MIN(_xlfn._xlws.FILTER(INDEX(SED_Table,0,8),INDEX(SED_Table,0,8)<>0)),0),0),0) + IFERROR(IF(YEAR(Mezz_Loan_Due_Date) = YEAR(X15),IFERROR(-MIN(_xlfn._xlws.FILTER(INDEX(Mezz_Table,0,8),INDEX(Mezz_Table,0,8)<>0)),0),0),0)} -> 0 | Y33: {=IFERROR(IF(YEAR(SED_Loan_Due_Date) = YEAR(Y15), IFERROR(-MIN(_xlfn._xlws.FILTER(INDEX(SED_Table,0,8),INDEX(SED_Table,0,8)<>0)),0),0),0) + IFERROR(IF(YEAR(Mezz_Loan_Due_Date) = YEAR(Y15),IFERROR(-MIN(_xlfn._xlws.FILTER(INDEX(Mezz_Table,0,8),INDEX(Mezz_Table,0,8)<>0)),0),0),0)} -> 0 | Z33: {=IFERROR(IF(YEAR(SED_Loan_Due_Date) = YEAR(Z15), IFERROR(-MIN(_xlfn._xlws.FILTER(INDEX(SED_Table,0,8),INDEX(SED_Table,0,8)<>0)),0),0),0) + IFERROR(IF(YEAR(Mezz_Loan_Due_Date) = YEAR(Z15),IFERROR(-MIN(_xlfn._xlws.FILTER(INDEX(Mezz_Table,0,8),INDEX(Mezz_Table,0,8)<>0)),0),0),0)} -> 0 | AA33: {=IFERROR(IF(YEAR(SED_Loan_Due_Date) = YEAR(AA15), IFERROR(-MIN(_xlfn._xlws.FILTER(INDEX(SED_Table,0,8),INDEX(SED_Table,0,8)<>0)),0),0),0) + IFERROR(IF(YEAR(Mezz_Loan_Due_Date) = YEAR(AA15),IFERROR(-MIN(_xlfn._xlws.FILTER(INDEX(Mezz_Table,0,8),INDEX(Mezz_Table,0,8)<>0)),0),0),0)} -> 0 | ... AC33: {=IFERROR(IF(YEAR(SED_Loan_Due_Date) = YEAR(AC15), IFERROR(-MIN(_xlfn._xlws.FILTER(INDEX(SED_Table,0,8),INDEX(SED_Table,0,8)<>0)),0),0),0) + IFERROR(IF(YEAR(Mezz_Loan_Due_Date) = YEAR(AC15),IFERROR(-MIN(_xlfn._xlws.FILTER(INDEX(Mezz_Table,0,8),INDEX(Mezz_Table,0,8)<>0)),0),0),0)} -> 0
D34: Loan Origination Fee (0.00%) | S34: Loan Origination Fee | T34: =IF(T32=0,0,T32*-Refi_Origination_Feee) -> #VALUE! | U34: =IF(U32=0,0,U32*-Refi_Origination_Feee) -> 0 | V34: =IF(V32=0,0,V32*-Refi_Origination_Feee) -> 0 | W34: =IF(W32=0,0,W32*-Refi_Origination_Feee) -> 0 | X34: =IF(X32=0,0,X32*-Refi_Origination_Feee) -> 0 | Y34: =IF(Y32=0,0,Y32*-Refi_Origination_Feee) -> 0 | Z34: =IF(Z32=0,0,Z32*-Refi_Origination_Feee) -> 0 | AA34: =IF(AA32=0,0,AA32*-Refi_Origination_Feee) -> 0 | ... AC34: =IF(AC32=0,0,AC32*-Refi_Origination_Feee) -> 0
D35: Prepayment Penalty ($) | S35: Prepayment Penalty ($) | T35: =IF(T33=0,0,-SED_Prepayment_Penalty-Mezz_Prepayment_Penalty) -> 0 | U35: =IF(U33=0,0,-SED_Prepayment_Penalty-Mezz_Prepayment_Penalty) -> 0 | V35: =IF(V33=0,0,-SED_Prepayment_Penalty-Mezz_Prepayment_Penalty) -> 0 | W35: =IF(W33=0,0,-SED_Prepayment_Penalty-Mezz_Prepayment_Penalty) -> 0 | X35: =IF(X33=0,0,-SED_Prepayment_Penalty-Mezz_Prepayment_Penalty) -> 0 | Y35: =IF(Y33=0,0,-SED_Prepayment_Penalty-Mezz_Prepayment_Penalty) -> 0 | Z35: =IF(Z33=0,0,-SED_Prepayment_Penalty-Mezz_Prepayment_Penalty) -> 0 | AA35: =IF(AA33=0,0,-SED_Prepayment_Penalty-Mezz_Prepayment_Penalty) -> 0 | ... AC35: =IF(AC33=0,0,-SED_Prepayment_Penalty-Mezz_Prepayment_Penalty) -> 0
S36: Cash Flow From Financing | T36: =SUM(T30:T35) -> #VALUE! | U36: =SUM(U30:U35) -> 0 | V36: =SUM(V30:V35) -> 0 | W36: =SUM(W30:W35) -> 0 | X36: =SUM(X30:X35) -> 0 | Y36: =SUM(Y30:Y35) -> 0 | Z36: =SUM(Z30:Z35) -> 0 | AA36: =SUM(AA30:AA35) -> 0 | ... AC36: =SUM(AC30:AC35) -> 0

Sheet Rent Roll Input
B2: User Input | C2: User Input | E2: User Input | F2: User Input | G2: User Input | H2: User Input | I2: User Input | J2: User Input | K2: Calculation | L2: Calculation | M2: Calculation | N2: Calculation | O2: Calculation | P2: Calculation | Q2: Calculation | R2: Calculation | S2: Calculation | T2: Calculation | U2: Calculation | V2: Calculation | W2: Calculation
B3: Bed | C3: Bath | D3: Unit No. | E3: Unit Description | F3: Units | G3: Square Feet | H3: Currrent Rent / Unit / Month | I3: Potential Rent / Unit / Month | J3: Reno Rent / Unit / Month | K3: Scheduled Rent / Unit / Month | L3: Current Rent / SF / Month | M3: Potential Rent / SF / Month | N3: Reno Rent / SF / Month | O3: Scheduled Rent / SF / Month | P3: Current Rent / SF / Year | Q3: Potential Rent / SF / Year | R3: Reno Rent / SF / Year | S3: Scheduled Rent / SF / Year | T3: Total Sq Ft | U3: Unit Type
A4: HIDE | B4: {=IFERROR(SUM(INDEX(Rent_Roll_Input,0,COLUMN(A:A))),0)} -> 0 | C4: {=IFERROR(SUM(INDEX(Rent_Roll_Input,0,COLUMN(B:B))),0)} -> 0 | F4: {=IFERROR(SUM(INDEX(Rent_Roll_Input,0,COLUMN(E:E))),0)} -> 0 | G4: {=IFERROR(SUMPRODUCT(INDEX(Rent_Roll_Input,0,COLUMN($E:$E)),INDEX(Rent_Roll_Input,0,COLUMN(F:F))),0)} -> 0 | H4: {=IFERROR(SUMPRODUCT(INDEX(Rent_Roll_Input,0,COLUMN($E:$E)),INDEX(Rent_Roll_Input,0,COLUMN(G:G)))/F4,0)} -> 0 | I4: {=IFERROR(SUMPRODUCT(INDEX(Rent_Roll_Input,0,COLUMN($E:$E)),INDEX(Rent_Roll_Input,0,COLUMN(H:H)))/F4,0)} -> 0 | J4: {=IFERROR(SUMPRODUCT(INDEX(Rent_Roll_Input,0,COLUMN($E:$E)),INDEX(Rent_Roll_Input,0,COLUMN(I:I)))/F4,0)} -> 0 | K4: {=IFERROR(SUMPRODUCT(INDEX(Rent_Roll_Input,0,COLUMN($E:$E)),INDEX(Rent_Roll_Input,0,COLUMN(J:J)))/F4,0)} -> 0 | L4: =IF($U4 = "", "", H4/$G4*F4) -> #DIV/0! | M4: =IF($U4 = "", "", I4/$G4*F4) -> #DIV/0! | N4: =IF($U4 = "", "", J4/$G4*F4) -> #DIV/0! | O4: =IF($U4 = "", "", K4/$G4*F4) -> #DIV/0! | P4: =IF(L4="", "", L4*12) -> #DIV/0! | Q4: =IF(M4="", "", M4*12) -> #DIV/0! | R4: =IF(N4="", "", N4*12) -> #DIV/0! | S4: =IF(O4="", "", O4*12) -> #DIV/0! | T4: {=_xlfn.IFS(G4="", "", F4 = "", G4, 1, F4*G4)} -> 0 | U4: Totals/Weighted Averages
K5: =IF(G5= "", "", IF(H5=0,I5,H5)) | L5: =IF($U5 = "", "", H5/$G5) | M5: =IF($U5 = "", "", I5/$G5) | N5: =IF($U5 = "", "", J5/$G5) | O5: =IF($U5 = "", "", K5/$G5) | P5: =IF(L5="", "", L5*12) | Q5: =IF(M5="", "", M5*12) | R5: =IF(N5="", "", N5*12) | S5: =IF(O5="", "", O5*12) | T5: {=_xlfn.IFS(G5="", "", F5 = "", G5, 1, F5*G5)} | U5: =IF(AND(B5="", C5="", E5=""), "", IF(OR(B5=0,B5=""),E5,B5 & " Bed / " &C5& " Bath " &E5)) | V5: =IF(U5= "", "", B5) | W5: =IF(AND(B5="", C5="", E5=""), "", IF(OR(B5=0,B5=""),E5,B5 & " Bed / " &C5& " Bath "))
K6: =IF(G6= "", "", IF(H6=0,I6,H6)) | L6: =IF($U6 = "", "", H6/$G6) | M6: =IF($U6 = "", "", I6/$G6) | N6: =IF($U6 = "", "", J6/$G6) | O6: =IF($U6 = "", "", K6/$G6) | P6: =IF(L6="", "", L6*12) | Q6: =IF(M6="", "", M6*12) | R6: =IF(N6="", "", N6*12) | S6: =IF(O6="", "", O6*12) | T6: {=_xlfn.IFS(G6="", "", F6 = "", G6, 1, F6*G6)} | U6: =IF(AND(B6="", C6="", E6=""), "", IF(OR(B6=0,B6=""),E6,B6 & " Bed / " &C6& " Bath " &E6)) | V6: =IF(U6= "", "", B6) | W6: =IF(AND(B6="", C6="", E6=""), "", IF(OR(B6=0,B6=""),E6,B6 & " Bed / " &C6& " Bath "))
K7: =IF(G7= "", "", IF(H7=0,I7,H7)) | L7: =IF($U7 = "", "", H7/$G7) | M7: =IF($U7 = "", "", I7/$G7) | N7: =IF($U7 = "", "", J7/$G7) | O7: =IF($U7 = "", "", K7/$G7) | P7: =IF(L7="", "", L7*12) | Q7: =IF(M7="", "", M7*12) | R7: =IF(N7="", "", N7*12) | S7: =IF(O7="", "", O7*12) | T7: {=_xlfn.IFS(G7="", "", F7 = "", G7, 1, F7*G7)} | U7: =IF(AND(B7="", C7="", E7=""), "", IF(OR(B7=0,B7=""),E7,B7 & " Bed / " &C7& " Bath " &E7)) | V7: =IF(U7= "", "", B7) | W7: =IF(AND(B7="", C7="", E7=""), "", IF(OR(B7=0,B7=""),E7,B7 & " Bed / " &C7& " Bath "))
K8: =IF(G8= "", "", IF(H8=0,I8,H8)) | L8: =IF($U8 = "", "", H8/$G8) | M8: =IF($U8 = "", "", I8/$G8) | N8: =IF($U8 = "", "", J8/$G8) | O8: =IF($U8 = "", "", K8/$G8) | P8: =IF(L8="", "", L8*12) | Q8: =IF(M8="", "", M8*12) | R8: =IF(N8="", "", N8*12) | S8: =IF(O8="", "", O8*12) | T8: {=_xlfn.IFS(G8="", "", F8 = "", G8, 1, F8*G8)} | U8: =IF(AND(B8="", C8="", E8=""), "", IF(OR(B8=0,B8=""),E8,B8 & " Bed / " &C8& " Bath " &E8)) | V8: =IF(U8= "", "", B8) | W8: =IF(AND(B8="", C8="", E8=""), "", IF(OR(B8=0,B8=""),E8,B8 & " Bed / " &C8& " Bath ")) | X8: {=SUM(('Rent Roll Input'!$W$8:$W$214<>"")*1)} -> 0
K9: =IF(G9= "", "", IF(H9=0,I9,H9)) | L9: =IF($U9 = "", "", H9/$G9) | M9: =IF($U9 = "", "", I9/$G9) | N9: =IF($U9 = "", "", J9/$G9) | O9: =IF($U9 = "", "", K9/$G9) | P9: =IF(L9="", "", L9*12) | Q9: =IF(M9="", "", M9*12) | R9: =IF(N9="", "", N9*12) | S9: =IF(O9="", "", O9*12) | T9: {=_xlfn.IFS(G9="", "", F9 = "", G9, 1, F9*G9)} | U9: =IF(AND(B9="", C9="", E9=""), "", IF(OR(B9=0,B9=""),E9,B9 & " Bed / " &C9& " Bath " &E9)) | V9: =IF(U9= "", "", B9) | W9: =IF(AND(B9="", C9="", E9=""), "", IF(OR(B9=0,B9=""),E9,B9 & " Bed / " &C9& " Bath "))
K10: =IF(G10= "", "", IF(H10=0,I10,H10)) | L10: =IF($U10 = "", "", H10/$G10) | M10: =IF($U10 = "", "", I10/$G10) | N10: =IF($U10 = "", "", J10/$G10) | O10: =IF($U10 = "", "", K10/$G10) | P10: =IF(L10="", "", L10*12) | Q10: =IF(M10="", "", M10*12) | R10: =IF(N10="", "", N10*12) | S10: =IF(O10="", "", O10*12) | T10: {=_xlfn.IFS(G10="", "", F10 = "", G10, 1, F10*G10)} | U10: =IF(AND(B10="", C10="", E10=""), "", IF(OR(B10=0,B10=""),E10,B10 & " Bed / " &C10& " Bath " &E10)) | V10: =IF(U10= "", "", B10) | W10: =IF(AND(B10="", C10="", E10=""), "", IF(OR(B10=0,B10=""),E10,B10 & " Bed / " &C10& " Bath "))
K11: =IF(G11= "", "", IF(H11=0,I11,H11)) | L11: =IF($U11 = "", "", H11/$G11) | M11: =IF($U11 = "", "", I11/$G11) | N11: =IF($U11 = "", "", J11/$G11) | O11: =IF($U11 = "", "", K11/$G11) | P11: =IF(L11="", "", L11*12) | Q11: =IF(M11="", "", M11*12) | R11: =IF(N11="", "", N11*12) | S11: =IF(O11="", "", O11*12) | T11: {=_xlfn.IFS(G11="", "", F11 = "", G11, 1, F11*G11)} | U11: =IF(AND(B11="", C11="", E11=""), "", IF(OR(B11=0,B11=""),E11,B11 & " Bed / " &C11& " Bath " &E11)) | V11: =IF(U11= "", "", B11) | W11: =IF(AND(B11="", C11="", E11=""), "", IF(OR(B11=0,B11=""),E11,B11 & " Bed / " &C11& " Bath "))
K12: =IF(G12= "", "", IF(H12=0,I12,H12)) | L12: =IF($U12 = "", "", H12/$G12) | M12: =IF($U12 = "", "", I12/$G12) | N12: =IF($U12 = "", "", J12/$G12) | O12: =IF($U12 = "", "", K12/$G12) | P12: =IF(L12="", "", L12*12) | Q12: =IF(M12="", "", M12*12) | R12: =IF(N12="", "", N12*12) | S12: =IF(O12="", "", O12*12) | T12: {=_xlfn.IFS(G12="", "", F12 = "", G12, 1, F12*G12)} | U12: =IF(AND(B12="", C12="", E12=""), "", IF(OR(B12=0,B12=""),E12,B12 & " Bed / " &C12& " Bath " &E12)) | V12: =IF(U12= "", "", B12) | W12: =IF(AND(B12="", C12="", E12=""), "", IF(OR(B12=0,B12=""),E12,B12 & " Bed / " &C12& " Bath "))
K13: =IF(G13= "", "", IF(H13=0,I13,H13)) | L13: =IF($U13 = "", "", H13/$G13) | M13: =IF($U13 = "", "", I13/$G13) | N13: =IF($U13 = "", "", J13/$G13) | O13: =IF($U13 = "", "", K13/$G13) | P13: =IF(L13="", "", L13*12) | Q13: =IF(M13="", "", M13*12) | R13: =IF(N13="", "", N13*12) | S13: =IF(O13="", "", O13*12) | T13: {=_xlfn.IFS(G13="", "", F13 = "", G13, 1, F13*G13)} | U13: =IF(AND(B13="", C13="", E13=""), "", IF(OR(B13=0,B13=""),E13,B13 & " Bed / " &C13& " Bath " &E13)) | V13: =IF(U13= "", "", B13) | W13: =IF(AND(B13="", C13="", E13=""), "", IF(OR(B13=0,B13=""),E13,B13 & " Bed / " &C13& " Bath "))
K14: =IF(G14= "", "", IF(H14=0,I14,H14)) | L14: =IF($U14 = "", "", H14/$G14) | M14: =IF($U14 = "", "", I14/$G14) | N14: =IF($U14 = "", "", J14/$G14) | O14: =IF($U14 = "", "", K14/$G14) | P14: =IF(L14="", "", L14*12) | Q14: =IF(M14="", "", M14*12) | R14: =IF(N14="", "", N14*12) | S14: =IF(O14="", "", O14*12) | T14: {=_xlfn.IFS(G14="", "", F14 = "", G14, 1, F14*G14)} | U14: =IF(AND(B14="", C14="", E14=""), "", IF(OR(B14=0,B14=""),E14,B14 & " Bed / " &C14& " Bath " &E14)) | V14: =IF(U14= "", "", B14) | W14: =IF(AND(B14="", C14="", E14=""), "", IF(OR(B14=0,B14=""),E14,B14 & " Bed / " &C14& " Bath "))
K15: =IF(G15= "", "", IF(H15=0,I15,H15)) | L15: =IF($U15 = "", "", H15/$G15) | M15: =IF($U15 = "", "", I15/$G15) | N15: =IF($U15 = "", "", J15/$G15) | O15: =IF($U15 = "", "", K15/$G15) | P15: =IF(L15="", "", L15*12) | Q15: =IF(M15="", "", M15*12) | R15: =IF(N15="", "", N15*12) | S15: =IF(O15="", "", O15*12) | T15: {=_xlfn.IFS(G15="", "", F15 = "", G15, 1, F15*G15)} | U15: =IF(AND(B15="", C15="", E15=""), "", IF(OR(B15=0,B15=""),E15,B15 & " Bed / " &C15& " Bath " &E15)) | V15: =IF(U15= "", "", B15) | W15: =IF(AND(B15="", C15="", E15=""), "", IF(OR(B15=0,B15=""),E15,B15 & " Bed / " &C15& " Bath "))
K16: =IF(G16= "", "", IF(H16=0,I16,H16)) | L16: =IF($U16 = "", "", H16/$G16) | M16: =IF($U16 = "", "", I16/$G16) | N16: =IF($U16 = "", "", J16/$G16) | O16: =IF($U16 = "", "", K16/$G16) | P16: =IF(L16="", "", L16*12) | Q16: =IF(M16="", "", M16*12) | R16: =IF(N16="", "", N16*12) | S16: =IF(O16="", "", O16*12) | T16: {=_xlfn.IFS(G16="", "", F16 = "", G16, 1, F16*G16)} | U16: =IF(AND(B16="", C16="", E16=""), "", IF(OR(B16=0,B16=""),E16,B16 & " Bed / " &C16& " Bath " &E16)) | V16: =IF(U16= "", "", B16) | W16: =IF(AND(B16="", C16="", E16=""), "", IF(OR(B16=0,B16=""),E16,B16 & " Bed / " &C16& " Bath "))
K17: =IF(G17= "", "", IF(H17=0,I17,H17)) | L17: =IF($U17 = "", "", H17/$G17) | M17: =IF($U17 = "", "", I17/$G17) | N17: =IF($U17 = "", "", J17/$G17) | O17: =IF($U17 = "", "", K17/$G17) | P17: =IF(L17="", "", L17*12) | Q17: =IF(M17="", "", M17*12) | R17: =IF(N17="", "", N17*12) | S17: =IF(O17="", "", O17*12) | T17: {=_xlfn.IFS(G17="", "", F17 = "", G17, 1, F17*G17)} | U17: =IF(AND(B17="", C17="", E17=""), "", IF(OR(B17=0,B17=""),E17,B17 & " Bed / " &C17& " Bath " &E17)) | V17: =IF(U17= "", "", B17) | W17: =IF(AND(B17="", C17="", E17=""), "", IF(OR(B17=0,B17=""),E17,B17 & " Bed / " &C17& " Bath "))
K18: =IF(G18= "", "", IF(H18=0,I18,H18)) | L18: =IF($U18 = "", "", H18/$G18) | M18: =IF($U18 = "", "", I18/$G18) | N18: =IF($U18 = "", "", J18/$G18) | O18: =IF($U18 = "", "", K18/$G18) | P18: =IF(L18="", "", L18*12) | Q18: =IF(M18="", "", M18*12) | R18: =IF(N18="", "", N18*12) | S18: =IF(O18="", "", O18*12) | T18: {=_xlfn.IFS(G18="", "", F18 = "", G18, 1, F18*G18)} | U18: =IF(AND(B18="", C18="", E18=""), "", IF(OR(B18=0,B18=""),E18,B18 & " Bed / " &C18& " Bath " &E18)) | V18: =IF(U18= "", "", B18) | W18: =IF(AND(B18="", C18="", E18=""), "", IF(OR(B18=0,B18=""),E18,B18 & " Bed / " &C18& " Bath "))
K19: =IF(G19= "", "", IF(H19=0,I19,H19)) | L19: =IF($U19 = "", "", H19/$G19) | M19: =IF($U19 = "", "", I19/$G19) | N19: =IF($U19 = "", "", J19/$G19) | O19: =IF($U19 = "", "", K19/$G19) | P19: =IF(L19="", "", L19*12) | Q19: =IF(M19="", "", M19*12) | R19: =IF(N19="", "", N19*12) | S19: =IF(O19="", "", O19*12) | T19: {=_xlfn.IFS(G19="", "", F19 = "", G19, 1, F19*G19)} | U19: =IF(AND(B19="", C19="", E19=""), "", IF(OR(B19=0,B19=""),E19,B19 & " Bed / " &C19& " Bath " &E19)) | V19: =IF(U19= "", "", B19) | W19: =IF(AND(B19="", C19="", E19=""), "", IF(OR(B19=0,B19=""),E19,B19 & " Bed / " &C19& " Bath "))
K20: =IF(G20= "", "", IF(H20=0,I20,H20)) | L20: =IF($U20 = "", "", H20/$G20) | M20: =IF($U20 = "", "", I20/$G20) | N20: =IF($U20 = "", "", J20/$G20) | O20: =IF($U20 = "", "", K20/$G20) | P20: =IF(L20="", "", L20*12) | Q20: =IF(M20="", "", M20*12) | R20: =IF(N20="", "", N20*12) | S20: =IF(O20="", "", O20*12) | T20: {=_xlfn.IFS(G20="", "", F20 = "", G20, 1, F20*G20)} | U20: =IF(AND(B20="", C20="", E20=""), "", IF(OR(B20=0,B20=""),E20,B20 & " Bed / " &C20& " Bath " &E20)) | V20: =IF(U20= "", "", B20) | W20: =IF(AND(B20="", C20="", E20=""), "", IF(OR(B20=0,B20=""),E20,B20 & " Bed / " &C20& " Bath "))
... K64: =IF(G64= "", "", IF(H64=0,I64,H64)) | L64: =IF($U64 = "", "", H64/$G64) | M64: =IF($U64 = "", "", I64/$G64) | N64: =IF($U64 = "", "", J64/$G64) | O64: =IF($U64 = "", "", K64/$G64) | P64: =IF(L64="", "", L64*12) | Q64: =IF(M64="", "", M64*12) | R64: =IF(N64="", "", N64*12) | S64: =IF(O64="", "", O64*12) | T64: {=_xlfn.IFS(G64="", "", F64 = "", G64, 1, F64*G64)} | U64: =IF(AND(B64="", C64="", E64=""), "", IF(OR(B64=0,B64=""),E64,B64 & " Bed / " &C64& " Bath " &E64)) | V64: =IF(U64= "", "", B64) | W64: =IF(AND(B64="", C64="", E64=""), "", IF(OR(B64=0,B64=""),E64,B64 & " Bed / " &C64& " Bath "))
L65: =IF($U65 = "", "", H65/$G65) | M65: =IF($U65 = "", "", I65/$G65) | N65: =IF($U65 = "", "", J65/$G65) | O65: =IF($U65 = "", "", K65/$G65) | P65: =IF(L65="", "", L65*12) | Q65: =IF(M65="", "", M65*12) | R65: =IF(N65="", "", N65*12) | S65: =IF(O65="", "", O65*12) | T65: {=_xlfn.IFS(G65="", "", F65 = "", G65, 1, F65*G65)} | U65: =IF(AND(B65="", C65="", E65=""), "", IF(OR(B65=0,B65=""),E65,B65 & " Bed / " &C65& " Bath " &E65)) | V65: =IF(U65= "", "", B65) | W65: =IF(AND(B65="", C65="", E65=""), "", IF(OR(B65=0,B65=""),E65,B65 & " Bed / " &C65& " Bath "))
L66: =IF($U66 = "", "", H66/$G66) | M66: =IF($U66 = "", "", I66/$G66) | N66: =IF($U66 = "", "", J66/$G66) | O66: =IF($U66 = "", "", K66/$G66) | P66: =IF(L66="", "", L66*12) | Q66: =IF(M66="", "", M66*12) | R66: =IF(N66="", "", N66*12) | S66: =IF(O66="", "", O66*12) | T66: {=_xlfn.IFS(G66="", "", F66 = "", G66, 1, F66*G66)} | U66: =IF(AND(B66="", C66="", E66=""), "", IF(OR(B66=0,B66=""),E66,B66 & " Bed / " &C66& " Bath " &E66)) | V66: =IF(U66= "", "", B66) | W66: =IF(AND(B66="", C66="", E66=""), "", IF(OR(B66=0,B66=""),E66,B66 & " Bed / " &C66& " Bath "))
L67: =IF($U67 = "", "", H67/$G67) | M67: =IF($U67 = "", "", I67/$G67) | N67: =IF($U67 = "", "", J67/$G67) | O67: =IF($U67 = "", "", K67/$G67) | P67: =IF(L67="", "", L67*12) | Q67: =IF(M67="", "", M67*12) | R67: =IF(N67="", "", N67*12) | S67: =IF(O67="", "", O67*12) | T67: {=_xlfn.IFS(G67="", "", F67 = "", G67, 1, F67*G67)} | U67: =IF(AND(B67="", C67="", E67=""), "", IF(OR(B67=0,B67=""),E67,B67 & " Bed / " &C67& " Bath " &E67)) | V67: =IF(U67= "", "", B67) | W67: =IF(AND(B67="", C67="", E67=""), "", IF(OR(B67=0,B67=""),E67,B67 & " Bed / " &C67& " Bath "))
L68: =IF($U68 = "", "", H68/$G68) | M68: =IF($U68 = "", "", I68/$G68) | N68: =IF($U68 = "", "", J68/$G68) | O68: =IF($U68 = "", "", K68/$G68) | P68: =IF(L68="", "", L68*12) | Q68: =IF(M68="", "", M68*12) | R68: =IF(N68="", "", N68*12) | S68: =IF(O68="", "", O68*12) | T68: {=_xlfn.IFS(G68="", "", F68 = "", G68, 1, F68*G68)} | U68: =IF(AND(B68="", C68="", E68=""), "", IF(OR(B68=0,B68=""),E68,B68 & " Bed / " &C68& " Bath " &E68)) | V68: =IF(U68= "", "", B68) | W68: =IF(AND(B68="", C68="", E68=""), "", IF(OR(B68=0,B68=""),E68,B68 & " Bed / " &C68& " Bath "))
L69: =IF($U69 = "", "", H69/$G69) | M69: =IF($U69 = "", "", I69/$G69) | N69: =IF($U69 = "", "", J69/$G69) | O69: =IF($U69 = "", "", K69/$G69) | P69: =IF(L69="", "", L69*12) | Q69: =IF(M69="", "", M69*12) | R69: =IF(N69="", "", N69*12) | S69: =IF(O69="", "", O69*12) | T69: {=_xlfn.IFS(G69="", "", F69 = "", G69, 1, F69*G69)} | U69: =IF(AND(B69="", C69="", E69=""), "", IF(OR(B69=0,B69=""),E69,B69 & " Bed / " &C69& " Bath " &E69)) | V69: =IF(U69= "", "", B69) | W69: =IF(AND(B69="", C69="", E69=""), "", IF(OR(B69=0,B69=""),E69,B69 & " Bed / " &C69& " Bath "))
L70: =IF($U70 = "", "", H70/$G70) | M70: =IF($U70 = "", "", I70/$G70) | N70: =IF($U70 = "", "", J70/$G70) | O70: =IF($U70 = "", "", K70/$G70) | P70: =IF(L70="", "", L70*12) | Q70: =IF(M70="", "", M70*12) | R70: =IF(N70="", "", N70*12) | S70: =IF(O70="", "", O70*12) | T70: {=_xlfn.IFS(G70="", "", F70 = "", G70, 1, F70*G70)} | U70: =IF(AND(B70="", C70="", E70=""), "", IF(OR(B70=0,B70=""),E70,B70 & " Bed / " &C70& " Bath " &E70)) | V70: =IF(U70= "", "", B70) | W70: =IF(AND(B70="", C70="", E70=""), "", IF(OR(B70=0,B70=""),E70,B70 & " Bed / " &C70& " Bath "))
L71: =IF($U71 = "", "", H71/$G71) | M71: =IF($U71 = "", "", I71/$G71) | N71: =IF($U71 = "", "", J71/$G71) | O71: =IF($U71 = "", "", K71/$G71) | P71: =IF(L71="", "", L71*12) | Q71: =IF(M71="", "", M71*12) | R71: =IF(N71="", "", N71*12) | S71: =IF(O71="", "", O71*12) | T71: {=_xlfn.IFS(G71="", "", F71 = "", G71, 1, F71*G71)} | U71: =IF(AND(B71="", C71="", E71=""), "", IF(OR(B71=0,B71=""),E71,B71 & " Bed / " &C71& " Bath " &E71)) | V71: =IF(U71= "", "", B71) | W71: =IF(AND(B71="", C71="", E71=""), "", IF(OR(B71=0,B71=""),E71,B71 & " Bed / " &C71& " Bath "))
L72: =IF($U72 = "", "", H72/$G72) | M72: =IF($U72 = "", "", I72/$G72) | N72: =IF($U72 = "", "", J72/$G72) | O72: =IF($U72 = "", "", K72/$G72) | P72: =IF(L72="", "", L72*12) | Q72: =IF(M72="", "", M72*12) | R72: =IF(N72="", "", N72*12) | S72: =IF(O72="", "", O72*12) | T72: {=_xlfn.IFS(G72="", "", F72 = "", G72, 1, F72*G72)} | U72: =IF(AND(B72="", C72="", E72=""), "", IF(OR(B72=0,B72=""),E72,B72 & " Bed / " &C72& " Bath " &E72)) | V72: =IF(U72= "", "", B72) | W72: =IF(AND(B72="", C72="", E72=""), "", IF(OR(B72=0,B72=""),E72,B72 & " Bed / " &C72& " Bath "))
L73: =IF($U73 = "", "", H73/$G73) | M73: =IF($U73 = "", "", I73/$G73) | N73: =IF($U73 = "", "", J73/$G73) | O73: =IF($U73 = "", "", K73/$G73) | P73: =IF(L73="", "", L73*12) | Q73: =IF(M73="", "", M73*12) | R73: =IF(N73="", "", N73*12) | S73: =IF(O73="", "", O73*12) | T73: {=_xlfn.IFS(G73="", "", F73 = "", G73, 1, F73*G73)} | U73: =IF(AND(B73="", C73="", E73=""), "", IF(OR(B73=0,B73=""),E73,B73 & " Bed / " &C73& " Bath " &E73)) | V73: =IF(U73= "", "", B73) | W73: =IF(AND(B73="", C73="", E73=""), "", IF(OR(B73=0,B73=""),E73,B73 & " Bed / " &C73& " Bath "))
L74: =IF($U74 = "", "", H74/$G74) | M74: =IF($U74 = "", "", I74/$G74) | N74: =IF($U74 = "", "", J74/$G74) | O74: =IF($U74 = "", "", K74/$G74) | P74: =IF(L74="", "", L74*12) | Q74: =IF(M74="", "", M74*12) | R74: =IF(N74="", "", N74*12) | S74: =IF(O74="", "", O74*12) | T74: {=_xlfn.IFS(G74="", "", F74 = "", G74, 1, F74*G74)} | U74: =IF(AND(B74="", C74="", E74=""), "", IF(OR(B74=0,B74=""),E74,B74 & " Bed / " &C74& " Bath " &E74)) | V74: =IF(U74= "", "", B74) | W74: =IF(AND(B74="", C74="", E74=""), "", IF(OR(B74=0,B74=""),E74,B74 & " Bed / " &C74& " Bath "))
L75: =IF($U75 = "", "", H75/$G75) | M75: =IF($U75 = "", "", I75/$G75) | N75: =IF($U75 = "", "", J75/$G75) | O75: =IF($U75 = "", "", K75/$G75) | P75: =IF(L75="", "", L75*12) | Q75: =IF(M75="", "", M75*12) | R75: =IF(N75="", "", N75*12) | S75: =IF(O75="", "", O75*12) | T75: {=_xlfn.IFS(G75="", "", F75 = "", G75, 1, F75*G75)} | U75: =IF(AND(B75="", C75="", E75=""), "", IF(OR(B75=0,B75=""),E75,B75 & " Bed / " &C75& " Bath " &E75)) | V75: =IF(U75= "", "", B75) | W75: =IF(AND(B75="", C75="", E75=""), "", IF(OR(B75=0,B75=""),E75,B75 & " Bed / " &C75& " Bath "))
L76: =IF($U76 = "", "", H76/$G76) | M76: =IF($U76 = "", "", I76/$G76) | N76: =IF($U76 = "", "", J76/$G76) | O76: =IF($U76 = "", "", K76/$G76) | P76: =IF(L76="", "", L76*12) | Q76: =IF(M76="", "", M76*12) | R76: =IF(N76="", "", N76*12) | S76: =IF(O76="", "", O76*12) | T76: {=_xlfn.IFS(G76="", "", F76 = "", G76, 1, F76*G76)} | U76: =IF(AND(B76="", C76="", E76=""), "", IF(OR(B76=0,B76=""),E76,B76 & " Bed / " &C76& " Bath " &E76)) | V76: =IF(U76= "", "", B76) | W76: =IF(AND(B76="", C76="", E76=""), "", IF(OR(B76=0,B76=""),E76,B76 & " Bed / " &C76& " Bath "))
L77: =IF($U77 = "", "", H77/$G77) | M77: =IF($U77 = "", "", I77/$G77) | N77: =IF($U77 = "", "", J77/$G77) | O77: =IF($U77 = "", "", K77/$G77) | P77: =IF(L77="", "", L77*12) | Q77: =IF(M77="", "", M77*12) | R77: =IF(N77="", "", N77*12) | S77: =IF(O77="", "", O77*12) | T77: {=_xlfn.IFS(G77="", "", F77 = "", G77, 1, F77*G77)} | U77: =IF(AND(B77="", C77="", E77=""), "", IF(OR(B77=0,B77=""),E77,B77 & " Bed / " &C77& " Bath " &E77)) | V77: =IF(U77= "", "", B77) | W77: =IF(AND(B77="", C77="", E77=""), "", IF(OR(B77=0,B77=""),E77,B77 & " Bed / " &C77& " Bath "))
K78: =IF(G78= "", "", IF(H78=0,I78,H78)) | L78: =IF($U78 = "", "", H78/$G78) | M78: =IF($U78 = "", "", I78/$G78) | N78: =IF($U78 = "", "", J78/$G78) | O78: =IF($U78 = "", "", K78/$G78) | P78: =IF(L78="", "", L78*12) | Q78: =IF(M78="", "", M78*12) | R78: =IF(N78="", "", N78*12) | S78: =IF(O78="", "", O78*12) | T78: {=_xlfn.IFS(G78="", "", F78 = "", G78, 1, F78*G78)} | U78: =IF(AND(B78="", C78="", E78=""), "", IF(OR(B78=0,B78=""),E78,B78 & " Bed / " &C78& " Bath " &E78)) | V78: =IF(U78= "", "", B78) | W78: =IF(AND(B78="", C78="", E78=""), "", IF(OR(B78=0,B78=""),E78,B78 & " Bed / " &C78& " Bath "))
K79: =IF(G79= "", "", IF(H79=0,I79,H79)) | L79: =IF($U79 = "", "", H79/$G79) | M79: =IF($U79 = "", "", I79/$G79) | N79: =IF($U79 = "", "", J79/$G79) | O79: =IF($U79 = "", "", K79/$G79) | P79: =IF(L79="", "", L79*12) | Q79: =IF(M79="", "", M79*12) | R79: =IF(N79="", "", N79*12) | S79: =IF(O79="", "", O79*12) | T79: {=_xlfn.IFS(G79="", "", F79 = "", G79, 1, F79*G79)} | U79: =IF(AND(B79="", C79="", E79=""), "", IF(OR(B79=0,B79=""),E79,B79 & " Bed / " &C79& " Bath " &E79)) | V79: =IF(U79= "", "", B79) | W79: =IF(AND(B79="", C79="", E79=""), "", IF(OR(B79=0,B79=""),E79,B79 & " Bed / " &C79& " Bath "))
K80: =IF(G80= "", "", IF(H80=0,I80,H80)) | L80: =IF($U80 = "", "", H80/$G80) | M80: =IF($U80 = "", "", I80/$G80) | N80: =IF($U80 = "", "", J80/$G80) | O80: =IF($U80 = "", "", K80/$G80) | P80: =IF(L80="", "", L80*12) | Q80: =IF(M80="", "", M80*12) | R80: =IF(N80="", "", N80*12) | S80: =IF(O80="", "", O80*12) | T80: {=_xlfn.IFS(G80="", "", F80 = "", G80, 1, F80*G80)} | U80: =IF(AND(B80="", C80="", E80=""), "", IF(OR(B80=0,B80=""),E80,B80 & " Bed / " &C80& " Bath " &E80)) | V80: =IF(U80= "", "", B80) | W80: =IF(AND(B80="", C80="", E80=""), "", IF(OR(B80=0,B80=""),E80,B80 & " Bed / " &C80& " Bath "))
K81: =IF(G81= "", "", IF(H81=0,I81,H81)) | L81: =IF($U81 = "", "", H81/$G81) | M81: =IF($U81 = "", "", I81/$G81) | N81: =IF($U81 = "", "", J81/$G81) | O81: =IF($U81 = "", "", K81/$G81) | P81: =IF(L81="", "", L81*12) | Q81: =IF(M81="", "", M81*12) | R81: =IF(N81="", "", N81*12) | S81: =IF(O81="", "", O81*12) | T81: {=_xlfn.IFS(G81="", "", F81 = "", G81, 1, F81*G81)} | U81: =IF(AND(B81="", C81="", E81=""), "", IF(OR(B81=0,B81=""),E81,B81 & " Bed / " &C81& " Bath " &E81)) | V81: =IF(U81= "", "", B81) | W81: =IF(AND(B81="", C81="", E81=""), "", IF(OR(B81=0,B81=""),E81,B81 & " Bed / " &C81& " Bath "))
K82: =IF(G82= "", "", IF(H82=0,I82,H82)) | L82: =IF($U82 = "", "", H82/$G82) | M82: =IF($U82 = "", "", I82/$G82) | N82: =IF($U82 = "", "", J82/$G82) | O82: =IF($U82 = "", "", K82/$G82) | P82: =IF(L82="", "", L82*12) | Q82: =IF(M82="", "", M82*12) | R82: =IF(N82="", "", N82*12) | S82: =IF(O82="", "", O82*12) | T82: {=_xlfn.IFS(G82="", "", F82 = "", G82, 1, F82*G82)} | U82: =IF(AND(B82="", C82="", E82=""), "", IF(OR(B82=0,B82=""),E82,B82 & " Bed / " &C82& " Bath " &E82)) | V82: =IF(U82= "", "", B82) | W82: =IF(AND(B82="", C82="", E82=""), "", IF(OR(B82=0,B82=""),E82,B82 & " Bed / " &C82& " Bath "))
K83: =IF(G83= "", "", IF(H83=0,I83,H83)) | L83: =IF($U83 = "", "", H83/$G83) | M83: =IF($U83 = "", "", I83/$G83) | N83: =IF($U83 = "", "", J83/$G83) | O83: =IF($U83 = "", "", K83/$G83) | P83: =IF(L83="", "", L83*12) | Q83: =IF(M83="", "", M83*12) | R83: =IF(N83="", "", N83*12) | S83: =IF(O83="", "", O83*12) | T83: {=_xlfn.IFS(G83="", "", F83 = "", G83, 1, F83*G83)} | U83: =IF(AND(B83="", C83="", E83=""), "", IF(OR(B83=0,B83=""),E83,B83 & " Bed / " &C83& " Bath " &E83)) | V83: =IF(U83= "", "", B83) | W83: =IF(AND(B83="", C83="", E83=""), "", IF(OR(B83=0,B83=""),E83,B83 & " Bed / " &C83& " Bath "))
K84: =IF(G84= "", "", IF(H84=0,I84,H84)) | L84: =IF($U84 = "", "", H84/$G84) | M84: =IF($U84 = "", "", I84/$G84) | N84: =IF($U84 = "", "", J84/$G84) | O84: =IF($U84 = "", "", K84/$G84) | P84: =IF(L84="", "", L84*12) | Q84: =IF(M84="", "", M84*12) | R84: =IF(N84="", "", N84*12) | S84: =IF(O84="", "", O84*12) | T84: {=_xlfn.IFS(G84="", "", F84 = "", G84, 1, F84*G84)} | U84: =IF(AND(B84="", C84="", E84=""), "", IF(OR(B84=0,B84=""),E84,B84 & " Bed / " &C84& " Bath " &E84)) | V84: =IF(U84= "", "", B84) | W84: =IF(AND(B84="", C84="", E84=""), "", IF(OR(B84=0,B84=""),E84,B84 & " Bed / " &C84& " Bath "))
K85: =IF(G85= "", "", IF(H85=0,I85,H85)) | L85: =IF($U85 = "", "", H85/$G85) | M85: =IF($U85 = "", "", I85/$G85) | N85: =IF($U85 = "", "", J85/$G85) | O85: =IF($U85 = "", "", K85/$G85) | P85: =IF(L85="", "", L85*12) | Q85: =IF(M85="", "", M85*12) | R85: =IF(N85="", "", N85*12) | S85: =IF(O85="", "", O85*12) | T85: {=_xlfn.IFS(G85="", "", F85 = "", G85, 1, F85*G85)} | U85: =IF(AND(B85="", C85="", E85=""), "", IF(OR(B85=0,B85=""),E85,B85 & " Bed / " &C85& " Bath " &E85)) | V85: =IF(U85= "", "", B85) | W85: =IF(AND(B85="", C85="", E85=""), "", IF(OR(B85=0,B85=""),E85,B85 & " Bed / " &C85& " Bath "))
K86: =IF(G86= "", "", IF(H86=0,I86,H86)) | L86: =IF($U86 = "", "", H86/$G86) | M86: =IF($U86 = "", "", I86/$G86) | N86: =IF($U86 = "", "", J86/$G86) | O86: =IF($U86 = "", "", K86/$G86) | P86: =IF(L86="", "", L86*12) | Q86: =IF(M86="", "", M86*12) | R86: =IF(N86="", "", N86*12) | S86: =IF(O86="", "", O86*12) | T86: {=_xlfn.IFS(G86="", "", F86 = "", G86, 1, F86*G86)} | U86: =IF(AND(B86="", C86="", E86=""), "", IF(OR(B86=0,B86=""),E86,B86 & " Bed / " &C86& " Bath " &E86)) | V86: =IF(U86= "", "", B86) | W86: =IF(AND(B86="", C86="", E86=""), "", IF(OR(B86=0,B86=""),E86,B86 & " Bed / " &C86& " Bath "))
K87: =IF(G87= "", "", IF(H87=0,I87,H87)) | L87: =IF($U87 = "", "", H87/$G87) | M87: =IF($U87 = "", "", I87/$G87) | N87: =IF($U87 = "", "", J87/$G87) | O87: =IF($U87 = "", "", K87/$G87) | P87: =IF(L87="", "", L87*12) | Q87: =IF(M87="", "", M87*12) | R87: =IF(N87="", "", N87*12) | S87: =IF(O87="", "", O87*12) | T87: {=_xlfn.IFS(G87="", "", F87 = "", G87, 1, F87*G87)} | U87: =IF(AND(B87="", C87="", E87=""), "", IF(OR(B87=0,B87=""),E87,B87 & " Bed / " &C87& " Bath " &E87)) | V87: =IF(U87= "", "", B87) | W87: =IF(AND(B87="", C87="", E87=""), "", IF(OR(B87=0,B87=""),E87,B87 & " Bed / " &C87& " Bath "))
K88: =IF(G88= "", "", IF(H88=0,I88,H88)) | L88: =IF($U88 = "", "", H88/$G88) | M88: =IF($U88 = "", "", I88/$G88) | N88: =IF($U88 = "", "", J88/$G88) | O88: =IF($U88 = "", "", K88/$G88) | P88: =IF(L88="", "", L88*12) | Q88: =IF(M88="", "", M88*12) | R88: =IF(N88="", "", N88*12) | S88: =IF(O88="", "", O88*12) | T88: {=_xlfn.IFS(G88="", "", F88 = "", G88, 1, F88*G88)} | U88: =IF(AND(B88="", C88="", E88=""), "", IF(OR(B88=0,B88=""),E88,B88 & " Bed / " &C88& " Bath " &E88)) | V88: =IF(U88= "", "", B88) | W88: =IF(AND(B88="", C88="", E88=""), "", IF(OR(B88=0,B88=""),E88,B88 & " Bed / " &C88& " Bath "))
K89: =IF(G89= "", "", IF(H89=0,I89,H89)) | L89: =IF($U89 = "", "", H89/$G89) | M89: =IF($U89 = "", "", I89/$G89) | N89: =IF($U89 = "", "", J89/$G89) | O89: =IF($U89 = "", "", K89/$G89) | P89: =IF(L89="", "", L89*12) | Q89: =IF(M89="", "", M89*12) | R89: =IF(N89="", "", N89*12) | S89: =IF(O89="", "", O89*12) | T89: {=_xlfn.IFS(G89="", "", F89 = "", G89, 1, F89*G89)} | U89: =IF(AND(B89="", C89="", E89=""), "", IF(OR(B89=0,B89=""),E89,B89 & " Bed / " &C89& " Bath " &E89)) | V89: =IF(U89= "", "", B89) | W89: =IF(AND(B89="", C89="", E89=""), "", IF(OR(B89=0,B89=""),E89,B89 & " Bed / " &C89& " Bath "))
... K214: =IF(G214= "", "", IF(H214=0,I214,H214)) | L214: =IF($U214 = "", "", H214/$G214) | M214: =IF($U214 = "", "", I214/$G214) | N214: =IF($U214 = "", "", J214/$G214) | O214: =IF($U214 = "", "", K214/$G214) | P214: =IF(L214="", "", L214*12) | Q214: =IF(M214="", "", M214*12) | R214: =IF(N214="", "", N214*12) | S214: =IF(O214="", "", O214*12) | T214: {=_xlfn.IFS(G214="", "", F214 = "", G214, 1, F214*G214)} | U214: =IF(AND(B214="", C214="", E214=""), "", IF(OR(B214=0,B214=""),E214,B214 & " Bed / " &C214& " Bath " &E214)) | V214: =IF(U214= "", "", B214) | W214: =IF(AND(B214="", C214="", E214=""), "", IF(OR(B214=0,B214=""),E214,B214 & " Bed / " &C214& " Bath "))
V215: =IF(U215= "", "", B215) | W215: =IF(AND(B215="", C215="", E215=""), "", IF(OR(B215=0,B215=""),E215,B215 & " Bed / " &C215& " Bath "))
V216: =IF(U216= "", "", B216) | W216: =IF(AND(B216="", C216="", E216=""), "", IF(OR(B216=0,B216=""),E216,B216 & " Bed / " &C216& " Bath "))
V217: =IF(U217= "", "", B217) | W217: =IF(AND(B217="", C217="", E217=""), "", IF(OR(B217=0,B217=""),E217,B217 & " Bed / " &C217& " Bath "))
V218: =IF(U218= "", "", B218) | W218: =IF(AND(B218="", C218="", E218=""), "", IF(OR(B218=0,B218=""),E218,B218 & " Bed / " &C218& " Bath "))
V219: =IF(U219= "", "", B219) | W219: =IF(AND(B219="", C219="", E219=""), "", IF(OR(B219=0,B219=""),E219,B219 & " Bed / " &C219& " Bath "))
V220: =IF(U220= "", "", B220) | W220: =IF(AND(B220="", C220="", E220=""), "", IF(OR(B220=0,B220=""),E220,B220 & " Bed / " &C220& " Bath "))
V221: =IF(U221= "", "", B221) | W221: =IF(AND(B221="", C221="", E221=""), "", IF(OR(B221=0,B221=""),E221,B221 & " Bed / " &C221& " Bath "))
V222: =IF(U222= "", "", B222) | W222: =IF(AND(B222="", C222="", E222=""), "", IF(OR(B222=0,B222=""),E222,B222 & " Bed / " &C222& " Bath "))
V223: =IF(U223= "", "", B223) | W223: =IF(AND(B223="", C223="", E223=""), "", IF(OR(B223=0,B223=""),E223,B223 & " Bed / " &C223& " Bath "))
V224: =IF(U224= "", "", B224) | W224: =IF(AND(B224="", C224="", E224=""), "", IF(OR(B224=0,B224=""),E224,B224 & " Bed / " &C224& " Bath "))
V225: =IF(U225= "", "", B225) | W225: =IF(AND(B225="", C225="", E225=""), "", IF(OR(B225=0,B225=""),E225,B225 & " Bed / " &C225& " Bath "))
V226: =IF(U226= "", "", B226) | W226: =IF(AND(B226="", C226="", E226=""), "", IF(OR(B226=0,B226=""),E226,B226 & " Bed / " &C226& " Bath "))
... V642: =IF(U642= "", "", B642) | W642: =IF(AND(B642="", C642="", E642=""), "", IF(OR(B642=0,B642=""),E642,B642 & " Bed / " &C642& " Bath "))

Sheet Rent Roll Summary Calculations
A1: {=Unit_Amt_Summary} -> 0 | B1: {=Unit_Type_Summary} | C1: {=Summary_SQFT_UNIT} -> 0 | D1: {=Summary_SCHEDULED_RENTS} -> 0 | E1: {=Summary_MARKET_RENTS} -> 0

Sheet Calculations
B1: SED_ | C1: NEW_ | D1: Mezz_ | E1: Refi_ | X1: Operating Statement Columns
A2: Variable | B2: Seller's Existing Debt | C2: New Loan | D2: Mezzanine Loan | E2: Refinance Loan | F2: Current | H2: Variable | I2: Value | J2: Stored Value | X2: NumColumns | Y2: 2
A3: Rate_Compounding_Switch | B3: {=_xlfn.SWITCH(SED_Compounding_Switch, "Monthly", 12, "Semi-Annually", 2)} -> #N/A | C3: {=IFERROR(_xlfn.SWITCH(NEW_Compounding_Switch, "Monthly", 12, "Semi-Annually", 2),0)} -> 0 | D3: {=_xlfn.SWITCH(INDIRECT(D1& "Compounding_Switch"), "Monthly", 12, "Semi-Annually", 2)} -> #N/A | E3: {=_xlfn.SWITCH(INDIRECT(E1& "Compounding_Switch"), "Monthly", 12, "Semi-Annually", 2)} -> #N/A | H3: Variable_Rent_Roll_Detail | P3: Initial Cash- | Q3: Year 10 | R3: Year 10 | X3: Value 1 | Y3: Prior 2
A4: Rate_Period_Switch | B4: =ROUNDDOWN(YEARFRAC(SED_Origination_Date,Date_of_Analysis)*SED_Rate_Compounding_Switch,0) -> #N/A | C4: =ROUNDDOWN(YEARFRAC(NEW_Origination_Date,Date_of_Analysis)*NEW_Rate_Compounding_Switch,0) -> 0 | D4: =ROUNDDOWN(YEARFRAC(Mezz_Origination_Date,Date_of_Analysis)*Mezz_Rate_Compounding_Switch,0) -> #N/A | E4: =ROUNDDOWN(YEARFRAC(Mezz_Origination_Date,Date_of_Analysis)*Mezz_Rate_Compounding_Switch,0) -> #N/A | H4: hide_sale_price | I4: FALSE | J4: =hide_sale_price -> #NAME? | M4: Purchase | N4: ='Operating Statement'!O4 -> CURRENT | O4: ='Operating Statement'!Q4 -> YEAR 1 | P4: on-Cash | Q4: Unlevered | R4: Levered | S4: Price | T4: Price | U4: ='Operating Statement'!Q4 -> YEAR 1 | X4: Value 2 | Y4: Prior 1
A5: I_Adj | B5: =(SED_Interest_Rate/SED_Rate_Compounding_Switch + 1) ^ (SED_Rate_Compounding_Switch/12)-1 -> #N/A | C5: =(NEW_Interest_Rate/NEW_Rate_Compounding_Switch + 1) ^ (NEW_Rate_Compounding_Switch/12)-1 -> #DIV/0! | D5: =(Mezz_Interest_Rate/Mezz_Rate_Compounding_Switch + 1) ^ (Mezz_Rate_Compounding_Switch/12)-1 -> #N/A | E5: =(Refi_Interest_Rate/Refi_Rate_Compounding_Switch + 1) ^ (Refi_Rate_Compounding_Switch/12)-1 -> #N/A | H5: NewIncrement | I5: =IF(Switch_Pricing_Variable = "CAP Rate", Cap_Increment, Price_Increments) -> #NAME? | M5: Price | N5: Cap Rate | O5: Cap Rate | P5: Return | Q5: IRR | R5: IRR | S5: Per SF | T5: Per Unit | U5: GRM | X5: Value 3 | Y5: Current
A6: Amort_Periods | B6: =SED_Amort*12 -> 0 | C6: =NEW_Amort*12 -> 0 | D6: =Mezz_Amort*12 -> 0 | E6: =Refi_Amort*12 -> 0 | H6: debt_service | I6: {=_xlfn.IFS(AF_Type = "All Cash", 0, AF_Type = "Financed - New Loan", AF_Loan_Payment * 12, "Financed - Assumed Loan", SED_Loan_Payment * 12)} -> #NAME? | J6: {=debt_service} -> 0 | X6: Value 4 | Y6: Year 1
A7: Amort_P_Adj | B7: =SED_Amort_Periods -> 0 | C7: =NEW_Amort_Periods -> 0 | D7: =Mezz_Amort_Periods -> 0 | E7: =Refi_Amort_Periods -> 0 | H7: cap_over_lease | X7: Value 5 | Y7: Year 2
A8: Int_Only_Period | B8: {=SED_Rate_Period_Switch-(SED_Interest_Only/12 )*SED_Rate_Compounding_Switch} -> #N/A | C8: =NEW_Rate_Period_Switch-(NEW_Interest_Only/12 )*NEW_Rate_Compounding_Switch -> 0 | D8: =Mezz_Rate_Period_Switch-(Mezz_Interest_Only/12 )*Mezz_Rate_Compounding_Switch -> #N/A | E8: =IF(Refi_Rate_Period_Switch-(Refi_Interest_Only/12 )*Refi_Rate_Compounding_Switch <0,0,Refi_Rate_Period_Switch-(Refi_Interest_Only/12 )*Refi_Rate_Compounding_Switch) -> #N/A | H8: cap_rate | I8: =IFERROR(_xlfn.SINGLE(net_operating_income)/sale_price,"") | J8: {=cap_rate} -> 0
A9: Orig_Loan_Amount | B9: =SED_Orig_Loan_Amount -> 0 | C9: =NEW_LTV * sale_price -> 0 | D9: =Mezz_LTV*sale_price -> 0 | E9: =IFERROR(VLOOKUP(DATE(YEAR(Refi_Origination_Date),MONTH(Refi_Origination_Date),1)-1,'Loan Amort Table'!C6:H500,6)+VLOOKUP(DATE(YEAR(Refi_Origination_Date),MONTH(Refi_Origination_Date),1)-1,'Loan Amort Table'!U6:Z500,6),"") | H9: down_payment | I9: =IF(AF_Type = "Financed - New Loan", IF(AF_Down_Payment_Switch = "Down Payment (%)", AF_Down_Payment * sale_price, AF_Down_Payment),0) -> #NAME? | J9: {=down_payment} -> 0 | O9: Initial Cash-
A10: CUMPRINC | B10: =IFERROR(CUMPRINC(SED_I_Adj,SED_Amort_P_Adj, SED_Orig_Loan_Amount,1, SED_Int_Only_Period,0),0) -> 0 | C10: =IFERROR(CUMPRINC(NEW_I_Adj,NEW_Amort_P_Adj, NEW_Orig_Loan_Amount,1, NEW_Int_Only_Period,0),0) -> 0 | D10: {=IFERROR(CUMPRINC(Mezz_I_Adj,Mezz_Amort_P_Adj, Mezz_Orig_Loan_Amount,1, Mezz_Int_Only_Period,0),0)} -> 0 | E10: =IFERROR(CUMPRINC(Refi_I_Adj,Refi_Amort_P_Adj, Refi_Orig_Loan_Amount,1, Refi_Int_Only_Period,0),0) -> 0 | H10: exp_reimbursement | I10: =_xlfn.SINGLE(exp_reimbursement) -> 0 | J10: =_xlfn.SINGLE(exp_reimbursement) -> 0 | N10: Year One | O10: on-Cash | P10: Unleveraged | Q10: Leveraged | R10: Price | S10: Price | T10: Year One
A11: Loan_Balance | B11: =SED_Orig_Loan_Amount + SED_CUMPRINC -> 0 | C11: =NEW_Orig_Loan_Amount + NEW_CUMPRINC -> 0 | D11: =SUM(D9:D10) -> 0 | E11: =SUM(E9:E10) -> 0 | F11: =IF(Acq_Financing_Type_Switch="Financed - Assumed Loan",SED_Loan_Balance,NEW_Loan_Balance) -> 0 | H11: gross_scheduled_income | I11: =Annual_Rent -> #NAME? | J11: {=gross_scheduled_income} -> 0 | M11: Price | N11: Cap Rate | O11: Return | P11: IRR | Q11: IRR | R11: Per SF | S11: Per Unit | T11: GRM
A12: Loan_Payment | B12: {=IF(SED_Int_Only_Period<0, SED_IPMT,SED_PMT)} -> #N/A | C12: =IFERROR(IF(NEW_Int_Only_Period<0, NEW_IPMT,NEW_PMT),0) -> 0 | D12: {=IF(Mezz_Int_Only_Period<0, Mezz_IPMT,Mezz_PMT)} -> #N/A | E12: =IF(Refi_Int_Only_Period<0, Refi_IPMT,Refi_PMT) -> #N/A | H12: guarantor | I12: =_xlfn.SINGLE(guarantor) -> 0 | J12: =_xlfn.SINGLE(guarantor) -> 0 | M12: {=Price} -> 0 | N12: ='Pricing Detail'!$H$13 -> 0 | O12: ='Pricing Detail'!$G$15 -> 0 | P12: ='Cash Flow'!$P$45 -> 0 | Q12: ='Cash Flow'!$P$46 -> 0 | R12: ='Pricing Detail'!$G$8 -> 0 | S12: ='Pricing Detail'!$G$7 -> 0 | T12: ='Pricing Detail'!C2 -> 0
A13: Loan_Due_Date | B13: {=EDATE(SED_Origination_Date, SED_Term*12-1)} -> #NUM! | C13: {=EDATE(NEW_Origination_Date, NEW_Term*12-1)} -> #NUM! | D13: =IF(Acq_Financing_Type_Switch= "Financed - Assumed Loan", SED_Loan_Due_Date,NEW_Loan_Due_Date) -> #NUM! | E13: =IFERROR(DATE(YEAR(Refi_Origination_Date)+Refi_Term, MONTH(Refi_Origination_Date)-1, DAY(Refi_Origination_Date)),"") | H13: lease_term | I13: =_xlfn.SINGLE(IF(_xlfn.SINGLE(sale_leaseback)= TRUE, AF_Orig_Term,"")) | J13: {=lease_term} -> 0 | M13: =M14+Price_Increments -> 0
A14: PMT | B14: ='Debt Input'!F29 -> 0 | C14: =IFERROR(PMT(NEW_I_Adj,NEW_Amort_Periods,NEW_Orig_Loan_Amount),0) -> 0 | D14: ='Debt Input'!J29 -> 0 | E14: ='Debt Input'!L29 -> 0 | F14: =IF(Acq_Financing_Type_Switch="Financed - Assumed Loan",SED_PMT,NEW_PMT) -> 0 | H14: lease_end | I14: =_xlfn.SINGLE(IF(_xlfn.SINGLE(sale_leaseback)=FALSE, Lease_Commencement,"")) -> #NAME? | J14: {=lease_end} -> 0 | M14: =M15+Price_Increments -> 0
A15: IPMT | B15: =IPMT(SED_I_Adj,1,SED_Amort_P_Adj, SED_Orig_Loan_Amount,0) -> #N/A | C15: =IFERROR(IPMT(NEW_I_Adj,1,NEW_Amort_Periods, NEW_Orig_Loan_Amount,0),0) -> 0 | D15: =IPMT(Mezz_I_Adj,1,Mezz_Amort_P_Adj, Mezz_Orig_Loan_Amount,0) -> #N/A | E15: =IPMT(Refi_I_Adj,1,Refi_Amort_P_Adj, Refi_Orig_Loan_Amount,0) -> #N/A | H15: lease_type | I15: =_xlfn.SINGLE(lease_type) -> 0 | M15: =M16+Price_Increments -> 0
A16: PPMT | B16: =PPMT(SED_I_Adj,1, SED_Amort_P_Adj, SED_Orig_Loan_Amount,0) -> #N/A | C16: =IFERROR(PPMT(NEW_I_Adj,1, NEW_Amort_P_Adj, NEW_Orig_Loan_Amount,0),0) -> 0 | D16: =PPMT(Mezz_I_Adj,1, Mezz_Amort_P_Adj, Mezz_Orig_Loan_Amount,0) -> #N/A | E16: =PPMT(Refi_I_Adj,1, Refi_Amort_P_Adj, Refi_Orig_Loan_Amount,0) -> #N/A | H16: loan_type | I16: =AF_Type -> #NAME? | J16: {=loan_type} -> New Loan | M16: =M17+Price_Increments -> 0
A17: Loan Constant | B17: =-SED_Loan_Payment/SED_Orig_Loan_Amount*12 -> #N/A | C17: =IFERROR(-NEW_Loan_Payment/NEW_Orig_Loan_Amount*12,0) -> 0 | D17: =-Mezz_Loan_Payment/Mezz_Orig_Loan_Amount*12 -> #N/A | E17: =-Refi_Loan_Payment/Refi_Orig_Loan_Amount*12 -> #N/A | H17: net_operating_income | I17: =_xlfn.SINGLE(net_operating_income) -> 0 | M17: =M18+Price_Increments -> 0
A18: FV | B18: =FV(SED_I_Adj, SED_Term*12, SED_PMT, SED_Orig_Loan_Amount) -> #N/A | C18: =FV(NEW_I_Adj, NEW_Term*12, NEW_PMT, NEW_Orig_Loan_Amount) -> #DIV/0! | D18: =FV(Mezz_I_Adj, Mezz_Term*12, Mezz_PMT, Mezz_Orig_Loan_Amount) -> #N/A | E18: =FV(Refi_I_Adj, Refi_Term*12, Refi_PMT, Refi_Orig_Loan_Amount) -> #N/A | H18: operating_expenses | I18: =_xlfn.SINGLE(operating_expenses) -> 0 | M18: {=Price} -> 0
A19: Time Remaining | B19: =ROUNDUP(YEARFRAC(SED_Origination_Date, SED_Loan_Due_Date)*12,0)+1 -> #NUM! | C19: =ROUNDUP(YEARFRAC(NEW_Origination_Date, NEW_Loan_Due_Date)*12,0)+1 -> #NUM! | D19: =ROUNDUP(YEARFRAC(Mezz_Origination_Date, Mezz_Loan_Due_Date)*12,0)+1 -> #NUM! | E19: =ROUNDUP(YEARFRAC(Refi_Origination_Date, Refi_Loan_Due_Date)*12,0)+1 -> #VALUE! | H19: principal_reduction_yr_1 | I19: {=principal_reduction_yr_1} -> 0 | M19: =M18-Price_Increments -> 0
A20: CUMIPMT | H20: sale_leaseback | I20: FALSE | M20: =M19-Price_Increments -> 0
A21: Refi_Term | B21: =IFERROR(ROUNDUP(YEARFRAC(SED_Origination_Date, Refi_Origination_Date)*12-SED_Interest_Only,0),"") -> 0 | D21: =IFERROR(ROUNDUP(YEARFRAC(Mezz_Origination_Date, Refi_Origination_Date)*12-Mezz_Interest_Only,0),"") -> 0 | E21: =IFERROR(ROUNDUP(YEARFRAC(Refi_Origination_Date, Refi_Origination_Date)*12-Refi_Interest_Only,0),"") -> 0 | H21: sale_price | I21: =sale_price -> 0 | M21: =M20-Price_Increments -> 0
A22: FV_Refi | B22: =FV(SED_I_Adj,SED_Refi_Term,SED_PMT,SED_Orig_Loan_Amount) -> #N/A | D22: {=FV(Mezz_I_Adj,Mezz_Refi_Term,Mezz_PMT,Mezz_Orig_Loan_Amount)} -> #N/A | E22: {=FV(Refi_I_Adj,Refi_Refi_Term,Refi_PMT,Refi_Orig_Loan_Amount)} -> #N/A | H22: tenant | I22: =_xlfn.SINGLE(tenant) -> 0 | M22: =M21-Price_Increments -> 0
A23: Priciple Reduction 1st Year | B23: {=IFERROR( IF(SED_Interest_Only>=12,0, IF(SED_Interest_Only =0,- CUMPRINC( SED_I_Adj,SED_Amort_Periods,SED_Orig_Loan_Amount,1,12,0),IF(AND(SED_Interest_Only > 0, SED_Interest_Only < 12),-CUMPRINC( SED_I_Adj,SED_Amort_Periods,SED_Orig_Loan_Amount,SED_Int_Only_Period,12,0),"")) ),"")} | H23: Gross Annualized Rents | M23: =M22-Price_Increments -> 0
A24: _Term | B24: =SED_Term -> 0 | C24: =NEW_Term -> 0 | D24: =ROUND(((YEAR(Mezz_Loan_Due_Date)-YEAR(Mezz_Origination_Date))*12+MONTH(Mezz_Loan_Due_Date)-MONTH(Mezz_Origination_Date)+1)/12,0) -> #NUM! | E24: =Refi_Term -> 0 | H24: Units | I24: =_xlfn.XLOOKUP(Label_Total, 'Rent Roll Calculations'!A3:A31,'Rent Roll Calculations'!B3:B31) -> 0
A25: _Begin_PMT | B25: =EDATE(SED_Origination_Date,SED_Interest_Only) -> 0 | C25: =EDATE(NEW_Origination_Date,NEW_Interest_Only) -> 0 | D25: =EDATE(Mezz_Origination_Date,Mezz_Interest_Only) -> 0 | E25: =EDATE(Refi_Origination_Date,Refi_Interest_Only) -> 0 | H25: Total_Sq_Ft | I25: =_xlfn.XLOOKUP(Label_Total, 'Rent Roll Calculations'!A3:A31,'Rent Roll Calculations'!C3:C31) -> 0
A26: Loan_Origination_Fee | F26: =IF(Acq_Financing_Type_Switch = "Financed - Assumed Loan", SED_Origination_Fee*SED_Loan_Balance,NEW_Origination_Fee*NEW_Orig_Loan_Amount) -> 0 | H26: SED_to_Refi_Period | I26: =DATEDIF(SED_Origination_Date,Refi_Origination_Date,"m") -> 0
A27: Interest_Only_PMT | B27: =SED_Loan_Balance * SED_I_Adj -> #N/A | C27: =NEW_Loan_Balance * NEW_I_Adj -> #DIV/0! | D27: =Mezz_Loan_Balance * SED_I_Adj -> #N/A | E27: =Refi_Loan_Balance * SED_I_Adj -> #N/A
M28: ='Equity Returns Options'!C3 -> REFINANCE | N28: ='Equity Returns Options'!F3 -> SELL & EXCHANGE | O28: ='Equity Returns Options'!I3 -> HOLD
M29: {=IF(M28="Sell",NA(),INDEX(Equity_Returns_Input,15,MATCH(M28,Equity_Returns_Input_Headers,0)+1))} -> 0 | N29: {=IF(N28="Sell",NA(),INDEX(Equity_Returns_Input,15,MATCH(N28,Equity_Returns_Input_Headers,0)+1))} -> 0 | O29: {=IF(O28="Sell",NA(),INDEX(Equity_Returns_Input,15,MATCH(O28,Equity_Returns_Input_Headers,0)+1))} -> 0
M31: =M28 -> REFINANCE | N31: =N28 -> SELL & EXCHANGE | O31: =O28 -> HOLD
M32: {=IF(M28="Sell",NA(),INDEX(Equity_Returns_Input,16,MATCH(M28,Equity_Returns_Input_Headers,0)+1))} -> 0 | N32: {=IF(N28="Sell",NA(),INDEX(Equity_Returns_Input,16,MATCH(N28,Equity_Returns_Input_Headers,0)+1))} | O32: {=IF(O28="Sell",NA(),INDEX(Equity_Returns_Input,16,MATCH(O28,Equity_Returns_Input_Headers,0)+1))}

Sheet Annualized Rents
A1: Monthly Income - Current | B1: {=IFERROR(SUMPRODUCT(_xlfn._xlws.FILTER(INDEX(Rent_Roll_Input_Total, 0,5),INDEX(Rent_Roll_Input_Total, 0,20) ='Rent Roll Input'!$U$4), _xlfn._xlws.FILTER(INDEX(Rent_Roll_Input_Total, 0,7),INDEX(Rent_Roll_Input_Total, 0,20) ='Rent Roll Input'!$U$4))*12,0)} -> 0 | C1: Gross Current Rent
A2: Monthly Income - Scheduled | B2: {=IFERROR(SUMPRODUCT(_xlfn._xlws.FILTER(INDEX(Rent_Roll_Input_Total, 0,5),INDEX(Rent_Roll_Input_Total, 0,20) ='Rent Roll Input'!$U$4), _xlfn._xlws.FILTER(INDEX(Rent_Roll_Input_Total, 0,10),INDEX(Rent_Roll_Input_Total, 0,20) ='Rent Roll Input'!$U$4))*12,0)} -> 0 | C2: Gross Scheduled Rent
A3: Monthly Income - Potential | B3: {=IFERROR(SUMPRODUCT(_xlfn._xlws.FILTER(INDEX(Rent_Roll_Input_Total, 0,5),INDEX(Rent_Roll_Input_Total, 0,20) ='Rent Roll Input'!$U$4), _xlfn._xlws.FILTER(INDEX(Rent_Roll_Input_Total, 0,8),INDEX(Rent_Roll_Input_Total, 0,20) ='Rent Roll Input'!$U$4))*12,0)} -> 0 | C3: Gross Potential Rent
A4: Monthly Income - Reno | B4: {=IFERROR(SUMPRODUCT(_xlfn._xlws.FILTER(INDEX(Rent_Roll_Input_Total, 0,5),INDEX(Rent_Roll_Input_Total, 0,20) ='Rent Roll Input'!$U$4), _xlfn._xlws.FILTER(INDEX(Rent_Roll_Input_Total, 0,9),INDEX(Rent_Roll_Input_Total, 0,20) ='Rent Roll Input'!$U$4))*12,0)} -> 0 | C4: Gross Reno Rent

Sheet Rent Roll Calculations
E1: Scheduled | F1: Scheduled | G1: Scheduled | H1: Current | I1: Current | J1: Current | K1: Current | L1: Current | M1: Current | N1: Current | O1: Scheduled | P1: Scheduled | Q1: Scheduled | R1: Scheduled | S1: Potential | T1: Potential | U1: Potential | V1: Potential | W1: Reno | X1: Reno | Y1: Reno | Z1: Reno
A2: Unit Type | B2: Total Units | C2: Total Sq Ft | D2: Avg Sq Ft | E2: Min Rent - Scheduled | F2: Max Rent - Scheduled | G2: Rental Range - Scheduled | H2: Min Rent - Current | I2: Max Rent - Current | J2: Rental Range - Current | K2: Monthly Income - Current | L2: Avg Rent Mo - Current | M2: Avg Rent Yr - Current | N2: Yearly Income - Current | O2: Monthly Income - Scheduled | P2: Avg Rent Mo - Scheduled | Q2: Avg Rent Yr - Scheduled | R2: Yearly Income - Scheduled | S2: Monthly Income - Potential | T2: Avg Rent Mo - Potential | U2: Avg Rent Yr - Potential | V2: Yearly Income - Potential | W2: Total Rent Mo - Reno | X2: Avg Rent Mo - Reno | Y2: Avg Rent Yr - Reno | Z2: Monthly Income - Reno | AA2: Avg Rent / SF / Mo - Current | AB2: Avg Rent / SF / Mo - Scheduled | AC2: Avg Rent / SF / Mo - Potential | AD2: Avg Rent / SF / Mo - Reno | AE2: Avg Rent / SF / Yr - Current | AF2: Avg Rent / SF / Yr - Scheduled | AG2: Avg Rent / SF / Yr - Potential | AH2: Avg Rent / SF / Yr - Reno
A3: {=INDEX(_xlfn._xlws.SORT(_xlfn.UNIQUE(_xlfn._xlws.FILTER('Rent Roll Input'!U4:V214,('Rent Roll Input'!U4:U214<>"")*ROW('Rent Roll Input'!U4:U214)>3)),2),0,1)} -> Totals/Weighted Averages | B3: {=_xlfn.IFS(A3="","",1,SUMIFS('Rent Roll Input'!$F$4:$F$214,'Rent Roll Input'!$U$4:$U$214,$A3))} -> 0 | C3: {=_xlfn.IFS(B3="","",A3 = Label_Total, 'Rent Roll Input'!$G$4,1,SUMIFS('Rent Roll Input'!$T$5:$T$214,'Rent Roll Input'!$U$5:$U$214,$A3))} -> 0 | D3: =IF(C3="", "", C3/B3) -> #DIV/0! | E3: {=_xlfn.IFS($A3 = "", "", $A3 = Label_Total, "", 1, MIN(_xlfn._xlws.FILTER(INDEX(Rent_Roll_Input_Total,0, 10),INDEX(Rent_Roll_Input_Total,0, 20)=$A3)))} | F3: {=_xlfn.IFS($A3 = "", "", $A3 = Label_Total, "", 1, MAX(_xlfn._xlws.FILTER(INDEX(Rent_Roll_Input_Total,0, 10),INDEX(Rent_Roll_Input_Total,0, 20)=$A3)))} | G3: {=_xlfn.IFS(A3="", "", A3 = Label_Total, "", 1, TEXT(E3, "$#,##0") & " - " & TEXT(F3, "$#,##0"))} | H3: {=_xlfn.IFS($A3 = "", "", $A3 = Label_Total, "", 1, MIN(_xlfn._xlws.FILTER(INDEX(Rent_Roll_Input_Total,0, 7),INDEX(Rent_Roll_Input_Total,0, 20)=$A3)))} | I3: {=_xlfn.IFS($A3 = "", "", $A3 = Label_Total, "", 1, MAX(_xlfn._xlws.FILTER(INDEX(Rent_Roll_Input_Total,0, 7),INDEX(Rent_Roll_Input_Total,0, 20)=$A3)))} | J3: {=_xlfn.IFS($A3="", "", A3 = Label_Total, "", 1, TEXT(H3, "$#,##0") & " - " & TEXT(I3, "$#,##0"))} | K3: {=IFERROR(_xlfn.IFS($A3="", "",1, SUMPRODUCT(_xlfn._xlws.FILTER(INDEX(Rent_Roll_Input_Total, 0,5),INDEX(Rent_Roll_Input_Total, 0,20) = $A3), _xlfn._xlws.FILTER(INDEX(Rent_Roll_Input_Total, 0,7),INDEX(Rent_Roll_Input_Total, 0,20) = $A3))),0)} -> 0 | L3: =IF($A3="", "",K3/$B3) -> #DIV/0! | M3: =IF($A3 = "", "", L3*12) -> #DIV/0! | N3: =IF($A3 = "", "",$K3*12) -> 0 | O3: {=IFERROR(_xlfn.IFS($A3="", "",1, SUMPRODUCT(_xlfn._xlws.FILTER(INDEX(Rent_Roll_Input_Total, 0,5),INDEX(Rent_Roll_Input_Total, 0,20) = $A3), _xlfn._xlws.FILTER(INDEX(Rent_Roll_Input_Total, 0,10),INDEX(Rent_Roll_Input_Total, 0,20) = $A3))),0)} -> 0 | P3: =IF($A3="", "",O3/$B3) -> #DIV/0! | Q3: =IF($A3 = "", "", P3*12) -> #DIV/0! | R3: =IF($A3 = "", "", O3*12) -> 0 | S3: {=IFERROR(_xlfn.IFS(A3="", "",1, SUMPRODUCT(_xlfn._xlws.FILTER(INDEX(Rent_Roll_Input_Total, 0,5),INDEX(Rent_Roll_Input_Total, 0,20) = A3), _xlfn._xlws.FILTER(INDEX(Rent_Roll_Input_Total, 0,8),INDEX(Rent_Roll_Input_Total, 0,20) = A3))),0)} -> 0 | T3: =IF($A3="", "",S3/$B3) -> #DIV/0! | U3: =IF($A3 = "", "", T3*12) -> #DIV/0! | V3: =IF($A3 = "", "", S3*12) -> 0 | W3: {=IFERROR(_xlfn.IFS($A3="", "",1, SUMPRODUCT(_xlfn._xlws.FILTER(INDEX(Rent_Roll_Input_Total, 0,5),INDEX(Rent_Roll_Input_Total, 0,20) = $A3), _xlfn._xlws.FILTER(INDEX(Rent_Roll_Input_Total, 0,9),INDEX(Rent_Roll_Input_Total, 0,20) = $A3))),0)} -> 0 | X3: =IF($A3="", "",W3/$B3) -> #DIV/0! | Y3: =IF($A3 = "", "", X3*12) -> #DIV/0! | Z3: =IF($A3 = "", "", $B3*X3) -> #DIV/0! | AA3: =IF($C3="", "", K3/$C3) -> #DIV/0! | AB3: =IF($C3="", "", O3/$C3) -> #DIV/0! | AC3: =IF($C3="", "", S3/$C3) -> #DIV/0! | AD3: =IF($C3="", "", W3/$C3) -> #DIV/0! | AE3: =IF($C3="", "", AA3*12) -> #DIV/0! | AF3: =IF($C3="", "", AB3*12) -> #DIV/0! | AG3: =IF($C3="", "", AC3*12) -> #DIV/0! | AH3: =IF($C3="", "", AD3*12) -> #DIV/0!
B4: {=_xlfn.IFS(A4="","",1,SUMIFS('Rent Roll Input'!$F$4:$F$214,'Rent Roll Input'!$U$4:$U$214,$A4))} | C4: {=_xlfn.IFS(B4="","",A4 = Label_Total, 'Rent Roll Input'!$G$4,1,SUMIFS('Rent Roll Input'!$T$5:$T$214,'Rent Roll Input'!$U$5:$U$214,$A4))} | D4: =IF(C4="", "", C4/B4) | E4: {=_xlfn.IFS($A4 = "", "", $A4 = Label_Total, "", 1, MIN(_xlfn._xlws.FILTER(INDEX(Rent_Roll_Input_Total,0, 10),INDEX(Rent_Roll_Input_Total,0, 20)=$A4)))} | F4: {=_xlfn.IFS($A4 = "", "", $A4 = Label_Total, "", 1, MAX(_xlfn._xlws.FILTER(INDEX(Rent_Roll_Input_Total,0, 10),INDEX(Rent_Roll_Input_Total,0, 20)=$A4)))} | G4: {=_xlfn.IFS(A4="", "", A4 = Label_Total, "", 1, TEXT(E4, "$#,##0") & " - " & TEXT(F4, "$#,##0"))} | H4: {=_xlfn.IFS($A4 = "", "", $A4 = Label_Total, "", 1, MIN(_xlfn._xlws.FILTER(INDEX(Rent_Roll_Input_Total,0, 7),INDEX(Rent_Roll_Input_Total,0, 20)=$A4)))} | I4: {=_xlfn.IFS($A4 = "", "", $A4 = Label_Total, "", 1, MAX(_xlfn._xlws.FILTER(INDEX(Rent_Roll_Input_Total,0, 7),INDEX(Rent_Roll_Input_Total,0, 20)=$A4)))} | J4: {=_xlfn.IFS($A4="", "", A4 = Label_Total, "", 1, TEXT(H4, "$#,##0") & " - " & TEXT(I4, "$#,##0"))} | K4: {=_xlfn.IFS($A4="", "",1, SUMPRODUCT(_xlfn._xlws.FILTER(INDEX(Rent_Roll_Input_Total, 0,5),INDEX(Rent_Roll_Input_Total, 0,20) = $A4), _xlfn._xlws.FILTER(INDEX(Rent_Roll_Input_Total, 0,7),INDEX(Rent_Roll_Input_Total, 0,20) = $A4)))} | L4: =IF($A4="", "",K4/$B4) | M4: =IF($A4 = "", "", L4*12) | N4: =IF($A4 = "", "",$K4*12) | O4: {=_xlfn.IFS(A4="", "",1, SUMPRODUCT(_xlfn._xlws.FILTER(INDEX(Rent_Roll_Input_Total, 0,5),INDEX(Rent_Roll_Input_Total, 0,20) = A4), _xlfn._xlws.FILTER(INDEX(Rent_Roll_Input_Total, 0,10),INDEX(Rent_Roll_Input_Total, 0,20) = A4)))} | P4: =IF($A4="", "",O4/$B4) | Q4: =IF($A4 = "", "", P4*12) | R4: =IF($A4 = "", "", O4*12) | S4: {=_xlfn.IFS(A4="", "",1, SUMPRODUCT(_xlfn._xlws.FILTER(INDEX(Rent_Roll_Input_Total, 0,5),INDEX(Rent_Roll_Input_Total, 0,20) = A4), _xlfn._xlws.FILTER(INDEX(Rent_Roll_Input_Total, 0,8),INDEX(Rent_Roll_Input_Total, 0,20) = A4)))} | T4: =IF($A4="", "",S4/$B4) | U4: =IF($A4 = "", "", T4*12) | V4: =IF($A4 = "", "", S4*12) | W4: {=_xlfn.IFS($A4="", "",1, SUMPRODUCT(_xlfn._xlws.FILTER(INDEX(Rent_Roll_Input_Total, 0,5),INDEX(Rent_Roll_Input_Total, 0,20) = $A4), _xlfn._xlws.FILTER(INDEX(Rent_Roll_Input_Total, 0,9),INDEX(Rent_Roll_Input_Total, 0,20) = $A4)))} | X4: =IF($A4="", "",W4/$B4) | Y4: =IF($A4 = "", "", X4*12) | Z4: =IF($A4 = "", "", $B4*X4) | AA4: =IF($C4="", "", K4/$C4) | AB4: =IF($C4="", "", O4/$C4) | AC4: =IF($C4="", "", S4/$C4) | AD4: =IF($C4="", "", W4/$C4) | AE4: =IF($C4="", "", AA4*12) | AF4: =IF($C4="", "", AB4*12) | AG4: =IF($C4="", "", AC4*12) | AH4: =IF($C4="", "", AD4*12)
B5: {=_xlfn.IFS(A5="","",1,SUMIFS('Rent Roll Input'!$F$4:$F$214,'Rent Roll Input'!$U$4:$U$214,$A5))} | C5: {=_xlfn.IFS(B5="","",A5 = Label_Total, 'Rent Roll Input'!$G$4,1,SUMIFS('Rent Roll Input'!$T$5:$T$214,'Rent Roll Input'!$U$5:$U$214,$A5))} | D5: =IF(C5="", "", C5/B5) | E5: {=_xlfn.IFS($A5 = "", "", $A5 = Label_Total, "", 1, MIN(_xlfn._xlws.FILTER(INDEX(Rent_Roll_Input_Total,0, 10),INDEX(Rent_Roll_Input_Total,0, 20)=$A5)))} | F5: {=_xlfn.IFS($A5 = "", "", $A5 = Label_Total, "", 1, MAX(_xlfn._xlws.FILTER(INDEX(Rent_Roll_Input_Total,0, 10),INDEX(Rent_Roll_Input_Total,0, 20)=$A5)))} | G5: {=_xlfn.IFS(A5="", "", A5 = Label_Total, "", 1, TEXT(E5, "$#,##0") & " - " & TEXT(F5, "$#,##0"))} | H5: {=_xlfn.IFS($A5 = "", "", $A5 = Label_Total, "", 1, MIN(_xlfn._xlws.FILTER(INDEX(Rent_Roll_Input_Total,0, 7),INDEX(Rent_Roll_Input_Total,0, 20)=$A5)))} | I5: {=_xlfn.IFS($A5 = "", "", $A5 = Label_Total, "", 1, MAX(_xlfn._xlws.FILTER(INDEX(Rent_Roll_Input_Total,0, 7),INDEX(Rent_Roll_Input_Total,0, 20)=$A5)))} | J5: {=_xlfn.IFS($A5="", "", A5 = Label_Total, "", 1, TEXT(H5, "$#,##0") & " - " & TEXT(I5, "$#,##0"))} | K5: {=_xlfn.IFS($A5="", "",1, SUMPRODUCT(_xlfn._xlws.FILTER(INDEX(Rent_Roll_Input_Total, 0,5),INDEX(Rent_Roll_Input_Total, 0,20) = $A5), _xlfn._xlws.FILTER(INDEX(Rent_Roll_Input_Total, 0,7),INDEX(Rent_Roll_Input_Total, 0,20) = $A5)))} | L5: =IF($A5="", "",K5/$B5) | M5: =IF($A5 = "", "", L5*12) | N5: =IF($A5 = "", "",$K5*12) | O5: {=_xlfn.IFS(A5="", "",1, SUMPRODUCT(_xlfn._xlws.FILTER(INDEX(Rent_Roll_Input_Total, 0,5),INDEX(Rent_Roll_Input_Total, 0,20) = A5), _xlfn._xlws.FILTER(INDEX(Rent_Roll_Input_Total, 0,10),INDEX(Rent_Roll_Input_Total, 0,20) = A5)))} | P5: =IF($A5="", "",O5/$B5) | Q5: =IF($A5 = "", "", P5*12) | R5: =IF($A5 = "", "", O5*12) | S5: {=_xlfn.IFS(A5="", "",1, SUMPRODUCT(_xlfn._xlws.FILTER(INDEX(Rent_Roll_Input_Total, 0,5),INDEX(Rent_Roll_Input_Total, 0,20) = A5), _xlfn._xlws.FILTER(INDEX(Rent_Roll_Input_Total, 0,8),INDEX(Rent_Roll_Input_Total, 0,20) = A5)))} | T5: =IF($A5="", "",S5/$B5) | U5: =IF($A5 = "", "", T5*12) | V5: =IF($A5 = "", "", S5*12) | W5: {=_xlfn.IFS($A5="", "",1, SUMPRODUCT(_xlfn._xlws.FILTER(INDEX(Rent_Roll_Input_Total, 0,5),INDEX(Rent_Roll_Input_Total, 0,20) = $A5), _xlfn._xlws.FILTER(INDEX(Rent_Roll_Input_Total, 0,9),INDEX(Rent_Roll_Input_Total, 0,20) = $A5)))} | X5: =IF($A5="", "",W5/$B5) | Y5: =IF($A5 = "", "", X5*12) | Z5: =IF($A5 = "", "", $B5*X5) | AA5: =IF($C5="", "", K5/$C5) | AB5: =IF($C5="", "", O5/$C5) | AC5: =IF($C5="", "", S5/$C5) | AD5: =IF($C5="", "", W5/$C5) | AE5: =IF($C5="", "", AA5*12) | AF5: =IF($C5="", "", AB5*12) | AG5: =IF($C5="", "", AC5*12) | AH5: =IF($C5="", "", AD5*12)
B6: {=_xlfn.IFS(A6="","",1,SUMIFS('Rent Roll Input'!$F$4:$F$214,'Rent Roll Input'!$U$4:$U$214,$A6))} | C6: {=_xlfn.IFS(B6="","",A6 = Label_Total, 'Rent Roll Input'!$G$4,1,SUMIFS('Rent Roll Input'!$T$5:$T$214,'Rent Roll Input'!$U$5:$U$214,$A6))} | D6: =IF(C6="", "", C6/B6) | E6: {=_xlfn.IFS($A6 = "", "", $A6 = Label_Total, "", 1, MIN(_xlfn._xlws.FILTER(INDEX(Rent_Roll_Input_Total,0, 10),INDEX(Rent_Roll_Input_Total,0, 20)=$A6)))} | F6: {=_xlfn.IFS($A6 = "", "", $A6 = Label_Total, "", 1, MAX(_xlfn._xlws.FILTER(INDEX(Rent_Roll_Input_Total,0, 10),INDEX(Rent_Roll_Input_Total,0, 20)=$A6)))} | G6: {=_xlfn.IFS(A6="", "", A6 = Label_Total, "", 1, TEXT(E6, "$#,##0") & " - " & TEXT(F6, "$#,##0"))} | H6: {=_xlfn.IFS($A6 = "", "", $A6 = Label_Total, "", 1, MIN(_xlfn._xlws.FILTER(INDEX(Rent_Roll_Input_Total,0, 7),INDEX(Rent_Roll_Input_Total,0, 20)=$A6)))} | I6: {=_xlfn.IFS($A6 = "", "", $A6 = Label_Total, "", 1, MAX(_xlfn._xlws.FILTER(INDEX(Rent_Roll_Input_Total,0, 7),INDEX(Rent_Roll_Input_Total,0, 20)=$A6)))} | J6: {=_xlfn.IFS($A6="", "", A6 = Label_Total, "", 1, TEXT(H6, "$#,##0") & " - " & TEXT(I6, "$#,##0"))} | K6: {=_xlfn.IFS($A6="", "",1, SUMPRODUCT(_xlfn._xlws.FILTER(INDEX(Rent_Roll_Input_Total, 0,5),INDEX(Rent_Roll_Input_Total, 0,20) = $A6), _xlfn._xlws.FILTER(INDEX(Rent_Roll_Input_Total, 0,7),INDEX(Rent_Roll_Input_Total, 0,20) = $A6)))} | L6: =IF($A6="", "",K6/$B6) | M6: =IF($A6 = "", "", L6*12) | N6: =IF($A6 = "", "",$K6*12) | O6: {=_xlfn.IFS(A6="", "",1, SUMPRODUCT(_xlfn._xlws.FILTER(INDEX(Rent_Roll_Input_Total, 0,5),INDEX(Rent_Roll_Input_Total, 0,20) = A6), _xlfn._xlws.FILTER(INDEX(Rent_Roll_Input_Total, 0,10),INDEX(Rent_Roll_Input_Total, 0,20) = A6)))} | P6: =IF($A6="", "",O6/$B6) | Q6: =IF($A6 = "", "", P6*12) | R6: =IF($A6 = "", "", O6*12) | S6: {=_xlfn.IFS(A6="", "",1, SUMPRODUCT(_xlfn._xlws.FILTER(INDEX(Rent_Roll_Input_Total, 0,5),INDEX(Rent_Roll_Input_Total, 0,20) = A6), _xlfn._xlws.FILTER(INDEX(Rent_Roll_Input_Total, 0,8),INDEX(Rent_Roll_Input_Total, 0,20) = A6)))} | T6: =IF($A6="", "",S6/$B6) | U6: =IF($A6 = "", "", T6*12) | V6: =IF($A6 = "", "", S6*12) | W6: {=_xlfn.IFS($A6="", "",1, SUMPRODUCT(_xlfn._xlws.FILTER(INDEX(Rent_Roll_Input_Total, 0,5),INDEX(Rent_Roll_Input_Total, 0,20) = $A6), _xlfn._xlws.FILTER(INDEX(Rent_Roll_Input_Total, 0,9),INDEX(Rent_Roll_Input_Total, 0,20) = $A6)))} | X6: =IF($A6="", "",W6/$B6) | Y6: =IF($A6 = "", "", X6*12) | Z6: =IF($A6 = "", "", $B6*X6) | AA6: =IF($C6="", "", K6/$C6) | AB6: =IF($C6="", "", O6/$C6) | AC6: =IF($C6="", "", S6/$C6) | AD6: =IF($C6="", "", W6/$C6) | AE6: =IF($C6="", "", AA6*12) | AF6: =IF($C6="", "", AB6*12) | AG6: =IF($C6="", "", AC6*12) | AH6: =IF($C6="", "", AD6*12)
B7: {=_xlfn.IFS(A7="","",1,SUMIFS('Rent Roll Input'!$F$4:$F$214,'Rent Roll Input'!$U$4:$U$214,$A7))} | C7: {=_xlfn.IFS(B7="","",A7 = Label_Total, 'Rent Roll Input'!$G$4,1,SUMIFS('Rent Roll Input'!$T$5:$T$214,'Rent Roll Input'!$U$5:$U$214,$A7))} | D7: =IF(C7="", "", C7/B7) | E7: {=_xlfn.IFS($A7 = "", "", $A7 = Label_Total, "", 1, MIN(_xlfn._xlws.FILTER(INDEX(Rent_Roll_Input_Total,0, 10),INDEX(Rent_Roll_Input_Total,0, 20)=$A7)))} | F7: {=_xlfn.IFS($A7 = "", "", $A7 = Label_Total, "", 1, MAX(_xlfn._xlws.FILTER(INDEX(Rent_Roll_Input_Total,0, 10),INDEX(Rent_Roll_Input_Total,0, 20)=$A7)))} | G7: {=_xlfn.IFS(A7="", "", A7 = Label_Total, "", 1, TEXT(E7, "$#,##0") & " - " & TEXT(F7, "$#,##0"))} | H7: {=_xlfn.IFS($A7 = "", "", $A7 = Label_Total, "", 1, MIN(_xlfn._xlws.FILTER(INDEX(Rent_Roll_Input_Total,0, 7),INDEX(Rent_Roll_Input_Total,0, 20)=$A7)))} | I7: {=_xlfn.IFS($A7 = "", "", $A7 = Label_Total, "", 1, MAX(_xlfn._xlws.FILTER(INDEX(Rent_Roll_Input_Total,0, 7),INDEX(Rent_Roll_Input_Total,0, 20)=$A7)))} | J7: {=_xlfn.IFS($A7="", "", A7 = Label_Total, "", 1, TEXT(H7, "$#,##0") & " - " & TEXT(I7, "$#,##0"))} | K7: {=_xlfn.IFS($A7="", "",1, SUMPRODUCT(_xlfn._xlws.FILTER(INDEX(Rent_Roll_Input_Total, 0,5),INDEX(Rent_Roll_Input_Total, 0,20) = $A7), _xlfn._xlws.FILTER(INDEX(Rent_Roll_Input_Total, 0,7),INDEX(Rent_Roll_Input_Total, 0,20) = $A7)))} | L7: =IF($A7="", "",K7/$B7) | M7: =IF($A7 = "", "", L7*12) | N7: =IF($A7 = "", "",$K7*12) | O7: {=_xlfn.IFS(A7="", "",1, SUMPRODUCT(_xlfn._xlws.FILTER(INDEX(Rent_Roll_Input_Total, 0,5),INDEX(Rent_Roll_Input_Total, 0,20) = A7), _xlfn._xlws.FILTER(INDEX(Rent_Roll_Input_Total, 0,10),INDEX(Rent_Roll_Input_Total, 0,20) = A7)))} | P7: =IF($A7="", "",O7/$B7) | Q7: =IF($A7 = "", "", P7*12) | R7: =IF($A7 = "", "", O7*12) | S7: {=_xlfn.IFS(A7="", "",1, SUMPRODUCT(_xlfn._xlws.FILTER(INDEX(Rent_Roll_Input_Total, 0,5),INDEX(Rent_Roll_Input_Total, 0,20) = A7), _xlfn._xlws.FILTER(INDEX(Rent_Roll_Input_Total, 0,8),INDEX(Rent_Roll_Input_Total, 0,20) = A7)))} | T7: =IF($A7="", "",S7/$B7) | U7: =IF($A7 = "", "", T7*12) | V7: =IF($A7 = "", "", S7*12) | W7: {=_xlfn.IFS($A7="", "",1, SUMPRODUCT(_xlfn._xlws.FILTER(INDEX(Rent_Roll_Input_Total, 0,5),INDEX(Rent_Roll_Input_Total, 0,20) = $A7), _xlfn._xlws.FILTER(INDEX(Rent_Roll_Input_Total, 0,9),INDEX(Rent_Roll_Input_Total, 0,20) = $A7)))} | X7: =IF($A7="", "",W7/$B7) | Y7: =IF($A7 = "", "", X7*12) | Z7: =IF($A7 = "", "", $B7*X7) | AA7: =IF($C7="", "", K7/$C7) | AB7: =IF($C7="", "", O7/$C7) | AC7: =IF($C7="", "", S7/$C7) | AD7: =IF($C7="", "", W7/$C7) | AE7: =IF($C7="", "", AA7*12) | AF7: =IF($C7="", "", AB7*12) | AG7: =IF($C7="", "", AC7*12) | AH7: =IF($C7="", "", AD7*12)
B8: {=_xlfn.IFS(A8="","",1,SUMIFS('Rent Roll Input'!$F$4:$F$214,'Rent Roll Input'!$U$4:$U$214,$A8))} | C8: {=_xlfn.IFS(B8="","",A8 = Label_Total, 'Rent Roll Input'!$G$4,1,SUMIFS('Rent Roll Input'!$T$5:$T$214,'Rent Roll Input'!$U$5:$U$214,$A8))} | D8: =IF(C8="", "", C8/B8) | E8: {=_xlfn.IFS($A8 = "", "", $A8 = Label_Total, "", 1, MIN(_xlfn._xlws.FILTER(INDEX(Rent_Roll_Input_Total,0, 10),INDEX(Rent_Roll_Input_Total,0, 20)=$A8)))} | F8: {=_xlfn.IFS($A8 = "", "", $A8 = Label_Total, "", 1, MAX(_xlfn._xlws.FILTER(INDEX(Rent_Roll_Input_Total,0, 10),INDEX(Rent_Roll_Input_Total,0, 20)=$A8)))} | G8: {=_xlfn.IFS(A8="", "", A8 = Label_Total, "", 1, TEXT(E8, "$#,##0") & " - " & TEXT(F8, "$#,##0"))} | H8: {=_xlfn.IFS($A8 = "", "", $A8 = Label_Total, "", 1, MIN(_xlfn._xlws.FILTER(INDEX(Rent_Roll_Input_Total,0, 7),INDEX(Rent_Roll_Input_Total,0, 20)=$A8)))} | I8: {=_xlfn.IFS($A8 = "", "", $A8 = Label_Total, "", 1, MAX(_xlfn._xlws.FILTER(INDEX(Rent_Roll_Input_Total,0, 7),INDEX(Rent_Roll_Input_Total,0, 20)=$A8)))} | J8: {=_xlfn.IFS($A8="", "", A8 = Label_Total, "", 1, TEXT(H8, "$#,##0") & " - " & TEXT(I8, "$#,##0"))} | K8: {=_xlfn.IFS($A8="", "",1, SUMPRODUCT(_xlfn._xlws.FILTER(INDEX(Rent_Roll_Input_Total, 0,5),INDEX(Rent_Roll_Input_Total, 0,20) = $A8), _xlfn._xlws.FILTER(INDEX(Rent_Roll_Input_Total, 0,7),INDEX(Rent_Roll_Input_Total, 0,20) = $A8)))} | L8: =IF($A8="", "",K8/$B8) | M8: =IF($A8 = "", "", L8*12) | N8: =IF($A8 = "", "",$K8*12) | O8: {=_xlfn.IFS(A8="", "",1, SUMPRODUCT(_xlfn._xlws.FILTER(INDEX(Rent_Roll_Input_Total, 0,5),INDEX(Rent_Roll_Input_Total, 0,20) = A8), _xlfn._xlws.FILTER(INDEX(Rent_Roll_Input_Total, 0,10),INDEX(Rent_Roll_Input_Total, 0,20) = A8)))} | P8: =IF($A8="", "",O8/$B8) | Q8: =IF($A8 = "", "", P8*12) | R8: =IF($A8 = "", "", O8*12) | S8: {=_xlfn.IFS(A8="", "",1, SUMPRODUCT(_xlfn._xlws.FILTER(INDEX(Rent_Roll_Input_Total, 0,5),INDEX(Rent_Roll_Input_Total, 0,20) = A8), _xlfn._xlws.FILTER(INDEX(Rent_Roll_Input_Total, 0,8),INDEX(Rent_Roll_Input_Total, 0,20) = A8)))} | T8: =IF($A8="", "",S8/$B8) | U8: =IF($A8 = "", "", T8*12) | V8: =IF($A8 = "", "", S8*12) | W8: {=_xlfn.IFS($A8="", "",1, SUMPRODUCT(_xlfn._xlws.FILTER(INDEX(Rent_Roll_Input_Total, 0,5),INDEX(Rent_Roll_Input_Total, 0,20) = $A8), _xlfn._xlws.FILTER(INDEX(Rent_Roll_Input_Total, 0,9),INDEX(Rent_Roll_Input_Total, 0,20) = $A8)))} | X8: =IF($A8="", "",W8/$B8) | Y8: =IF($A8 = "", "", X8*12) | Z8: =IF($A8 = "", "", $B8*X8) | AA8: =IF($C8="", "", K8/$C8) | AB8: =IF($C8="", "", O8/$C8) | AC8: =IF($C8="", "", S8/$C8) | AD8: =IF($C8="", "", W8/$C8) | AE8: =IF($C8="", "", AA8*12) | AF8: =IF($C8="", "", AB8*12) | AG8: =IF($C8="", "", AC8*12) | AH8: =IF($C8="", "", AD8*12)
B9: {=_xlfn.IFS(A9="","",1,SUMIFS('Rent Roll Input'!$F$4:$F$214,'Rent Roll Input'!$U$4:$U$214,$A9))} | C9: {=_xlfn.IFS(B9="","",A9 = Label_Total, 'Rent Roll Input'!$G$4,1,SUMIFS('Rent Roll Input'!$T$5:$T$214,'Rent Roll Input'!$U$5:$U$214,$A9))} | D9: =IF(C9="", "", C9/B9) | E9: {=_xlfn.IFS($A9 = "", "", $A9 = Label_Total, "", 1, MIN(_xlfn._xlws.FILTER(INDEX(Rent_Roll_Input_Total,0, 10),INDEX(Rent_Roll_Input_Total,0, 20)=$A9)))} | F9: {=_xlfn.IFS($A9 = "", "", $A9 = Label_Total, "", 1, MAX(_xlfn._xlws.FILTER(INDEX(Rent_Roll_Input_Total,0, 10),INDEX(Rent_Roll_Input_Total,0, 20)=$A9)))} | G9: {=_xlfn.IFS(A9="", "", A9 = Label_Total, "", 1, TEXT(E9, "$#,##0") & " - " & TEXT(F9, "$#,##0"))} | H9: {=_xlfn.IFS($A9 = "", "", $A9 = Label_Total, "", 1, MIN(_xlfn._xlws.FILTER(INDEX(Rent_Roll_Input_Total,0, 7),INDEX(Rent_Roll_Input_Total,0, 20)=$A9)))} | I9: {=_xlfn.IFS($A9 = "", "", $A9 = Label_Total, "", 1, MAX(_xlfn._xlws.FILTER(INDEX(Rent_Roll_Input_Total,0, 7),INDEX(Rent_Roll_Input_Total,0, 20)=$A9)))} | J9: {=_xlfn.IFS($A9="", "", A9 = Label_Total, "", 1, TEXT(H9, "$#,##0") & " - " & TEXT(I9, "$#,##0"))} | K9: {=_xlfn.IFS($A9="", "",1, SUMPRODUCT(_xlfn._xlws.FILTER(INDEX(Rent_Roll_Input_Total, 0,5),INDEX(Rent_Roll_Input_Total, 0,20) = $A9), _xlfn._xlws.FILTER(INDEX(Rent_Roll_Input_Total, 0,7),INDEX(Rent_Roll_Input_Total, 0,20) = $A9)))} | L9: =IF($A9="", "",K9/$B9) | M9: =IF($A9 = "", "", L9*12) | N9: =IF($A9 = "", "",$K9*12) | O9: {=_xlfn.IFS(A9="", "",1, SUMPRODUCT(_xlfn._xlws.FILTER(INDEX(Rent_Roll_Input_Total, 0,5),INDEX(Rent_Roll_Input_Total, 0,20) = A9), _xlfn._xlws.FILTER(INDEX(Rent_Roll_Input_Total, 0,10),INDEX(Rent_Roll_Input_Total, 0,20) = A9)))} | P9: =IF($A9="", "",O9/$B9) | Q9: =IF($A9 = "", "", P9*12) | R9: =IF($A9 = "", "", O9*12) | S9: {=_xlfn.IFS(A9="", "",1, SUMPRODUCT(_xlfn._xlws.FILTER(INDEX(Rent_Roll_Input_Total, 0,5),INDEX(Rent_Roll_Input_Total, 0,20) = A9), _xlfn._xlws.FILTER(INDEX(Rent_Roll_Input_Total, 0,8),INDEX(Rent_Roll_Input_Total, 0,20) = A9)))} | T9: =IF($A9="", "",S9/$B9) | U9: =IF($A9 = "", "", T9*12) | V9: =IF($A9 = "", "", S9*12) | W9: {=_xlfn.IFS($A9="", "",1, SUMPRODUCT(_xlfn._xlws.FILTER(INDEX(Rent_Roll_Input_Total, 0,5),INDEX(Rent_Roll_Input_Total, 0,20) = $A9), _xlfn._xlws.FILTER(INDEX(Rent_Roll_Input_Total, 0,9),INDEX(Rent_Roll_Input_Total, 0,20) = $A9)))} | X9: =IF($A9="", "",W9/$B9) | Y9: =IF($A9 = "", "", X9*12) | Z9: =IF($A9 = "", "", $B9*X9) | AA9: =IF($C9="", "", K9/$C9) | AB9: =IF($C9="", "", O9/$C9) | AC9: =IF($C9="", "", S9/$C9) | AD9: =IF($C9="", "", W9/$C9) | AE9: =IF($C9="", "", AA9*12) | AF9: =IF($C9="", "", AB9*12) | AG9: =IF($C9="", "", AC9*12) | AH9: =IF($C9="", "", AD9*12)
B10: {=_xlfn.IFS(A10="","",1,SUMIFS('Rent Roll Input'!$F$4:$F$214,'Rent Roll Input'!$U$4:$U$214,$A10))} | C10: {=_xlfn.IFS(B10="","",A10 = Label_Total, 'Rent Roll Input'!$G$4,1,SUMIFS('Rent Roll Input'!$T$5:$T$214,'Rent Roll Input'!$U$5:$U$214,$A10))} | D10: =IF(C10="", "", C10/B10) | E10: {=_xlfn.IFS($A10 = "", "", $A10 = Label_Total, "", 1, MIN(_xlfn._xlws.FILTER(INDEX(Rent_Roll_Input_Total,0, 10),INDEX(Rent_Roll_Input_Total,0, 20)=$A10)))} | F10: {=_xlfn.IFS($A10 = "", "", $A10 = Label_Total, "", 1, MAX(_xlfn._xlws.FILTER(INDEX(Rent_Roll_Input_Total,0, 10),INDEX(Rent_Roll_Input_Total,0, 20)=$A10)))} | G10: {=_xlfn.IFS(A10="", "", A10 = Label_Total, "", 1, TEXT(E10, "$#,##0") & " - " & TEXT(F10, "$#,##0"))} | H10: {=_xlfn.IFS($A10 = "", "", $A10 = Label_Total, "", 1, MIN(_xlfn._xlws.FILTER(INDEX(Rent_Roll_Input_Total,0, 7),INDEX(Rent_Roll_Input_Total,0, 20)=$A10)))} | I10: {=_xlfn.IFS($A10 = "", "", $A10 = Label_Total, "", 1, MAX(_xlfn._xlws.FILTER(INDEX(Rent_Roll_Input_Total,0, 7),INDEX(Rent_Roll_Input_Total,0, 20)=$A10)))} | J10: {=_xlfn.IFS($A10="", "", A10 = Label_Total, "", 1, TEXT(H10, "$#,##0") & " - " & TEXT(I10, "$#,##0"))} | K10: {=_xlfn.IFS($A10="", "",1, SUMPRODUCT(_xlfn._xlws.FILTER(INDEX(Rent_Roll_Input_Total, 0,5),INDEX(Rent_Roll_Input_Total, 0,20) = $A10), _xlfn._xlws.FILTER(INDEX(Rent_Roll_Input_Total, 0,7),INDEX(Rent_Roll_Input_Total, 0,20) = $A10)))} | L10: =IF($A10="", "",K10/$B10) | M10: =IF($A10 = "", "", L10*12) | N10: =IF($A10 = "", "",$K10*12) | O10: {=_xlfn.IFS(A10="", "",1, SUMPRODUCT(_xlfn._xlws.FILTER(INDEX(Rent_Roll_Input_Total, 0,5),INDEX(Rent_Roll_Input_Total, 0,20) = A10), _xlfn._xlws.FILTER(INDEX(Rent_Roll_Input_Total, 0,10),INDEX(Rent_Roll_Input_Total, 0,20) = A10)))} | P10: =IF($A10="", "",O10/$B10) | Q10: =IF($A10 = "", "", P10*12) | R10: =IF($A10 = "", "", O10*12) | S10: {=_xlfn.IFS(A10="", "",1, SUMPRODUCT(_xlfn._xlws.FILTER(INDEX(Rent_Roll_Input_Total, 0,5),INDEX(Rent_Roll_Input_Total, 0,20) = A10), _xlfn._xlws.FILTER(INDEX(Rent_Roll_Input_Total, 0,8),INDEX(Rent_Roll_Input_Total, 0,20) = A10)))} | T10: =IF($A10="", "",S10/$B10) | U10: =IF($A10 = "", "", T10*12) | V10: =IF($A10 = "", "", S10*12) | W10: {=_xlfn.IFS($A10="", "",1, SUMPRODUCT(_xlfn._xlws.FILTER(INDEX(Rent_Roll_Input_Total, 0,5),INDEX(Rent_Roll_Input_Total, 0,20) = $A10), _xlfn._xlws.FILTER(INDEX(Rent_Roll_Input_Total, 0,9),INDEX(Rent_Roll_Input_Total, 0,20) = $A10)))} | X10: =IF($A10="", "",W10/$B10) | Y10: =IF($A10 = "", "", X10*12) | Z10: =IF($A10 = "", "", $B10*X10) | AA10: =IF($C10="", "", K10/$C10) | AB10: =IF($C10="", "", O10/$C10) | AC10: =IF($C10="", "", S10/$C10) | AD10: =IF($C10="", "", W10/$C10) | AE10: =IF($C10="", "", AA10*12) | AF10: =IF($C10="", "", AB10*12) | AG10: =IF($C10="", "", AC10*12) | AH10: =IF($C10="", "", AD10*12)
B11: {=_xlfn.IFS(A11="","",1,SUMIFS('Rent Roll Input'!$F$4:$F$214,'Rent Roll Input'!$U$4:$U$214,$A11))} | C11: {=_xlfn.IFS(B11="","",A11 = Label_Total, 'Rent Roll Input'!$G$4,1,SUMIFS('Rent Roll Input'!$T$5:$T$214,'Rent Roll Input'!$U$5:$U$214,$A11))} | D11: =IF(C11="", "", C11/B11) | E11: {=_xlfn.IFS($A11 = "", "", $A11 = Label_Total, "", 1, MIN(_xlfn._xlws.FILTER(INDEX(Rent_Roll_Input_Total,0, 10),INDEX(Rent_Roll_Input_Total,0, 20)=$A11)))} | F11: {=_xlfn.IFS($A11 = "", "", $A11 = Label_Total, "", 1, MAX(_xlfn._xlws.FILTER(INDEX(Rent_Roll_Input_Total,0, 10),INDEX(Rent_Roll_Input_Total,0, 20)=$A11)))} | G11: {=_xlfn.IFS(A11="", "", A11 = Label_Total, "", 1, TEXT(E11, "$#,##0") & " - " & TEXT(F11, "$#,##0"))} | H11: {=_xlfn.IFS($A11 = "", "", $A11 = Label_Total, "", 1, MIN(_xlfn._xlws.FILTER(INDEX(Rent_Roll_Input_Total,0, 7),INDEX(Rent_Roll_Input_Total,0, 20)=$A11)))} | I11: {=_xlfn.IFS($A11 = "", "", $A11 = Label_Total, "", 1, MAX(_xlfn._xlws.FILTER(INDEX(Rent_Roll_Input_Total,0, 7),INDEX(Rent_Roll_Input_Total,0, 20)=$A11)))} | J11: {=_xlfn.IFS($A11="", "", A11 = Label_Total, "", 1, TEXT(H11, "$#,##0") & " - " & TEXT(I11, "$#,##0"))} | K11: {=_xlfn.IFS($A11="", "",1, SUMPRODUCT(_xlfn._xlws.FILTER(INDEX(Rent_Roll_Input_Total, 0,5),INDEX(Rent_Roll_Input_Total, 0,20) = $A11), _xlfn._xlws.FILTER(INDEX(Rent_Roll_Input_Total, 0,7),INDEX(Rent_Roll_Input_Total, 0,20) = $A11)))} | L11: =IF($A11="", "",K11/$B11) | M11: =IF($A11 = "", "", L11*12) | N11: =IF($A11 = "", "",$K11*12) | O11: {=_xlfn.IFS(A11="", "",1, SUMPRODUCT(_xlfn._xlws.FILTER(INDEX(Rent_Roll_Input_Total, 0,5),INDEX(Rent_Roll_Input_Total, 0,20) = A11), _xlfn._xlws.FILTER(INDEX(Rent_Roll_Input_Total, 0,10),INDEX(Rent_Roll_Input_Total, 0,20) = A11)))} | P11: =IF($A11="", "",O11/$B11) | Q11: =IF($A11 = "", "", P11*12) | R11: =IF($A11 = "", "", O11*12) | S11: {=_xlfn.IFS(A11="", "",1, SUMPRODUCT(_xlfn._xlws.FILTER(INDEX(Rent_Roll_Input_Total, 0,5),INDEX(Rent_Roll_Input_Total, 0,20) = A11), _xlfn._xlws.FILTER(INDEX(Rent_Roll_Input_Total, 0,8),INDEX(Rent_Roll_Input_Total, 0,20) = A11)))} | T11: =IF($A11="", "",S11/$B11) | U11: =IF($A11 = "", "", T11*12) | V11: =IF($A11 = "", "", S11*12) | W11: {=_xlfn.IFS($A11="", "",1, SUMPRODUCT(_xlfn._xlws.FILTER(INDEX(Rent_Roll_Input_Total, 0,5),INDEX(Rent_Roll_Input_Total, 0,20) = $A11), _xlfn._xlws.FILTER(INDEX(Rent_Roll_Input_Total, 0,9),INDEX(Rent_Roll_Input_Total, 0,20) = $A11)))} | X11: =IF($A11="", "",W11/$B11) | Y11: =IF($A11 = "", "", X11*12) | Z11: =IF($A11 = "", "", $B11*X11) | AA11: =IF($C11="", "", K11/$C11) | AB11: =IF($C11="", "", O11/$C11) | AC11: =IF($C11="", "", S11/$C11) | AD11: =IF($C11="", "", W11/$C11) | AE11: =IF($C11="", "", AA11*12) | AF11: =IF($C11="", "", AB11*12) | AG11: =IF($C11="", "", AC11*12) | AH11: =IF($C11="", "", AD11*12)
B12: {=_xlfn.IFS(A12="","",1,SUMIFS('Rent Roll Input'!$F$4:$F$214,'Rent Roll Input'!$U$4:$U$214,$A12))} | C12: {=_xlfn.IFS(B12="","",A12 = Label_Total, 'Rent Roll Input'!$G$4,1,SUMIFS('Rent Roll Input'!$T$5:$T$214,'Rent Roll Input'!$U$5:$U$214,$A12))} | D12: =IF(C12="", "", C12/B12) | E12: {=_xlfn.IFS($A12 = "", "", $A12 = Label_Total, "", 1, MIN(_xlfn._xlws.FILTER(INDEX(Rent_Roll_Input_Total,0, 10),INDEX(Rent_Roll_Input_Total,0, 20)=$A12)))} | F12: {=_xlfn.IFS($A12 = "", "", $A12 = Label_Total, "", 1, MAX(_xlfn._xlws.FILTER(INDEX(Rent_Roll_Input_Total,0, 10),INDEX(Rent_Roll_Input_Total,0, 20)=$A12)))} | G12: {=_xlfn.IFS(A12="", "", A12 = Label_Total, "", 1, TEXT(E12, "$#,##0") & " - " & TEXT(F12, "$#,##0"))} | H12: {=_xlfn.IFS($A12 = "", "", $A12 = Label_Total, "", 1, MIN(_xlfn._xlws.FILTER(INDEX(Rent_Roll_Input_Total,0, 7),INDEX(Rent_Roll_Input_Total,0, 20)=$A12)))} | I12: {=_xlfn.IFS($A12 = "", "", $A12 = Label_Total, "", 1, MAX(_xlfn._xlws.FILTER(INDEX(Rent_Roll_Input_Total,0, 7),INDEX(Rent_Roll_Input_Total,0, 20)=$A12)))} | J12: {=_xlfn.IFS($A12="", "", A12 = Label_Total, "", 1, TEXT(H12, "$#,##0") & " - " & TEXT(I12, "$#,##0"))} | K12: {=_xlfn.IFS($A12="", "",1, SUMPRODUCT(_xlfn._xlws.FILTER(INDEX(Rent_Roll_Input_Total, 0,5),INDEX(Rent_Roll_Input_Total, 0,20) = $A12), _xlfn._xlws.FILTER(INDEX(Rent_Roll_Input_Total, 0,7),INDEX(Rent_Roll_Input_Total, 0,20) = $A12)))} | L12: =IF($A12="", "",K12/$B12) | M12: =IF($A12 = "", "", L12*12) | N12: =IF($A12 = "", "",$K12*12) | O12: {=_xlfn.IFS(A12="", "",1, SUMPRODUCT(_xlfn._xlws.FILTER(INDEX(Rent_Roll_Input_Total, 0,5),INDEX(Rent_Roll_Input_Total, 0,20) = A12), _xlfn._xlws.FILTER(INDEX(Rent_Roll_Input_Total, 0,10),INDEX(Rent_Roll_Input_Total, 0,20) = A12)))} | P12: =IF($A12="", "",O12/$B12) | Q12: =IF($A12 = "", "", P12*12) | R12: =IF($A12 = "", "", O12*12) | S12: {=_xlfn.IFS(A12="", "",1, SUMPRODUCT(_xlfn._xlws.FILTER(INDEX(Rent_Roll_Input_Total, 0,5),INDEX(Rent_Roll_Input_Total, 0,20) = A12), _xlfn._xlws.FILTER(INDEX(Rent_Roll_Input_Total, 0,8),INDEX(Rent_Roll_Input_Total, 0,20) = A12)))} | T12: =IF($A12="", "",S12/$B12) | U12: =IF($A12 = "", "", T12*12) | V12: =IF($A12 = "", "", S12*12) | W12: {=_xlfn.IFS($A12="", "",1, SUMPRODUCT(_xlfn._xlws.FILTER(INDEX(Rent_Roll_Input_Total, 0,5),INDEX(Rent_Roll_Input_Total, 0,20) = $A12), _xlfn._xlws.FILTER(INDEX(Rent_Roll_Input_Total, 0,9),INDEX(Rent_Roll_Input_Total, 0,20) = $A12)))} | X12: =IF($A12="", "",W12/$B12) | Y12: =IF($A12 = "", "", X12*12) | Z12: =IF($A12 = "", "", $B12*X12) | AA12: =IF($C12="", "", K12/$C12) | AB12: =IF($C12="", "", O12/$C12) | AC12: =IF($C12="", "", S12/$C12) | AD12: =IF($C12="", "", W12/$C12) | AE12: =IF($C12="", "", AA12*12) | AF12: =IF($C12="", "", AB12*12) | AG12: =IF($C12="", "", AC12*12) | AH12: =IF($C12="", "", AD12*12)
B13: {=_xlfn.IFS(A13="","",1,SUMIFS('Rent Roll Input'!$F$4:$F$214,'Rent Roll Input'!$U$4:$U$214,$A13))} | C13: {=_xlfn.IFS(B13="","",A13 = Label_Total, 'Rent Roll Input'!$G$4,1,SUMIFS('Rent Roll Input'!$T$5:$T$214,'Rent Roll Input'!$U$5:$U$214,$A13))} | D13: =IF(C13="", "", C13/B13) | E13: {=_xlfn.IFS($A13 = "", "", $A13 = Label_Total, "", 1, MIN(_xlfn._xlws.FILTER(INDEX(Rent_Roll_Input_Total,0, 10),INDEX(Rent_Roll_Input_Total,0, 20)=$A13)))} | F13: {=_xlfn.IFS($A13 = "", "", $A13 = Label_Total, "", 1, MAX(_xlfn._xlws.FILTER(INDEX(Rent_Roll_Input_Total,0, 10),INDEX(Rent_Roll_Input_Total,0, 20)=$A13)))} | G13: {=_xlfn.IFS(A13="", "", A13 = Label_Total, "", 1, TEXT(E13, "$#,##0") & " - " & TEXT(F13, "$#,##0"))} | H13: {=_xlfn.IFS($A13 = "", "", $A13 = Label_Total, "", 1, MIN(_xlfn._xlws.FILTER(INDEX(Rent_Roll_Input_Total,0, 7),INDEX(Rent_Roll_Input_Total,0, 20)=$A13)))} | I13: {=_xlfn.IFS($A13 = "", "", $A13 = Label_Total, "", 1, MAX(_xlfn._xlws.FILTER(INDEX(Rent_Roll_Input_Total,0, 7),INDEX(Rent_Roll_Input_Total,0, 20)=$A13)))} | J13: {=_xlfn.IFS($A13="", "", A13 = Label_Total, "", 1, TEXT(H13, "$#,##0") & " - " & TEXT(I13, "$#,##0"))} | K13: {=_xlfn.IFS($A13="", "",1, SUMPRODUCT(_xlfn._xlws.FILTER(INDEX(Rent_Roll_Input_Total, 0,5),INDEX(Rent_Roll_Input_Total, 0,20) = $A13), _xlfn._xlws.FILTER(INDEX(Rent_Roll_Input_Total, 0,7),INDEX(Rent_Roll_Input_Total, 0,20) = $A13)))} | L13: =IF($A13="", "",K13/$B13) | M13: =IF($A13 = "", "", L13*12) | N13: =IF($A13 = "", "",$K13*12) | O13: {=_xlfn.IFS(A13="", "",1, SUMPRODUCT(_xlfn._xlws.FILTER(INDEX(Rent_Roll_Input_Total, 0,5),INDEX(Rent_Roll_Input_Total, 0,20) = A13), _xlfn._xlws.FILTER(INDEX(Rent_Roll_Input_Total, 0,10),INDEX(Rent_Roll_Input_Total, 0,20) = A13)))} | P13: =IF($A13="", "",O13/$B13) | Q13: =IF($A13 = "", "", P13*12) | R13: =IF($A13 = "", "", O13*12) | S13: {=_xlfn.IFS(A13="", "",1, SUMPRODUCT(_xlfn._xlws.FILTER(INDEX(Rent_Roll_Input_Total, 0,5),INDEX(Rent_Roll_Input_Total, 0,20) = A13), _xlfn._xlws.FILTER(INDEX(Rent_Roll_Input_Total, 0,8),INDEX(Rent_Roll_Input_Total, 0,20) = A13)))} | T13: =IF($A13="", "",S13/$B13) | U13: =IF($A13 = "", "", T13*12) | V13: =IF($A13 = "", "", S13*12) | W13: {=_xlfn.IFS($A13="", "",1, SUMPRODUCT(_xlfn._xlws.FILTER(INDEX(Rent_Roll_Input_Total, 0,5),INDEX(Rent_Roll_Input_Total, 0,20) = $A13), _xlfn._xlws.FILTER(INDEX(Rent_Roll_Input_Total, 0,9),INDEX(Rent_Roll_Input_Total, 0,20) = $A13)))} | X13: =IF($A13="", "",W13/$B13) | Y13: =IF($A13 = "", "", X13*12) | Z13: =IF($A13 = "", "", $B13*X13) | AA13: =IF($C13="", "", K13/$C13) | AB13: =IF($C13="", "", O13/$C13) | AC13: =IF($C13="", "", S13/$C13) | AD13: =IF($C13="", "", W13/$C13) | AE13: =IF($C13="", "", AA13*12) | AF13: =IF($C13="", "", AB13*12) | AG13: =IF($C13="", "", AC13*12) | AH13: =IF($C13="", "", AD13*12)
B14: {=_xlfn.IFS(A14="","",1,SUMIFS('Rent Roll Input'!$F$4:$F$214,'Rent Roll Input'!$U$4:$U$214,$A14))} | C14: {=_xlfn.IFS(B14="","",A14 = Label_Total, 'Rent Roll Input'!$G$4,1,SUMIFS('Rent Roll Input'!$T$5:$T$214,'Rent Roll Input'!$U$5:$U$214,$A14))} | D14: =IF(C14="", "", C14/B14) | E14: {=_xlfn.IFS($A14 = "", "", $A14 = Label_Total, "", 1, MIN(_xlfn._xlws.FILTER(INDEX(Rent_Roll_Input_Total,0, 10),INDEX(Rent_Roll_Input_Total,0, 20)=$A14)))} | F14: {=_xlfn.IFS($A14 = "", "", $A14 = Label_Total, "", 1, MAX(_xlfn._xlws.FILTER(INDEX(Rent_Roll_Input_Total,0, 10),INDEX(Rent_Roll_Input_Total,0, 20)=$A14)))} | G14: {=_xlfn.IFS(A14="", "", A14 = Label_Total, "", 1, TEXT(E14, "$#,##0") & " - " & TEXT(F14, "$#,##0"))} | H14: {=_xlfn.IFS($A14 = "", "", $A14 = Label_Total, "", 1, MIN(_xlfn._xlws.FILTER(INDEX(Rent_Roll_Input_Total,0, 7),INDEX(Rent_Roll_Input_Total,0, 20)=$A14)))} | I14: {=_xlfn.IFS($A14 = "", "", $A14 = Label_Total, "", 1, MAX(_xlfn._xlws.FILTER(INDEX(Rent_Roll_Input_Total,0, 7),INDEX(Rent_Roll_Input_Total,0, 20)=$A14)))} | J14: {=_xlfn.IFS($A14="", "", A14 = Label_Total, "", 1, TEXT(H14, "$#,##0") & " - " & TEXT(I14, "$#,##0"))} | K14: {=_xlfn.IFS($A14="", "",1, SUMPRODUCT(_xlfn._xlws.FILTER(INDEX(Rent_Roll_Input_Total, 0,5),INDEX(Rent_Roll_Input_Total, 0,20) = $A14), _xlfn._xlws.FILTER(INDEX(Rent_Roll_Input_Total, 0,7),INDEX(Rent_Roll_Input_Total, 0,20) = $A14)))} | L14: =IF($A14="", "",K14/$B14) | M14: =IF($A14 = "", "", L14*12) | N14: =IF($A14 = "", "",$K14*12) | O14: {=_xlfn.IFS(A14="", "",1, SUMPRODUCT(_xlfn._xlws.FILTER(INDEX(Rent_Roll_Input_Total, 0,5),INDEX(Rent_Roll_Input_Total, 0,20) = A14), _xlfn._xlws.FILTER(INDEX(Rent_Roll_Input_Total, 0,10),INDEX(Rent_Roll_Input_Total, 0,20) = A14)))} | P14: =IF($A14="", "",O14/$B14) | Q14: =IF($A14 = "", "", P14*12) | R14: =IF($A14 = "", "", O14*12) | S14: {=_xlfn.IFS(A14="", "",1, SUMPRODUCT(_xlfn._xlws.FILTER(INDEX(Rent_Roll_Input_Total, 0,5),INDEX(Rent_Roll_Input_Total, 0,20) = A14), _xlfn._xlws.FILTER(INDEX(Rent_Roll_Input_Total, 0,8),INDEX(Rent_Roll_Input_Total, 0,20) = A14)))} | T14: =IF($A14="", "",S14/$B14) | U14: =IF($A14 = "", "", T14*12) | V14: =IF($A14 = "", "", S14*12) | W14: {=_xlfn.IFS($A14="", "",1, SUMPRODUCT(_xlfn._xlws.FILTER(INDEX(Rent_Roll_Input_Total, 0,5),INDEX(Rent_Roll_Input_Total, 0,20) = $A14), _xlfn._xlws.FILTER(INDEX(Rent_Roll_Input_Total, 0,9),INDEX(Rent_Roll_Input_Total, 0,20) = $A14)))} | X14: =IF($A14="", "",W14/$B14) | Y14: =IF($A14 = "", "", X14*12) | Z14: =IF($A14 = "", "", $B14*X14) | AA14: =IF($C14="", "", K14/$C14) | AB14: =IF($C14="", "", O14/$C14) | AC14: =IF($C14="", "", S14/$C14) | AD14: =IF($C14="", "", W14/$C14) | AE14: =IF($C14="", "", AA14*12) | AF14: =IF($C14="", "", AB14*12) | AG14: =IF($C14="", "", AC14*12) | AH14: =IF($C14="", "", AD14*12)
B15: {=_xlfn.IFS(A15="","",1,SUMIFS('Rent Roll Input'!$F$4:$F$214,'Rent Roll Input'!$U$4:$U$214,$A15))} | C15: {=_xlfn.IFS(B15="","",A15 = Label_Total, 'Rent Roll Input'!$G$4,1,SUMIFS('Rent Roll Input'!$T$5:$T$214,'Rent Roll Input'!$U$5:$U$214,$A15))} | D15: =IF(C15="", "", C15/B15) | E15: {=_xlfn.IFS($A15 = "", "", $A15 = Label_Total, "", 1, MIN(_xlfn._xlws.FILTER(INDEX(Rent_Roll_Input_Total,0, 10),INDEX(Rent_Roll_Input_Total,0, 20)=$A15)))} | F15: {=_xlfn.IFS($A15 = "", "", $A15 = Label_Total, "", 1, MAX(_xlfn._xlws.FILTER(INDEX(Rent_Roll_Input_Total,0, 10),INDEX(Rent_Roll_Input_Total,0, 20)=$A15)))} | G15: {=_xlfn.IFS(A15="", "", A15 = Label_Total, "", 1, TEXT(E15, "$#,##0") & " - " & TEXT(F15, "$#,##0"))} | H15: {=_xlfn.IFS($A15 = "", "", $A15 = Label_Total, "", 1, MIN(_xlfn._xlws.FILTER(INDEX(Rent_Roll_Input_Total,0, 7),INDEX(Rent_Roll_Input_Total,0, 20)=$A15)))} | I15: {=_xlfn.IFS($A15 = "", "", $A15 = Label_Total, "", 1, MAX(_xlfn._xlws.FILTER(INDEX(Rent_Roll_Input_Total,0, 7),INDEX(Rent_Roll_Input_Total,0, 20)=$A15)))} | J15: {=_xlfn.IFS($A15="", "", A15 = Label_Total, "", 1, TEXT(H15, "$#,##0") & " - " & TEXT(I15, "$#,##0"))} | K15: {=_xlfn.IFS($A15="", "",1, SUMPRODUCT(_xlfn._xlws.FILTER(INDEX(Rent_Roll_Input_Total, 0,5),INDEX(Rent_Roll_Input_Total, 0,20) = $A15), _xlfn._xlws.FILTER(INDEX(Rent_Roll_Input_Total, 0,7),INDEX(Rent_Roll_Input_Total, 0,20) = $A15)))} | L15: =IF($A15="", "",K15/$B15) | M15: =IF($A15 = "", "", L15*12) | N15: =IF($A15 = "", "",$K15*12) | O15: {=_xlfn.IFS(A15="", "",1, SUMPRODUCT(_xlfn._xlws.FILTER(INDEX(Rent_Roll_Input_Total, 0,5),INDEX(Rent_Roll_Input_Total, 0,20) = A15), _xlfn._xlws.FILTER(INDEX(Rent_Roll_Input_Total, 0,10),INDEX(Rent_Roll_Input_Total, 0,20) = A15)))} | P15: =IF($A15="", "",O15/$B15) | Q15: =IF($A15 = "", "", P15*12) | R15: =IF($A15 = "", "", O15*12) | S15: {=_xlfn.IFS(A15="", "",1, SUMPRODUCT(_xlfn._xlws.FILTER(INDEX(Rent_Roll_Input_Total, 0,5),INDEX(Rent_Roll_Input_Total, 0,20) = A15), _xlfn._xlws.FILTER(INDEX(Rent_Roll_Input_Total, 0,8),INDEX(Rent_Roll_Input_Total, 0,20) = A15)))} | T15: =IF($A15="", "",S15/$B15) | U15: =IF($A15 = "", "", T15*12) | V15: =IF($A15 = "", "", S15*12) | W15: {=_xlfn.IFS($A15="", "",1, SUMPRODUCT(_xlfn._xlws.FILTER(INDEX(Rent_Roll_Input_Total, 0,5),INDEX(Rent_Roll_Input_Total, 0,20) = $A15), _xlfn._xlws.FILTER(INDEX(Rent_Roll_Input_Total, 0,9),INDEX(Rent_Roll_Input_Total, 0,20) = $A15)))} | X15: =IF($A15="", "",W15/$B15) | Y15: =IF($A15 = "", "", X15*12) | Z15: =IF($A15 = "", "", $B15*X15) | AA15: =IF($C15="", "", K15/$C15) | AB15: =IF($C15="", "", O15/$C15) | AC15: =IF($C15="", "", S15/$C15) | AD15: =IF($C15="", "", W15/$C15) | AE15: =IF($C15="", "", AA15*12) | AF15: =IF($C15="", "", AB15*12) | AG15: =IF($C15="", "", AC15*12) | AH15: =IF($C15="", "", AD15*12)
... B31: {=_xlfn.IFS(A31="","",1,SUMIFS('Rent Roll Input'!$F$4:$F$214,'Rent Roll Input'!$U$4:$U$214,$A31))} | C31: {=_xlfn.IFS(B31="","",A31 = Label_Total, 'Rent Roll Input'!$G$4,1,SUMIFS('Rent Roll Input'!$T$5:$T$214,'Rent Roll Input'!$U$5:$U$214,$A31))} | D31: =IF(C31="", "", C31/B31) | E31: {=_xlfn.IFS($A31 = "", "", $A31 = Label_Total, "", 1, MIN(_xlfn._xlws.FILTER(INDEX(Rent_Roll_Input_Total,0, 10),INDEX(Rent_Roll_Input_Total,0, 20)=$A31)))} | F31: {=_xlfn.IFS($A31 = "", "", $A31 = Label_Total, "", 1, MAX(_xlfn._xlws.FILTER(INDEX(Rent_Roll_Input_Total,0, 10),INDEX(Rent_Roll_Input_Total,0, 20)=$A31)))} | G31: {=_xlfn.IFS(A31="", "", A31 = Label_Total, "", 1, TEXT(E31, "$#,##0") & " - " & TEXT(F31, "$#,##0"))} | H31: {=_xlfn.IFS($A31 = "", "", $A31 = Label_Total, "", 1, MIN(_xlfn._xlws.FILTER(INDEX(Rent_Roll_Input_Total,0, 7),INDEX(Rent_Roll_Input_Total,0, 20)=$A31)))} | I31: {=_xlfn.IFS($A31 = "", "", $A31 = Label_Total, "", 1, MAX(_xlfn._xlws.FILTER(INDEX(Rent_Roll_Input_Total,0, 7),INDEX(Rent_Roll_Input_Total,0, 20)=$A31)))} | J31: {=_xlfn.IFS($A31="", "", A31 = Label_Total, "", 1, TEXT(H31, "$#,##0") & " - " & TEXT(I31, "$#,##0"))} | K31: {=_xlfn.IFS($A31="", "",1, SUMPRODUCT(_xlfn._xlws.FILTER(INDEX(Rent_Roll_Input_Total, 0,5),INDEX(Rent_Roll_Input_Total, 0,20) = $A31), _xlfn._xlws.FILTER(INDEX(Rent_Roll_Input_Total, 0,7),INDEX(Rent_Roll_Input_Total, 0,20) = $A31)))} | L31: =IF($A31="", "",K31/$B31) | M31: =IF($A31 = "", "", L31*12) | N31: =IF($A31 = "", "",$K31*12) | O31: {=_xlfn.IFS(A31="", "",1, SUMPRODUCT(_xlfn._xlws.FILTER(INDEX(Rent_Roll_Input_Total, 0,5),INDEX(Rent_Roll_Input_Total, 0,20) = A31), _xlfn._xlws.FILTER(INDEX(Rent_Roll_Input_Total, 0,10),INDEX(Rent_Roll_Input_Total, 0,20) = A31)))} | P31: =IF($A31="", "",O31/$B31) | Q31: =IF($A31 = "", "", P31*12) | R31: =IF($A31 = "", "", O31*12) | S31: {=_xlfn.IFS(A31="", "",1, SUMPRODUCT(_xlfn._xlws.FILTER(INDEX(Rent_Roll_Input_Total, 0,5),INDEX(Rent_Roll_Input_Total, 0,20) = A31), _xlfn._xlws.FILTER(INDEX(Rent_Roll_Input_Total, 0,8),INDEX(Rent_Roll_Input_Total, 0,20) = A31)))} | T31: =IF($A31="", "",S31/$B31) | U31: =IF($A31 = "", "", T31*12) | V31: =IF($A31 = "", "", S31*12) | W31: {=_xlfn.IFS($A31="", "",1, SUMPRODUCT(_xlfn._xlws.FILTER(INDEX(Rent_Roll_Input_Total, 0,5),INDEX(Rent_Roll_Input_Total, 0,20) = $A31), _xlfn._xlws.FILTER(INDEX(Rent_Roll_Input_Total, 0,9),INDEX(Rent_Roll_Input_Total, 0,20) = $A31)))} | X31: =IF($A31="", "",W31/$B31) | Y31: =IF($A31 = "", "", X31*12) | Z31: =IF($A31 = "", "", $B31*X31) | AA31: =IF($C31="", "", K31/$C31) | AB31: =IF($C31="", "", O31/$C31) | AC31: =IF($C31="", "", S31/$C31) | AD31: =IF($C31="", "", W31/$C31) | AE31: =IF($C31="", "", AA31*12) | AF31: =IF($C31="", "", AB31*12) | AG31: =IF($C31="", "", AC31*12) | AH31: =IF($C31="", "", AD31*12)
A32: 0
A33: Gross Annualized Rents | E33: {=IFERROR(_xlfn._xlws.FILTER($O$3:$O$31,$A$3:$A$31='Rent Roll Input'!$U$4)*12,0)} -> 0 | F33: {=IFERROR(_xlfn._xlws.FILTER($O$3:$O$31,$A$3:$A$31='Rent Roll Input'!$U$4)*12,0)} -> 0 | G33: {=IFERROR(_xlfn._xlws.FILTER($O$3:$O$31,$A$3:$A$31='Rent Roll Input'!$U$4)*12,0)} -> 0 | H33: {=IFERROR(_xlfn._xlws.FILTER($K$3:$K$31,$A$3:$A$31='Rent Roll Input'!$U$4)*12,0)} -> 0 | I33: {=_xlfn._xlws.FILTER($K$3:$K$31,$A$3:$A$31='Rent Roll Input'!$U$4)*12} -> 0 | J33: {=_xlfn._xlws.FILTER($K$3:$K$31,$A$3:$A$31='Rent Roll Input'!$U$4)*12} -> 0 | K33: {=_xlfn._xlws.FILTER($K$3:$K$31,$A$3:$A$31='Rent Roll Input'!$U$4)*12} -> 0 | L33: {=_xlfn._xlws.FILTER($K$3:$K$31,$A$3:$A$31='Rent Roll Input'!$U$4)*12} -> 0 | M33: {=_xlfn._xlws.FILTER($K$3:$K$31,$A$3:$A$31='Rent Roll Input'!$U$4)*12} -> 0 | N33: {=_xlfn._xlws.FILTER($K$3:$K$31,$A$3:$A$31='Rent Roll Input'!$U$4)*12} -> 0 | O33: {=_xlfn._xlws.FILTER($O$3:$O$31,$A$3:$A$31='Rent Roll Input'!$U$4)*12} -> 0 | P33: {=_xlfn._xlws.FILTER($O$3:$O$31,$A$3:$A$31='Rent Roll Input'!$U$4)*12} -> 0 | Q33: {=_xlfn._xlws.FILTER($O$3:$O$31,$A$3:$A$31='Rent Roll Input'!$U$4)*12} -> 0 | R33: {=_xlfn._xlws.FILTER($O$3:$O$31,$A$3:$A$31='Rent Roll Input'!$U$4)*12} -> 0 | S33: {=_xlfn._xlws.FILTER($S$3:$S$31,$A$3:$A$31='Rent Roll Input'!$U$4)*12} -> 0 | T33: {=_xlfn._xlws.FILTER($S$3:$S$31,$A$3:$A$31='Rent Roll Input'!$U$4)*12} -> 0 | U33: {=_xlfn._xlws.FILTER($S$3:$S$31,$A$3:$A$31='Rent Roll Input'!$U$4)*12} -> 0 | V33: {=_xlfn._xlws.FILTER($S$3:$S$31,$A$3:$A$31='Rent Roll Input'!$U$4)*12} -> 0 | W33: {=_xlfn._xlws.FILTER($Z$3:$Z$31,$A$3:$A$31='Rent Roll Input'!$U$4)*12} -> #DIV/0! | X33: {=_xlfn._xlws.FILTER($Z$3:$Z$31,$A$3:$A$31='Rent Roll Input'!$U$4)*12} -> #DIV/0! | Y33: {=_xlfn._xlws.FILTER($Z$3:$Z$31,$A$3:$A$31='Rent Roll Input'!$U$4)*12} -> #DIV/0! | Z33: {=_xlfn._xlws.FILTER($Z$3:$Z$31,$A$3:$A$31='Rent Roll Input'!$U$4)*12} -> #DIV/0!

Sheet Rent Roll Detail Calculations
A1: {=_xlfn._xlws.FILTER('Rent Roll Input'!B3:Z4,'Rent Roll Input'!B3:Z3<>"")} -> Bed | B1: Bath | C1: Unit No. | D1: Unit Description | E1: Units | F1: Square Feet | G1: Currrent Rent / Unit / Month | H1: Potential Rent / Unit / Month | I1: Reno Rent / Unit / Month | J1: Scheduled Rent / Unit / Month | K1: Current Rent / SF / Month | L1: Potential Rent / SF / Month | M1: Reno Rent / SF / Month | N1: Scheduled Rent / SF / Month | O1: Current Rent / SF / Year | P1: Potential Rent / SF / Year | Q1: Reno Rent / SF / Year | R1: Scheduled Rent / SF / Year | S1: Total Sq Ft | T1: Unit Type
A2: 0 | B2: 0 | C2: 0 | D2: 0 | E2: 0 | F2: 0 | G2: 0 | H2: 0 | I2: 0 | J2: 0 | K2: #DIV/0! | L2: #DIV/0! | M2: #DIV/0! | N2: #DIV/0! | O2: #DIV/0! | P2: #DIV/0! | Q2: #DIV/0! | R2: #DIV/0! | S2: 0 | T2: Totals/Weighted Averages
A3: {=_xlfn._xlws.FILTER('Rent Roll Input'!B5:U214, 'Rent Roll Input'!U5:U214<>"")} -> #VALUE!

Sheet Equity Returns Input
B2: STRATEGIC OWNERSHIP OPTIONS
B4: SALE
B5: Sale Price | C5: =sale_price -> 0
B6: Less: Commissions/Adjustments
B7: Less: Mortgage Balance | C7: =IFERROR(SED_Loan_Balance,0) -> 0
B8: Less: Prepayment Penalty | C8: =IFERROR(SED_Prepayment_Penalty,0) -> 0
B9: Seller's Net Proceeds | C9: =C5-C6-C7-C8 -> 0
B10: NOI to use for Hold & Refinance Scenarios: | C10: Year 1
B12: SELL & EXCHANGE | E12: HOLD | H12: REFINANCE | K12: SELL
B13: Property Type | E13: Property Type | F13: Multifamily | H13: Property Type | I13: Multifamily | K13: Price | L13: =OFFSET(ERO_SaleStart,1,1) -> 0
B14: Address | E14: Address | H14: Address | I14: =$F$14 -> 0 | K14: Less: Prepayment Penalty/Defeasance | L14: =OFFSET(ERO_SaleStart,4,1) -> 0
B15: City, State | E15: City, State | H15: City, State | I15: =$F$15 -> 0 | K15: Less: Mortgage Balance | L15: =OFFSET(ERO_SaleStart,3,1) -> 0
B16: Price | E16: Price | F16: =OFFSET(ERO_SaleStart,1,1) -> 0 | H16: Price (Appraised Value) | I16: =OFFSET(ERO_SaleStart,1,1) -> 0 | K16: Gross Sales Proceeds | L16: =13:13-SUM(L14:L15) -> 0
B17: CAP Rate | C17: =IF(C16=0,0,C24/C16) -> 0 | E17: CAP Rate | F17: =IF(F16=0,0,F24/F16) -> 0 | H17: LTV | K17: Fees/Transfer Taxes
B18: LTV | C18: =IF(C16=0,0, C20/C16) -> 0 | E18: LTV | F18: =IF(F16=0,0, F20/F16) -> 0 | H18: Current Loan Balance | I18: =OFFSET(ERO_SaleStart,3,1) -> 0
B19: Down Payment* | C19: =OFFSET(ERO_SaleStart,5,1) -> 0 | E19: Current Equity | F19: =F16-F20 -> 0 | H19: New Loan Amount | I19: =I17*I16 -> 0
B20: Loan Amount | C20: =C16-C19 -> 0 | E20: Mortgage Balance | F20: =OFFSET(ERO_SaleStart,3,1) -> 0 | H20: Net Proceeds From New Loan | I20: =I19-I18 -> 0
B21: Interest Rate | E21: Interest Rate | F21: {=Current_Interest_Rate} -> 0 | H21: Interest Rate | L21: =SUM((L13*L18),(L13*L19),(L13*L20)) -> 0
B22: Amortization | E22: Amortization | F22: {=Current_Amort} -> 0 | H22: Amortization | K22: Capital Gains Taxes
B23: Term | E23: Term | F23: {=Current_Term} -> 0 | H23: Term
B24: Net Operating Income | E24: Net Operating Income | F24: =OFFSET('Operating Statement'!Q41,0,-IFERROR(OS_YrsHist+2-MATCH(C10, ddl_OpColumns, 0),1)*2,1,1) -> 0 | H24: Net Operating Income
B25: Less: Debt Service | C25: =IF(C22=0,0,-PMT(C21/12,C22*12,20:20)*12) -> 0 | E25: Less: Debt Service | F25: =IF(F22=0,0,-Current_PMT*12) -> 0 | H25: Less: Debt Service | I25: =IF(I22=0,0,-PMT(I21/12,I22*12,I19)*12) -> 0 | L25: =SUM((L23*(L13-L21)),(L24*(L13-L21))) -> 0
B26: Net Cash Flow After Debt Service | C26: =C24-C25 -> 0 | E26: Net Cash Flow After Debt Service | F26: =F24-F25 -> 0 | H26: Net Cash Flow After Debt Service | I26: =I24-I25 -> 0 | K26: Sale without 1031 Exchange | L26: =L16-L21-L25 -> 0
B27: Return on Equity | C27: =IFERROR(C26/C19,"") | E27: Return on Equity | F27: =IFERROR(F26/F19,"") | H27: Return on Equity | I27: =IF(I16-I18=0,0,I26/(I16-I19)) -> 0 | K27: Sale with 1031 Exchange | L27: =L16-L21 -> 0
B30: Notes:

Sheet Data Validation
A1: All Cash | B1: No | C1: {=_xlfn._xlws.SORT(TRANSPOSE(_xlfn._xlws.FILTER('Rent Roll Calculations'!2:2,'Rent Roll Calculations'!2:2<>"")))} -> Avg Rent / SF / Mo - Current | E1: {=_xlfn._xlws.SORT(TRANSPOSE(_xlfn._xlws.FILTER('Rent Roll Detail Calculations'!1:1,'Rent Roll Detail Calculations'!1:1<>"")))} -> Bath | G1: {=TRANSPOSE(_xlfn._xlws.FILTER('Rent Roll Detail Calculations'!1:1,'Rent Roll Detail Calculations'!1:1<>""))} -> Bed | H1: {=TRANSPOSE(_xlfn._xlws.FILTER(COLUMN('Rent Roll Detail Calculations'!1:1),'Rent Roll Detail Calculations'!1:1<>""))} -> 1 | J1: Hide | L1: SELL & EXCHANGE
A2: Financed - New Loan | B2: Yes, Loan Amount is Known | C2: Avg Rent / SF / Mo - Potential | E2: Bed | G2: Bath | H2: 2 | J2: 1 | L2: HOLD
A3: Financed - Assumed Loan | B3: Yes, Loan Amount is Estimated | C3: Avg Rent / SF / Mo - Reno | E3: Current Rent / SF / Month | G3: Unit No. | H3: 3 | J3: 2 | L3: REFINANCE
C4: Avg Rent / SF / Mo - Scheduled | E4: Current Rent / SF / Year | G4: Unit Description | H4: 4 | J4: 3 | L4: SELL
C5: Avg Rent / SF / Yr - Current | E5: Currrent Rent / Unit / Month | G5: Units | H5: 5
C6: Avg Rent / SF / Yr - Potential | E6: Potential Rent / SF / Month | G6: Square Feet | H6: 6
C7: Avg Rent / SF / Yr - Reno | E7: Potential Rent / SF / Year | G7: Currrent Rent / Unit / Month | H7: 7
C8: Avg Rent / SF / Yr - Scheduled | E8: Potential Rent / Unit / Month | G8: Potential Rent / Unit / Month | H8: 8
C9: Avg Rent Mo - Current | E9: Reno Rent / SF / Month | G9: Reno Rent / Unit / Month | H9: 9
C10: Avg Rent Mo - Potential | E10: Reno Rent / SF / Year | G10: Scheduled Rent / Unit / Month | H10: 10
C11: Avg Rent Mo - Reno | E11: Reno Rent / Unit / Month | G11: Current Rent / SF / Month | H11: 11
C12: Avg Rent Mo - Scheduled | E12: Scheduled Rent / SF / Month | G12: Potential Rent / SF / Month | H12: 12
C13: Avg Rent Yr - Current | E13: Scheduled Rent / SF / Year | G13: Reno Rent / SF / Month | H13: 13
C14: Avg Rent Yr - Potential | E14: Scheduled Rent / Unit / Month | G14: Scheduled Rent / SF / Month | H14: 14
C15: Avg Rent Yr - Reno | E15: Square Feet | G15: Current Rent / SF / Year | H15: 15
C16: Avg Rent Yr - Scheduled | E16: Total Sq Ft | G16: Potential Rent / SF / Year | H16: 16
... C20: Min Rent - Current | E20: Units | G20: Unit Type | H20: 20
C21: Min Rent - Scheduled
C22: Monthly Income - Current
C23: Monthly Income - Potential
C24: Monthly Income - Reno
C25: Monthly Income - Scheduled
C26: Rental Range - Current
C27: Rental Range - Scheduled
C28: Total Rent Mo - Reno
C29: Total Sq Ft
C30: Total Units
C31: Unit Type
C32: Yearly Income - Current
... C34: Yearly Income - Scheduled

Sheet Rent Roll Detail
B2: Highlight Alternating rows? | C2: Yes
A4: Select Columns for output | B4: Unit No. | C4: Unit Type | D4: Square Feet | E4: Currrent Rent / Unit / Month | F4: Current Rent / SF / Month | G4: Scheduled Rent / Unit / Month | H4: Scheduled Rent / SF / Month
B7: =IF(B4 = "", "", B4) -> Unit No. | C7: =IF(C4 = "", "", C4) -> Unit Type | D7: =IF(D4 = "", "", D4) -> Square Feet | E7: =IF(E4 = "", "", E4) -> Currrent Rent / Unit / Month | F7: =IF(F4 = "", "", F4) -> Current Rent / SF / Month | G7: =IF(G4 = "", "", G4) -> Scheduled Rent / Unit / Month | H7: =IF(H4 = "", "", H4) -> Scheduled Rent / SF / Month | I7: =IF(I4 = "", "", I4) | ... P7: =IF(P4 = "", "", P4)
B8: {=IFERROR(INDEX(_xlfn._xlws.SORT(Rent_Roll_Input_Total,1), 0,MATCH(B4,Rent_Roll_Input_Headers,0)),"")} | C8: {=IFERROR(INDEX(_xlfn._xlws.SORT(Rent_Roll_Input_Total,1), 0,MATCH(C4,Rent_Roll_Input_Headers,0)),"")} | D8: {=IFERROR(INDEX(_xlfn._xlws.SORT(Rent_Roll_Input_Total,1), 0,MATCH(D4,Rent_Roll_Input_Headers,0)),"")} | E8: {=IFERROR(INDEX(_xlfn._xlws.SORT(Rent_Roll_Input_Total,1), 0,MATCH(E4,Rent_Roll_Input_Headers,0)),"")} | F8: {=IFERROR(INDEX(_xlfn._xlws.SORT(Rent_Roll_Input_Total,1), 0,MATCH(F4,Rent_Roll_Input_Headers,0)),"")} | G8: {=IFERROR(INDEX(_xlfn._xlws.SORT(Rent_Roll_Input_Total,1), 0,MATCH(G4,Rent_Roll_Input_Headers,0)),"")} | H8: {=IFERROR(INDEX(_xlfn._xlws.SORT(Rent_Roll_Input_Total,1), 0,MATCH(H4,Rent_Roll_Input_Headers,0)),"")} | I8: {=IFERROR(INDEX(_xlfn._xlws.SORT(Rent_Roll_Input_Total,1), 0,MATCH(I4,Rent_Roll_Input_Headers,0)),"")} | ... P8: {=IFERROR(INDEX(_xlfn._xlws.SORT(Rent_Roll_Input_Total,1), 0,MATCH(P4,Rent_Roll_Input_Headers,0)),"")}

Sheet Rent Roll Summary
A3: Select Columns for output | C3: Total Units | D3: Avg Sq Ft | E3: Rental Range - Scheduled | F3: Avg Rent Mo - Scheduled | G3: Avg Rent / SF / Mo - Scheduled | H3: Monthly Income - Scheduled | I3: Avg Rent Mo - Potential | J3: Avg Rent / SF / Mo - Potential | K3: Monthly Income - Potential
A5: Show Annualized Rents | F5: Yes | I5: Yes
B8: Unit Type | C8: =IF(C3="", "",C3) -> Total Units | D8: =IF(D3="", "",D3) -> Avg Sq Ft | E8: =IF(E3="", "",E3) -> Rental Range - Scheduled | F8: =IF(F3="", "",F3) -> Avg Rent Mo - Scheduled | G8: =IF(G3="", "",G3) -> Avg Rent / SF / Mo - Scheduled | H8: =IF(H3="", "",H3) -> Monthly Income - Scheduled | I8: =IF(I3="", "",I3) -> Avg Rent Mo - Potential | J8: =IF(J3="", "",J3) -> Avg Rent / SF / Mo - Potential | ... M8: =IF(M3="", "",M3)
B9: {=IF(COUNTIF(5:5, "Yes") > 0, _xlfn._xlws.FILTER('Rent Roll Calculations'!A3:A33,'Rent Roll Calculations'!A3:A33<>""), _xlfn._xlws.FILTER('Rent Roll Calculations'!A3:A31,'Rent Roll Calculations'!A3:A31<>""))} -> Totals/Weighted Averages | C9: {=IF(C5="Yes",IFERROR(INDEX(_xlfn._xlws.FILTER('Rent Roll Calculations'!$A$3:$AH$33,'Rent Roll Calculations'!$A$3:$A$33<>""),0,MATCH(C3,Rent_Roll_Calculations_Headers,0)),""),IFERROR(INDEX(_xlfn._xlws.FILTER('Rent Roll Calculations'!$A$3:$AH$31,'Rent Roll Calculations'!$A$3:$A$31<>""),0,MATCH(C3,Rent_Roll_Calculations_Headers,0)),""))} -> 0 | D9: {=IF(D5="Yes",IFERROR(INDEX(_xlfn._xlws.FILTER('Rent Roll Calculations'!$A$3:$AH$33,'Rent Roll Calculations'!$A$3:$A$33<>""),0,MATCH(D3,Rent_Roll_Calculations_Headers,0)),""),IFERROR(INDEX(_xlfn._xlws.FILTER('Rent Roll Calculations'!$A$3:$AH$31,'Rent Roll Calculations'!$A$3:$A$31<>""),0,MATCH(D3,Rent_Roll_Calculations_Headers,0)),""))} | E9: {=IF(E5="Yes",IFERROR(INDEX(_xlfn._xlws.FILTER('Rent Roll Calculations'!$A$3:$AH$33,'Rent Roll Calculations'!$A$3:$A$33<>""),0,MATCH(E3,Rent_Roll_Calculations_Headers,0)),""),IFERROR(INDEX(_xlfn._xlws.FILTER('Rent Roll Calculations'!$A$3:$AH$31,'Rent Roll Calculations'!$A$3:$A$31<>""),0,MATCH(E3,Rent_Roll_Calculations_Headers,0)),""))} | F9: {=IF(F5="Yes",IFERROR(INDEX(_xlfn._xlws.FILTER('Rent Roll Calculations'!$A$3:$AH$33,'Rent Roll Calculations'!$A$3:$A$33<>""),0,MATCH(F3,Rent_Roll_Calculations_Headers,0)),""),IFERROR(INDEX(_xlfn._xlws.FILTER('Rent Roll Calculations'!$A$3:$AH$31,'Rent Roll Calculations'!$A$3:$A$31<>""),0,MATCH(F3,Rent_Roll_Calculations_Headers,0)),""))} | G9: {=IF(G5="Yes",IFERROR(INDEX(_xlfn._xlws.FILTER('Rent Roll Calculations'!$A$3:$AH$33,'Rent Roll Calculations'!$A$3:$A$33<>""),0,MATCH(G3,Rent_Roll_Calculations_Headers,0)),""),IFERROR(INDEX(_xlfn._xlws.FILTER('Rent Roll Calculations'!$A$3:$AH$31,'Rent Roll Calculations'!$A$3:$A$31<>""),0,MATCH(G3,Rent_Roll_Calculations_Headers,0)),""))} | H9: {=IF(H5="Yes",IFERROR(INDEX(_xlfn._xlws.FILTER('Rent Roll Calculations'!$A$3:$AH$33,'Rent Roll Calculations'!$A$3:$A$33<>""),0,MATCH(H3,Rent_Roll_Calculations_Headers,0)),""),IFERROR(INDEX(_xlfn._xlws.FILTER('Rent Roll Calculations'!$A$3:$AH$31,'Rent Roll Calculations'!$A$3:$A$31<>""),0,MATCH(H3,Rent_Roll_Calculations_Headers,0)),""))} -> 0 | I9: {=IF(I5="Yes",IFERROR(INDEX(_xlfn._xlws.FILTER('Rent Roll Calculations'!$A$3:$AH$33,'Rent Roll Calculations'!$A$3:$A$33<>""),0,MATCH(I3,Rent_Roll_Calculations_Headers,0)),""),IFERROR(INDEX(_xlfn._xlws.FILTER('Rent Roll Calculations'!$A$3:$AH$31,'Rent Roll Calculations'!$A$3:$A$31<>""),0,MATCH(I3,Rent_Roll_Calculations_Headers,0)),""))} | J9: {=IF(J5="Yes",IFERROR(INDEX(_xlfn._xlws.FILTER('Rent Roll Calculations'!$A$3:$AH$33,'Rent Roll Calculations'!$A$3:$A$33<>""),0,MATCH(J3,Rent_Roll_Calculations_Headers,0)),""),IFERROR(INDEX(_xlfn._xlws.FILTER('Rent Roll Calculations'!$A$3:$AH$31,'Rent Roll Calculations'!$A$3:$A$31<>""),0,MATCH(J3,Rent_Roll_Calculations_Headers,0)),""))} | ... M9: {=IF(M5="Yes",IFERROR(INDEX(_xlfn._xlws.FILTER('Rent Roll Calculations'!$A$3:$AH$33,'Rent Roll Calculations'!$A$3:$A$33<>""),0,MATCH(M3,Rent_Roll_Calculations_Headers,0)),""),IFERROR(INDEX(_xlfn._xlws.FILTER('Rent Roll Calculations'!$A$3:$AH$31,'Rent Roll Calculations'!$A$3:$A$31<>""),0,MATCH(M3,Rent_Roll_Calculations_Headers,0)),""))}
B10: 0 | F10: 0 | I10: 0
B11: Gross Annualized Rents | F11: 0 | I11: 0
P14: {={" "}}

Sheet Operating Statement
E2: OPERATING STATEMENT | Z2: Remove Input Shading | AA2: No
E4: INCOME | I4: Prior 3 | K4: Prior 2 | M4: Prior 1 | O4: CURRENT | Q4: YEAR 1 | S4: Reno | T4: NOTES | U4: PER UNIT | V4: PER SF
E5: Rental Income
E6: Gross Potential Rent | O6: ='Annualized Rents'!$B$3 -> 0 | Q6: =O6*(1+Year1_RentGrowth) -> 0 | S6: ='Annualized Rents'!$B$4 -> 0 | U6: =IFERROR(Q6/Units,0) -> 0 | V6: =IFERROR(Q6/Total_Sq_Ft,0) -> 0
E7: Loss / Gain to Lease | J7: =IFERROR(-I7/I6,0) -> 0 | L7: =IFERROR(-K7/K6,0) -> 0 | N7: =IFERROR(-M7/M6,0) -> 0 | O7: =O8-O6 -> 0 | P7: =IFERROR(-O7/O6,0) -> 0 | Q7: =-Q6*R7 -> 0 | U7: =IFERROR(Q7/Units,0) -> 0 | V7: =IFERROR(Q7/Total_Sq_Ft,0) -> 0
E8: Gross Scheduled Rent | I8: =I6+I7 -> 0 | K8: =K6+K7 -> 0 | M8: =M6+M7 -> 0 | O8: =INDEX(Annualized_Total_Rents,MATCH(E8,Annualized_Rents_OS_Type,0),1) -> 0 | Q8: =+Q6+Q7 -> 0 | S8: =+S6+S7 -> 0 | U8: =IFERROR(Q8/Units,0) -> 0 | V8: =IFERROR(Q8/Total_Sq_Ft,0) -> 0
E9: Physical Vacancy | J9: =IFERROR(-I9/I8,0) -> 0 | L9: =IFERROR(-K9/K8,0) -> 0 | N9: =IFERROR(-M9/M8,0) -> 0 | O9: =-O8*P9 -> 0 | Q9: =-R9*Q8 -> 0 | U9: =IFERROR(Q9/Units,0) -> 0 | V9: =IFERROR(Q9/Total_Sq_Ft,0) -> 0
E10: Economic Vacancy
E11: Non-Revenue Units | J11: =IFERROR(-I11/I8,0) -> 0 | L11: =IFERROR(-K11/K8,0) -> 0 | N11: =IFERROR(-M11/M8,0) -> 0 | P11: =IFERROR(-O11/O8,0) -> 0 | Q11: =-$Q$8*R11 -> 0 | U11: =IFERROR(Q11/Units,0) -> 0 | V11: =IFERROR(Q11/Total_Sq_Ft,0) -> 0
E12: Bad Debt | J12: =IFERROR(-I12/I8,0) -> 0 | L12: =IFERROR(-K12/K8,0) -> 0 | N12: =IFERROR(-M12/M8,0) -> 0 | P12: =IFERROR(-O12/O8,0) -> 0 | Q12: =-$Q$8*R12 -> 0 | U12: =IFERROR(Q12/Units,0) -> 0 | V12: =IFERROR(Q12/Total_Sq_Ft,0) -> 0
E13: Concession | J13: =IFERROR(-I13/I8,0) -> 0 | L13: =IFERROR(-K13/K8,0) -> 0 | N13: =IFERROR(-M13/M8,0) -> 0 | P13: =IFERROR(-O13/O8,0) -> 0 | Q13: =-$Q$8*R13 -> 0 | U13: =IFERROR(Q13/Units,0) -> 0 | V13: =IFERROR(Q13/Total_Sq_Ft,0) -> 0
E14: TOTAL VACANCY | I14: =SUM(I11:I13)+I9 -> 0 | J14: =IFERROR(-I14/I8,1) -> 1 | K14: =SUM(K11:K13)+K9 -> 0 | L14: =IFERROR(-K14/K8,1) -> 1 | M14: =SUM(M11:M13)+M9 -> 0 | N14: =IFERROR(-M14/M8,1) -> 1 | O14: =SUM(O11:O13)+O9 -> 0 | P14: =IFERROR(-O14/O8,1) -> 1 | Q14: =SUM(Q11:Q13)+Q9 -> 0 | R14: =IFERROR(-Q14/Q8,1) -> 1 | S14: =SUM(S11:S13)+S9 -> 0 | U14: =IFERROR(Q14/Units,0) -> 0 | V14: =IFERROR(Q14/Total_Sq_Ft,0) -> 0
E15: Economic Occupancy | I15: =100%-J14 -> 0 | K15: =100%-L14 -> 0 | M15: =100%-N14 -> 0 | O15: =100%-P14 -> 0 | Q15: =100%-R14 -> 0 | S15: =IFERROR(1+S14/S8,"")
E16: Effective Rental Income | I16: =+I8+I14 -> 0 | K16: =+K8+K14 -> 0 | M16: =+M8+M14 -> 0 | O16: =+O8+O14 -> 0 | Q16: =+Q8+Q14 -> 0 | S16: =+S8+S14 -> 0 | U16: =IFERROR(Q16/Units,0) -> 0 | V16: =IFERROR(Q16/Total_Sq_Ft,0) -> 0
E17: Other Income
E18: Utility Bill-Back | I18: 0 | K18: 0 | M18: 0 | U18: =IFERROR(Q18/Units,0) -> 0 | V18: =IFERROR(Q18/Total_Sq_Ft,0) -> 0
E19: All Other Income | I19: 0 | K19: 0 | M19: 0 | U19: =IFERROR(Q19/Units,0) -> 0 | V19: =IFERROR(Q19/Total_Sq_Ft,0) -> 0
E20: TOTAL OTHER INCOME | I20: =SUM(I18:I19) -> 0 | K20: =SUM(K18:K19) -> 0 | M20: =SUM(M18:M19) -> 0 | O20: =SUM(O18:O19) -> 0 | Q20: =SUM(Q18:Q19) -> 0 | S20: =SUM(S18:S19) -> 0 | U20: =IFERROR(Q20/Units,0) -> 0 | V20: =IFERROR(Q20/Total_Sq_Ft,0) -> 0
E21: EFFECTIVE GROSS INCOME | I21: =I16+I20 -> 0 | K21: =K16+K20 -> 0 | M21: =M16+M20 -> 0 | O21: =O16+O20 -> 0 | Q21: =Q16+Q20 -> 0 | S21: =S16+S20 -> 0 | U21: =IFERROR(Q21/Units,0) -> 0 | V21: =IFERROR(Q21/Total_Sq_Ft,0) -> 0
E23: EXPENSES | I23: =I4 -> Prior 3 | K23: =K4 -> Prior 2 | M23: =M4 -> Prior 1 | O23: =O4 -> CURRENT | Q23: =Q4 -> YEAR 1 | T23: NOTES | U23: PER UNIT | V23: PER SF
E24: Real Estate Taxes | U24: =IFERROR(Q24/Units,0) -> 0 | V24: =IFERROR(Q24/Total_Sq_Ft,0) -> 0
E25: Insurance | U25: =IFERROR(Q25/Units,0) -> 0 | V25: =IFERROR(Q25/Total_Sq_Ft,0) -> 0
C26: Utilities | E26: Utilities - Electric | U26: =IFERROR(Q26/Units,0) -> 0 | V26: =IFERROR(Q26/Total_Sq_Ft,0) -> 0
E27: Utilities - Water & Sewer | U27: =IFERROR(Q27/Units,0) -> 0 | V27: =IFERROR(Q27/Total_Sq_Ft,0) -> 0
E28: Utilities - Gas | U28: =IFERROR(Q28/Units,0) -> 0 | V28: =IFERROR(Q28/Total_Sq_Ft,0) -> 0
C29: Operating Expenses | E29: Trash Removal | U29: =IFERROR(Q29/Units,0) -> 0 | V29: =IFERROR(Q29/Total_Sq_Ft,0) -> 0
E30: Repairs & Maintenance | U30: =IFERROR(Q30/Units,0) -> 0 | V30: =IFERROR(Q30/Total_Sq_Ft,0) -> 0
E31: Landscaping | U31: =IFERROR(Q31/Units,0) -> 0 | V31: =IFERROR(Q31/Total_Sq_Ft,0) -> 0
E32: Marketing & Advertising | U32: =IFERROR(Q32/Units,0) -> 0 | V32: =IFERROR(Q32/Total_Sq_Ft,0) -> 0
E33: Payroll | U33: =IFERROR(Q33/Units,0) -> 0 | V33: =IFERROR(Q33/Total_Sq_Ft,0) -> 0
E34: Alarm Monitoring/Inspection | U34: =IFERROR(Q34/Units,0) -> 0 | V34: =IFERROR(Q34/Total_Sq_Ft,0) -> 0
E35: General & Administrative | U35: =IFERROR(Q35/Units,0) -> 0 | V35: =IFERROR(Q35/Total_Sq_Ft,0) -> 0
E36: Misc. Expenses | U36: =IFERROR(Q36/Units,0) -> 0 | V36: =IFERROR(Q36/Total_Sq_Ft,0) -> 0
E37: Operating Reserves | U37: =IFERROR(Q37/Units,0) -> 0 | V37: =IFERROR(Q37/Total_Sq_Ft,0) -> 0
E38: Management Fee | O38: =O21*P38 -> 0 | Q38: =R38*Q21 -> 0 | U38: =IFERROR(Q38/Units,0) -> 0 | V38: =IFERROR(Q38/Total_Sq_Ft,0) -> 0
E39: TOTAL EXPENSES | I39: =SUM(I24:I38) -> 0 | K39: =SUM(K24:K38) -> 0 | M39: =SUM(M24:M38) -> 0 | O39: =SUM(O24:O38) -> 0 | Q39: =SUM(Q24:Q38) -> 0 | S39: =SUM(S24:S38) -> 0 | U39: =IFERROR(Q39/Units,0) -> 0 | V39: =IFERROR(Q39/Total_Sq_Ft,0) -> 0
E40: EXPENSES AS % OF EGI | I40: =IFERROR(I39/I21,0) -> 0 | K40: =IFERROR(K39/K21,0) -> 0 | M40: =IFERROR(M39/M21,0) -> 0 | O40: =IFERROR(O39/O21,0) -> 0 | Q40: =IFERROR(Q39/Q21,0) -> 0 | S40: =IFERROR(S39/S21,0) -> 0
E41: NET OPERATING INCOME | I41: =I21-I39 -> 0 | K41: =K21-K39 -> 0 | M41: =M21-M39 -> 0 | O41: =O21-O39 -> 0 | Q41: =Q21-Q39 -> 0 | S41: =S21-S39 -> 0 | U41: =IFERROR(Q41/Units,0) -> 0 | V41: =IFERROR(Q41/Total_Sq_Ft,0) -> 0
E42: Notes and assumptions to the above analysis are on the following page.

Sheet Notes
C3: NOTES TO OPERATING STATEMENT
C4: 1
C5: 2
C6: 3
C7: 4
C8: 5
C9: 6
C10: 7
C11: 8
C12: 9
C13: 10
C14: 11
C15: 12
... C33: 30

Sheet Pricing Detail
E1: PRICING DETAILS
E3: SUMMARY | L3: OPERATING DATA | S3: Rent Multiplier: | T3: GRM
E4: Price | G4: =IFERROR(IF(Priced="Unpriced","", Input!Q21),"") -> 0
E5: Down Payment | G5: =IFERROR(IF(Priced="Unpriced","-",-'Cash Flow'!F42+'Cash Flow'!F37),"-") -> 0 | H5: =IFERROR(IF(Priced="Unpriced","",G5/G4),"")
E6: Number of Units | G6: =Units -> 0 | L6: INCOME | N6: ='Operating Statement'!O4 -> CURRENT | P6: ='Operating Statement'!Q4 -> YEAR 1 | Q6: ='Operating Statement'!S4 -> Reno
E7: Price Per Unit | G7: =IFERROR(IF(Priced="Unpriced","-",G4/G6),0) -> 0 | L7: Gross Scheduled Rent | N7: ='Operating Statement'!O8 -> 0 | P7: ='Operating Statement'!Q8 -> 0 | Q7: ='Operating Statement'!S8 -> 0
E8: Price Per SqFt | G8: =IFERROR(IF(Priced="Unpriced","-",G4/G9),0) -> 0 | L8: Less: Vacancy/Deductions | M8: =IFERROR(N8/N7,0) -> 0 | N8: =-'Operating Statement'!O14 -> 0 | O8: =IFERROR(P8/P7,0) -> 0 | P8: =-'Operating Statement'!Q14 -> 0 | Q8: =-'Operating Statement'!S14 -> 0
E9: ='Rent Roll Summary'!T1&" SqFt" -> SqFt | G9: =Total_Sq_Ft -> 0 | L9: Total Effective Rental Income | N9: ='Operating Statement'!O16 -> 0 | P9: ='Operating Statement'!Q16 -> 0 | Q9: ='Operating Statement'!S16 -> 0
L10: Other Income | N10: ='Operating Statement'!O20 -> 0 | P10: ='Operating Statement'!Q20 -> 0 | Q10: ='Operating Statement'!S20 -> 0
L11: Effective Gross Income | N11: ='Operating Statement'!O21 -> 0 | P11: ='Operating Statement'!Q21 -> 0 | Q11: ='Operating Statement'!S21 -> 0
E12: RETURNS | G12: =N6 -> CURRENT | H12: =P6 -> YEAR 1 | I12: =Q6 -> Reno | L12: Less: Expenses | M12: =IFERROR(N12/$N$11,0) -> 0 | N12: ='Operating Statement'!O39 -> 0 | O12: =IFERROR(P12/P11,0) -> 0 | P12: ='Operating Statement'!Q39 -> 0 | Q12: ='Operating Statement'!S39 -> 0
E13: CAP Rate | G13: =IFERROR(N13/$G$4,0) -> 0 | H13: =IFERROR(P13/$G$4,0) -> 0 | I13: =IFERROR(Q13/$G$4,0) -> 0 | L13: Net Operating Income | N13: =N11-N12 -> 0 | P13: =P11-P12 -> 0 | Q13: =Q11-Q12 -> 0
E14: =IFERROR(IF(RentMult="GIM","GIM","GRM"),"") -> GRM | G14: =IFERROR($G$4/IF(RentMult="GIM",N7+N10,N7),0) -> 0 | H14: =IFERROR($G$4/IF(RentMult="GIM",P7+P10,P7),0) -> 0 | I14: =IFERROR($G$4/IF(RentMult="GIM",Q7+Q10,Q7),0) -> 0 | L14: Cash Flow | N14: =N13 -> 0 | P14: ='Cash Flow'!G33 -> 0 | Q14: =Q13 -> 0
E15: Cash-on-Cash | G15: =M16 -> 0 | H15: =O16 -> 0 | I15: =IFERROR(Q16/G5,0) -> 0 | L15: Debt Service | N15: =-SUM('Cash Flow'!G40:G41) -> 0 | P15: =-SUM('Cash Flow'!G40:G41) -> 0 | Q15: =-SUM('Cash Flow'!G40:G41) -> 0
E16: Debt Coverage Ratio | G16: =IFERROR(IF(Acq_Financing_Type_Switch="All Cash","N/A",N13/N15),0) -> 0 | H16: =IFERROR(IF(SwitchAcqMethod="All Cash","N/A",P13/P15),0) -> 0 | I16: =IFERROR(IF(SwitchAcqMethod="All Cash","N/A",Q13/Q15),0) -> 0 | L16: Net Cash Flow After Debt Service | M16: =IFERROR(IF(Priced="Unpriced","",N16/$G$5),0) -> 0 | N16: =N14-N15 -> 0 | O16: =IFERROR(IF(Priced="Unpriced","",P16/$G$5),0) -> 0 | P16: =P14-P15 -> 0 | Q16: =Q14-Q15 -> 0
L17: Principal Reduction | N17: =-'Cash Flow'!G41 -> 0 | P17: =-'Cash Flow'!H41 -> 0 | Q17: =-'Cash Flow'!H41 -> 0
L18: TOTAL RETURN | M18: =IFERROR(IF(Priced="Unpriced","",IFERROR(N18/$G$5,IFERROR(N18/$G$4,0))),"") -> 0 | N18: =N16+N17 -> 0 | O18: =IFERROR(IF(Priced="Unpriced","",IFERROR(P18/$G$5,IFERROR(P18/$G$4,0))),"") -> 0 | P18: =P16+P17 -> 0 | Q18: =Q16+Q17 -> 0
E19: FINANCING | H19: 1st Loan | I19: =IF(Mezz_Switch="Yes","Mezzanine","") -> Mezzanine
E20: Loan Amount | H20: =IF(Acq_Financing_Type_Switch = "Financed - Assumed Loan", SED_Loan_Balance, NEW_Loan_Balance) -> 0 | I20: =IF(Mezz_Switch = "Yes", Mezz_Loan_Balance,"") -> 0
E21: Loan Type | H21: =IF(Acq_Financing_Type_Switch = "Financed - Assumed Loan", "Assumed", "New") -> New | I21: =IF(Mezz_Switch = "Yes", "New","") -> New | L21: EXPENSES | N21: Current | P21: Year 1 | Q21: Reno
E22: Interest Rate | H22: =IF(Acq_Financing_Type_Switch = "Financed - Assumed Loan", SED_Interest_Rate, NEW_Interest_Rate) -> 0 | I22: =IF(Mezz_Switch = "Yes", Mezz_Interest_Rate,"") -> 0 | L22: Real Estate Taxes | N22: ='Operating Statement'!O24 -> 0 | P22: ='Operating Statement'!Q24 -> 0 | Q22: ='Operating Statement'!S24 -> 0
E23: Amortization | H23: =IF(Acq_Financing_Type_Switch = "Financed - Assumed Loan", SED_Amort, NEW_Amort) -> 0 | I23: =IF(Mezz_Switch = "Yes", Mezz_Amort,"") -> 0 | L23: Insurance | N23: ='Operating Statement'!O25 -> 0 | P23: ='Operating Statement'!Q25 -> 0 | Q23: ='Operating Statement'!S25 -> 0
E24: Year Due | H24: =IF(Acq_Financing_Type_Switch = "Financed - Assumed Loan", YEAR(SED_Loan_Due_Date), YEAR(NEW_Loan_Due_Date)) -> #NUM! | I24: =IF(Mezz_Switch = "Yes",YEAR(Mezz_Loan_Due_Date),"") -> #NUM! | L24: Utilities - Electric | N24: ='Operating Statement'!O26 -> 0 | P24: ='Operating Statement'!Q26 -> 0 | Q24: ='Operating Statement'!S26 -> 0
E25: Loan information is subject to change. Contact your Marcus & Millichap Capital Corporation representative. | L25: Utilities - Water & Sewer | N25: ='Operating Statement'!O27 -> 0 | P25: ='Operating Statement'!Q27 -> 0 | Q25: ='Operating Statement'!S27 -> 0
L26: Utilities - Gas | N26: ='Operating Statement'!O28 -> 0 | P26: ='Operating Statement'!Q28 -> 0 | Q26: ='Operating Statement'!S28 -> 0
E27: # OF UNITS | F27: UNIT TYPE | H27: SQFT/UNIT | I27: SCHEDULED RENTS | J27: MARKET RENTS | L27: Trash Removal | N27: ='Operating Statement'!O29 -> 0 | P27: ='Operating Statement'!Q29 -> 0 | Q27: ='Operating Statement'!S29 -> 0
E28: {=Unit_Amt_Summary} -> 0 | F28: {=Unit_Type_Summary} | H28: {=Summary_SQFT_UNIT} -> 0 | I28: {=Summary_SCHEDULED_RENTS} -> 0 | J28: {=Summary_MARKET_RENTS} -> 0 | L28: Repairs & Maintenance | N28: ='Operating Statement'!O30 -> 0 | P28: ='Operating Statement'!Q30 -> 0 | Q28: ='Operating Statement'!S30 -> 0
L29: Landscaping | N29: ='Operating Statement'!O31 -> 0 | P29: ='Operating Statement'!Q31 -> 0 | Q29: ='Operating Statement'!S31 -> 0
L30: Marketing & Advertising | N30: ='Operating Statement'!O32 -> 0 | P30: ='Operating Statement'!Q32 -> 0 | Q30: ='Operating Statement'!S32 -> 0
L31: Payroll | N31: ='Operating Statement'!O33 -> 0 | P31: ='Operating Statement'!Q33 -> 0 | Q31: ='Operating Statement'!S33 -> 0
L32: Alarm Monitoring/Inspection | N32: ='Operating Statement'!O34 -> 0 | P32: ='Operating Statement'!Q34 -> 0 | Q32: ='Operating Statement'!S34 -> 0
L33: General & Administrative | N33: ='Operating Statement'!O35 -> 0 | P33: ='Operating Statement'!Q35 -> 0 | Q33: ='Operating Statement'!S35 -> 0
L34: Misc. Expenses | N34: ='Operating Statement'!O36 -> 0 | P34: ='Operating Statement'!Q36 -> 0 | Q34: ='Operating Statement'!S36 -> 0
E35: IRR Year | G35: IRR Unlevered | H35: =IF(Acq_Financing_Type_Switch="All Cash","IRR Unlevered","IRR Levered") -> IRR Levered | L35: Operating Reserves | N35: ='Operating Statement'!O37 -> 0 | P35: ='Operating Statement'!Q37 -> 0 | Q35: ='Operating Statement'!S37 -> 0
E36: 5 | G36: =IFERROR('Cash Flow'!F57,0) -> 0 | H36: =IFERROR('Cash Flow'!F70,0) -> 0 | L36: Management Fee | N36: ='Operating Statement'!O38 -> 0 | P36: ='Operating Statement'!Q38 -> 0 | Q36: ='Operating Statement'!S38 -> 0
E37: 7 | G37: =IFERROR('Cash Flow'!F59,0) -> 0 | H37: =IFERROR('Cash Flow'!F72,0) -> 0 | L37: TOTAL EXPENSES | N37: =SUM(N22:N36) -> 0 | P37: =SUM(P22:P36) -> 0 | Q37: =SUM(Q22:Q36) -> 0
E38: 10 | G38: =IFERROR('Cash Flow'!F62,0) -> 0 | H38: =IFERROR('Cash Flow'!F75,0) -> 0 | L38: Expenses/Unit | N38: =IFERROR(N37/$G$6,0) -> 0 | P38: =IFERROR(P37/$G$6,0) -> 0 | Q38: =IFERROR(Q37/$G$6,0) -> 0
L39: Expenses/SF | N39: =IFERROR(N37/$G$9,0) -> 0 | P39: =IFERROR(P37/$G$9,0) -> 0 | Q39: =IFERROR(Q37/$G$9,0) -> 0

Sheet Growth Rates
C1: GROWTH RATE PROJECTIONS
C3: Income | D3: ='Operating Statement'!Q4 -> YEAR 1 | E3: ='Cash Flow'!H4 -> 701 | F3: ='Cash Flow'!I4 -> 1066 | G3: ='Cash Flow'!J4 -> 1431 | H3: ='Cash Flow'!K4 -> 1797 | I3: ='Cash Flow'!L4 -> 2162 | J3: ='Cash Flow'!M4 -> 2527 | K3: ='Cash Flow'!N4 -> 2892 | L3: ='Cash Flow'!O4 -> 3258 | M3: ='Cash Flow'!P4 -> 3623
C4: ='Operating Statement'!E5 -> Rental Income
C5: ='Operating Statement'!E6 -> Gross Potential Rent | D5: =IFERROR(('Operating Statement'!Q6-'Operating Statement'!O6)/'Operating Statement'!O6,"") | E5: 0.05 | F5: 0.04 | G5: 0.04 | H5: 0.03 | I5: 0.03 | J5: 0.03 | K5: 0.03 | L5: 0.03 | M5: 0.03
C6: ='Operating Statement'!E7&"(1)" -> Loss / Gain to Lease(1) | D6: ='Operating Statement'!R7 -> 0 | E6: 0.02 | F6: 0.02 | G6: 0.01 | H6: 0.01 | I6: 0.01 | J6: 0.01 | K6: 0.01 | L6: 0.01 | M6: 0.01
C7: ='Operating Statement'!E9 -> Physical Vacancy | E7: 0.05 | F7: 0.05 | G7: 0.05 | H7: 0.03 | I7: 0.03 | J7: 0.03 | K7: 0.03 | L7: 0.03 | M7: 0.03
C8: Economic Vacancy (1)
C9: ='Operating Statement'!E11 -> Non-Revenue Units | E9: 0.001 | F9: 0.001 | G9: 0.001 | H9: 0.001 | I9: 0.001 | J9: 0.001 | K9: 0.001 | L9: 0.001 | M9: 0.001
C10: ='Operating Statement'!E12 -> Bad Debt | E10: 0.003 | F10: 0.003 | G10: 0.003 | H10: 0.003 | I10: 0.003 | J10: 0.003 | K10: 0.003 | L10: 0.003 | M10: 0.003
C11: ='Operating Statement'!E13 -> Concession | E11: 0.001 | F11: 0.001 | G11: 0.001 | H11: 0.001 | I11: 0.001 | J11: 0.001 | K11: 0.001 | L11: 0.001 | M11: 0.001
C12: Total Vacancy | E12: =SUM(E9:E11)+E7 -> 0.055 | F12: =SUM(F9:F11)+F7 -> 0.055 | G12: =SUM(G9:G11)+G7 -> 0.055 | H12: =SUM(H9:H11)+H7 -> 0.035 | I12: =SUM(I9:I11)+I7 -> 0.035 | J12: =SUM(J9:J11)+J7 -> 0.035 | K12: =SUM(K9:K11)+K7 -> 0.035 | L12: =SUM(L9:L11)+L7 -> 0.035 | M12: =SUM(M9:M11)+M7 -> 0.035
C13: ='Operating Statement'!E20 -> TOTAL OTHER INCOME | E13: 0.02 | F13: 0.02 | G13: 0.02 | H13: 0.02 | I13: 0.02 | J13: 0.02 | K13: 0.02 | L13: 0.02 | M13: 0.02
C15: ='Operating Statement'!E23 -> EXPENSES | D15: ='Operating Statement'!Q4 -> YEAR 1 | E15: ='Cash Flow'!H4 -> 701 | F15: ='Cash Flow'!I4 -> 1066 | G15: ='Cash Flow'!J4 -> 1431 | H15: ='Cash Flow'!K4 -> 1797 | I15: ='Cash Flow'!L4 -> 2162 | J15: ='Cash Flow'!M4 -> 2527 | K15: ='Cash Flow'!N4 -> 2892 | L15: ='Cash Flow'!O4 -> 3258 | M15: ='Cash Flow'!P4 -> 3623
C16: ='Cash Flow'!E22 -> Operating Expenses | E16: 0.03 | F16: 0.03 | G16: 0.03 | H16: 0.03 | I16: 0.03 | J16: 0.03 | K16: 0.03 | L16: 0.03 | M16: 0.03
C17: ='Cash Flow'!E23 -> Real Estate Taxes | E17: 0.02 | F17: 0.02 | G17: 0.02 | H17: 0.02 | I17: 0.02 | J17: 0.02 | K17: 0.02 | L17: 0.02 | M17: 0.02
C18: ='Cash Flow'!E24 -> Insurance | E18: 0.03 | F18: 0.03 | G18: 0.03 | H18: 0.03 | I18: 0.03 | J18: 0.03 | K18: 0.03 | L18: 0.03 | M18: 0.03
C19: ='Cash Flow'!E25 -> Utilities | E19: 0.03 | F19: 0.03 | G19: 0.03 | H19: 0.03 | I19: 0.03 | J19: 0.03 | K19: 0.03 | L19: 0.03 | M19: 0.03
C20: ='Operating Statement'!E38&" (2)" -> Management Fee (2) | D20: ='Operating Statement'!R38 -> 0
C21: (1) Displayed as a % of Gross Potential Rent
C22: (2) Management Fees Calculated by % of EGR

Sheet Cash Flow
E1: CASH FLOW
E4: INCOME | F4: ='Operating Statement'!O4 -> CURRENT | G4: ='Debt Input'!T15 -> 366 | H4: ='Debt Input'!U15 -> 701 | I4: ='Debt Input'!V15 -> 1066 | J4: ='Debt Input'!W15 -> 1431 | K4: ='Debt Input'!X15 -> 1797 | L4: ='Debt Input'!Y15 -> 2162 | M4: ='Debt Input'!Z15 -> 2527 | N4: ='Debt Input'!AA15 -> 2892 | ... P4: ='Debt Input'!AC15 -> 3623
E5: ='Operating Statement'!E5 -> Rental Income
E6: ='Operating Statement'!E6 -> Gross Potential Rent | F6: ='Operating Statement'!O6 -> 0 | G6: ='Operating Statement'!Q6 -> 0 | H6: =G6*(1+'Growth Rates'!E5) -> 0 | I6: =H6*(1+'Growth Rates'!F5) -> 0 | J6: =I6*(1+'Growth Rates'!G5) -> 0 | K6: =J6*(1+'Growth Rates'!H5) -> 0 | L6: =K6*(1+'Growth Rates'!I5) -> 0 | M6: =L6*(1+'Growth Rates'!J5) -> 0 | N6: =M6*(1+'Growth Rates'!K5) -> 0 | O6: =N6*(1+'Growth Rates'!L5) -> 0 | P6: =O6*(1+'Growth Rates'!M5) -> 0
E7: ='Operating Statement'!E7 -> Loss / Gain to Lease | F7: ='Operating Statement'!O7 -> 0 | G7: ='Operating Statement'!Q7 -> 0 | H7: =-'Growth Rates'!E6*'Cash Flow'!H6 -> 0 | I7: =-'Growth Rates'!F6*'Cash Flow'!I6 -> 0 | J7: =-'Growth Rates'!G6*'Cash Flow'!J6 -> 0 | K7: =-'Growth Rates'!H6*'Cash Flow'!K6 -> 0 | L7: =-'Growth Rates'!I6*'Cash Flow'!L6 -> 0 | M7: =-'Growth Rates'!J6*'Cash Flow'!M6 -> 0 | N7: =-'Growth Rates'!K6*'Cash Flow'!N6 -> 0 | O7: =-'Growth Rates'!L6*'Cash Flow'!O6 -> 0 | P7: =-'Growth Rates'!M6*'Cash Flow'!P6 -> 0
E8: ='Operating Statement'!E8 -> Gross Scheduled Rent | F8: =SUM(F6:F7) -> 0 | G8: =SUM(G6:G7) -> 0 | H8: =SUM(H6:H7) -> 0 | I8: =SUM(I6:I7) -> 0 | J8: =SUM(J6:J7) -> 0 | K8: =SUM(K6:K7) -> 0 | L8: =SUM(L6:L7) -> 0 | M8: =SUM(M6:M7) -> 0 | ... P8: =SUM(P6:P7) -> 0
E9: ='Operating Statement'!E9 -> Physical Vacancy | F9: ='Operating Statement'!O9 -> 0 | G9: ='Operating Statement'!Q9 -> 0 | H9: =-'Growth Rates'!E7*H8 -> 0 | I9: =-'Growth Rates'!F7*I8 -> 0 | J9: =-'Growth Rates'!G7*J8 -> 0 | K9: =-'Growth Rates'!H7*K8 -> 0 | L9: =-'Growth Rates'!I7*L8 -> 0 | M9: =-'Growth Rates'!J7*M8 -> 0 | N9: =-'Growth Rates'!K7*N8 -> 0 | O9: =-'Growth Rates'!L7*O8 -> 0 | P9: =-'Growth Rates'!M7*P8 -> 0
E10: ='Operating Statement'!E10 -> Economic Vacancy
E11: ='Operating Statement'!E11 -> Non-Revenue Units | F11: ='Operating Statement'!O11 -> 0 | G11: ='Operating Statement'!Q11 -> 0 | H11: =-'Growth Rates'!E9*'Cash Flow'!H8 -> 0 | I11: =-'Growth Rates'!F9*'Cash Flow'!I8 -> 0 | J11: =-'Growth Rates'!G9*'Cash Flow'!J8 -> 0 | K11: =-'Growth Rates'!H9*'Cash Flow'!K8 -> 0 | L11: =-'Growth Rates'!I9*'Cash Flow'!L8 -> 0 | M11: =-'Growth Rates'!J9*'Cash Flow'!M8 -> 0 | N11: =-'Growth Rates'!K9*'Cash Flow'!N8 -> 0 | O11: =-'Growth Rates'!L9*'Cash Flow'!O8 -> 0 | P11: =-'Growth Rates'!M9*'Cash Flow'!P8 -> 0
E12: ='Operating Statement'!E12 -> Bad Debt | F12: ='Operating Statement'!O12 -> 0 | G12: ='Operating Statement'!Q12 -> 0 | H12: =-'Growth Rates'!E10*'Cash Flow'!H8 -> 0 | I12: =-'Growth Rates'!F10*'Cash Flow'!I8 -> 0 | J12: =-'Growth Rates'!G10*'Cash Flow'!J8 -> 0 | K12: =-'Growth Rates'!H10*'Cash Flow'!K8 -> 0 | L12: =-'Growth Rates'!I10*'Cash Flow'!L8 -> 0 | M12: =-'Growth Rates'!J10*'Cash Flow'!M8 -> 0 | N12: =-'Growth Rates'!K10*'Cash Flow'!N8 -> 0 | O12: =-'Growth Rates'!L10*'Cash Flow'!O8 -> 0 | P12: =-'Growth Rates'!M10*'Cash Flow'!P8 -> 0
E13: ='Operating Statement'!E13 -> Concession | F13: ='Operating Statement'!O13 -> 0 | G13: ='Operating Statement'!Q13 -> 0 | H13: =-'Growth Rates'!E11*'Cash Flow'!H8 -> 0 | I13: =-'Growth Rates'!F11*'Cash Flow'!I8 -> 0 | J13: =-'Growth Rates'!G11*'Cash Flow'!J8 -> 0 | K13: =-'Growth Rates'!H11*'Cash Flow'!K8 -> 0 | L13: =-'Growth Rates'!I11*'Cash Flow'!L8 -> 0 | M13: =-'Growth Rates'!J11*'Cash Flow'!M8 -> 0 | N13: =-'Growth Rates'!K11*'Cash Flow'!N8 -> 0 | O13: =-'Growth Rates'!L11*'Cash Flow'!O8 -> 0 | P13: =-'Growth Rates'!M11*'Cash Flow'!P8 -> 0
E14: ='Operating Statement'!E14 -> TOTAL VACANCY | F14: =SUM(F9:F13) -> 0 | G14: =SUM(G9:G13) -> 0 | H14: =SUM(H9:H13) -> 0 | I14: =SUM(I9:I13) -> 0 | J14: =SUM(J9:J13) -> 0 | K14: =SUM(K9:K13) -> 0 | L14: =SUM(L9:L13) -> 0 | M14: =SUM(M9:M13) -> 0 | ... P14: =SUM(P9:P13) -> 0
E15: ='Operating Statement'!E16 -> Effective Rental Income | F15: =+F8+F14 -> 0 | G15: =+G8+G14 -> 0 | H15: =+H8+H14 -> 0 | I15: =+I8+I14 -> 0 | J15: =+J8+J14 -> 0 | K15: =+K8+K14 -> 0 | L15: =+L8+L14 -> 0 | M15: =+M8+M14 -> 0 | ... P15: =+P8+P14 -> 0
E16: ='Operating Statement'!E17 -> Other Income
E17: ='Operating Statement'!E18 -> Utility Bill-Back | F17: ='Operating Statement'!O18 -> 0 | G17: ='Operating Statement'!Q18 -> 0 | H17: =G17*(1+'Growth Rates'!E13) -> 0 | I17: =H17*(1+'Growth Rates'!F13) -> 0 | J17: =I17*(1+'Growth Rates'!G13) -> 0 | K17: =J17*(1+'Growth Rates'!H13) -> 0 | L17: =K17*(1+'Growth Rates'!I13) -> 0 | M17: =L17*(1+'Growth Rates'!J13) -> 0 | N17: =M17*(1+'Growth Rates'!K13) -> 0 | O17: =N17*(1+'Growth Rates'!L13) -> 0 | P17: =O17*(1+'Growth Rates'!M13) -> 0
E18: ='Operating Statement'!E19 -> All Other Income | F18: ='Operating Statement'!O19 -> 0 | G18: ='Operating Statement'!Q19 -> 0 | H18: =G18*(1+'Growth Rates'!E13) -> 0 | I18: =H18*(1+'Growth Rates'!F13) -> 0 | J18: =I18*(1+'Growth Rates'!G13) -> 0 | K18: =J18*(1+'Growth Rates'!H13) -> 0 | L18: =K18*(1+'Growth Rates'!I13) -> 0 | M18: =L18*(1+'Growth Rates'!J13) -> 0 | N18: =M18*(1+'Growth Rates'!K13) -> 0 | O18: =N18*(1+'Growth Rates'!L13) -> 0 | P18: =O18*(1+'Growth Rates'!M13) -> 0
E19: ='Operating Statement'!E20 -> TOTAL OTHER INCOME | F19: ='Operating Statement'!O20 -> 0 | G19: ='Operating Statement'!Q20 -> 0 | H19: =G19*(1+'Growth Rates'!E13) -> 0 | I19: =H19*(1+'Growth Rates'!F13) -> 0 | J19: =I19*(1+'Growth Rates'!G13) -> 0 | K19: =J19*(1+'Growth Rates'!H13) -> 0 | L19: =K19*(1+'Growth Rates'!I13) -> 0 | M19: =L19*(1+'Growth Rates'!J13) -> 0 | N19: =M19*(1+'Growth Rates'!K13) -> 0 | O19: =N19*(1+'Growth Rates'!L13) -> 0 | P19: =O19*(1+'Growth Rates'!M13) -> 0
E20: ='Operating Statement'!E21 -> EFFECTIVE GROSS INCOME | F20: =F15+F19 -> 0 | G20: =G15+G19 -> 0 | H20: =H15+H19 -> 0 | I20: =I15+I19 -> 0 | J20: =J15+J19 -> 0 | K20: =K15+K19 -> 0 | L20: =L15+L19 -> 0 | M20: =M15+M19 -> 0 | ... P20: =P15+P19 -> 0
E21: EXPENSES
E22: Operating Expenses | F22: =-SUM('Operating Statement'!O29:O36) -> 0 | G22: =-SUM('Operating Statement'!Q29:Q36) -> 0 | H22: =G22*(1+'Growth Rates'!E16) -> 0 | I22: =H22*(1+'Growth Rates'!F16) -> 0 | J22: =I22*(1+'Growth Rates'!G16) -> 0 | K22: =J22*(1+'Growth Rates'!H16) -> 0 | L22: =K22*(1+'Growth Rates'!I16) -> 0 | M22: =L22*(1+'Growth Rates'!J16) -> 0 | N22: =M22*(1+'Growth Rates'!K16) -> 0 | O22: =N22*(1+'Growth Rates'!L16) -> 0 | P22: =O22*(1+'Growth Rates'!M16) -> 0
E23: ='Operating Statement'!E24 -> Real Estate Taxes | F23: =-'Operating Statement'!O24 -> 0 | G23: =-'Operating Statement'!Q24 -> 0 | H23: =G23*(1+'Growth Rates'!E17) -> 0 | I23: =H23*(1+'Growth Rates'!F17) -> 0 | J23: =I23*(1+'Growth Rates'!G17) -> 0 | K23: =J23*(1+'Growth Rates'!H17) -> 0 | L23: =K23*(1+'Growth Rates'!I17) -> 0 | M23: =L23*(1+'Growth Rates'!J17) -> 0 | N23: =M23*(1+'Growth Rates'!K17) -> 0 | O23: =N23*(1+'Growth Rates'!L17) -> 0 | P23: =O23*(1+'Growth Rates'!M17) -> 0
E24: ='Operating Statement'!E25 -> Insurance | F24: =-'Operating Statement'!O25 -> 0 | G24: =-'Operating Statement'!Q25 -> 0 | H24: =G24*(1+'Growth Rates'!E18) -> 0 | I24: =H24*(1+'Growth Rates'!F18) -> 0 | J24: =I24*(1+'Growth Rates'!G18) -> 0 | K24: =J24*(1+'Growth Rates'!H18) -> 0 | L24: =K24*(1+'Growth Rates'!I18) -> 0 | M24: =L24*(1+'Growth Rates'!J18) -> 0 | N24: =M24*(1+'Growth Rates'!K18) -> 0 | O24: =N24*(1+'Growth Rates'!L18) -> 0 | P24: =O24*(1+'Growth Rates'!M18) -> 0
E25: Utilities | F25: =-SUM('Operating Statement'!O26:O28) -> 0 | G25: =-SUM('Operating Statement'!Q26:Q28) -> 0 | H25: =G25*(1+'Growth Rates'!E19) -> 0 | I25: =H25*(1+'Growth Rates'!F19) -> 0 | J25: =I25*(1+'Growth Rates'!G19) -> 0 | K25: =J25*(1+'Growth Rates'!H19) -> 0 | L25: =K25*(1+'Growth Rates'!I19) -> 0 | M25: =L25*(1+'Growth Rates'!J19) -> 0 | N25: =M25*(1+'Growth Rates'!K19) -> 0 | O25: =N25*(1+'Growth Rates'!L19) -> 0 | P25: =O25*(1+'Growth Rates'!M19) -> 0
E26: ='Operating Statement'!E38 -> Management Fee | F26: =-'Operating Statement'!O38 -> 0 | G26: =-'Operating Statement'!Q38 -> 0 | H26: =-H20*'Growth Rates'!$D$20 -> 0 | I26: =-I20*'Growth Rates'!$D$20 -> 0 | J26: =-J20*'Growth Rates'!$D$20 -> 0 | K26: =-K20*'Growth Rates'!$D$20 -> 0 | L26: =-L20*'Growth Rates'!$D$20 -> 0 | M26: =-M20*'Growth Rates'!$D$20 -> 0 | N26: =-N20*'Growth Rates'!$D$20 -> 0 | O26: =-O20*'Growth Rates'!$D$20 -> 0 | P26: =-P20*'Growth Rates'!$D$20 -> 0
E27: Total Expenses | F27: =SUM(F22:F26) -> 0 | G27: =SUM(G22:G26) -> 0 | H27: =SUM(H22:H26) -> 0 | I27: =SUM(I22:I26) -> 0 | J27: =SUM(J22:J26) -> 0 | K27: =SUM(K22:K26) -> 0 | L27: =SUM(L22:L26) -> 0 | M27: =SUM(M22:M26) -> 0 | ... P27: =SUM(P22:P26) -> 0
E28: =+'Operating Statement'!E37 -> Operating Reserves | F28: =-'Operating Statement'!$O$37 -> 0 | G28: =-'Operating Statement'!$Q$37 -> 0 | H28: =-'Operating Statement'!$Q$37 -> 0 | I28: =-'Operating Statement'!$Q$37 -> 0 | J28: =-'Operating Statement'!$Q$37 -> 0 | K28: =-'Operating Statement'!$Q$37 -> 0 | L28: =-'Operating Statement'!$Q$37 -> 0 | M28: =-'Operating Statement'!$Q$37 -> 0 | N28: =-'Operating Statement'!$Q$37 -> 0 | ... P28: =-'Operating Statement'!$Q$37 -> 0
E29: ='Operating Statement'!E41 -> NET OPERATING INCOME | F29: =+F20+F27+F28 -> 0 | G29: =+G20+G27+G28 -> 0 | H29: =+H20+H27+H28 -> 0 | I29: =+I20+I27+I28 -> 0 | J29: =+J20+J27+J28 -> 0 | K29: =+K20+K27+K28 -> 0 | L29: =+L20+L27+L28 -> 0 | M29: =+M20+M27+M28 -> 0 | ... P29: =+P20+P27+P28 -> 0
E30: =IF(SwitchCapEx = "Yes","Renovation Costs","") | G30: =+IF(SwitchCapEx = "Yes",-Input!E27,"") | H30: =+IF(SwitchCapEx = "Yes",-Input!F27,"") | I30: =+IF(SwitchCapEx = "Yes",-Input!G27,"") | J30: =+IF(SwitchCapEx = "Yes",-Input!H27,"") | K30: =+IF(SwitchCapEx = "Yes",-Input!I27,"") | L30: =+IF(SwitchCapEx = "Yes",-Input!J27,"") | M30: =+IF(SwitchCapEx = "Yes",-Input!K27,"") | N30: =+IF(SwitchCapEx = "Yes",-Input!L27,"") | ... P30: =+IF(SwitchCapEx = "Yes",-Input!N27,"")
E31: PURCHASE PRICE / NET RESIDUAL VALUE
E32: Purchase Price/Net Residual Value | F32: =IF(Priced="Unpriced", "-", -Input!Q21) -> 0 | P32: =IFERROR(P29/Exit_CAP,"")
E33: Cash Flow Before Debt Financing | G33: =SUM(G29:G32) -> 0 | H33: =SUM(H29:H32) -> 0 | I33: =SUM(I29:I32) -> 0 | J33: =SUM(J29:J32) -> 0 | K33: =SUM(K29:K32) -> 0 | L33: =SUM(L29:L32) -> 0 | M33: =SUM(M29:M32) -> 0 | N33: =SUM(N29:N32) -> 0 | ... P33: =SUM(P29:P32) -> 0
E34: DEBT FINANCING
E35: Loan Amount | F35: {=IF(Acq_Financing_Type_Switch="All Cash",0,Current_Loan_Balance)+IF(Refi_Switch="Yes",Mezz_Loan_Balance,0)} -> 0 | G35: =IF(Acq_Financing_Type_Switch="All Cash",0,'Debt Input'!T32) | H35: =IF(Acq_Financing_Type_Switch="All Cash",0,'Debt Input'!U32) -> 0 | I35: =IF(Acq_Financing_Type_Switch="All Cash",0,'Debt Input'!V32) -> 0 | J35: =IF(Acq_Financing_Type_Switch="All Cash",0,'Debt Input'!W32) -> 0 | K35: =IF(Acq_Financing_Type_Switch="All Cash",0,'Debt Input'!X32) -> 0 | L35: =IF(Acq_Financing_Type_Switch="All Cash",0,'Debt Input'!Y32) -> 0 | M35: =IF(Acq_Financing_Type_Switch="All Cash",0,'Debt Input'!Z32) -> 0 | N35: =IF(Acq_Financing_Type_Switch="All Cash",0,'Debt Input'!AA32) -> 0 | ... P35: =IF(Acq_Financing_Type_Switch="All Cash",0,'Debt Input'!AC32) -> 0
E36: Remaining Balance | G36: =IF(Acq_Financing_Type_Switch="All Cash",0,'Debt Input'!T33) -> 0 | H36: =IF(Acq_Financing_Type_Switch="All Cash",0,'Debt Input'!U33) -> 0 | I36: =IF(Acq_Financing_Type_Switch="All Cash",0,'Debt Input'!V33) -> 0 | J36: =IF(Acq_Financing_Type_Switch="All Cash",0,'Debt Input'!W33) -> 0 | K36: =IF(Acq_Financing_Type_Switch="All Cash",0,'Debt Input'!X33) -> 0 | L36: =IF(Acq_Financing_Type_Switch="All Cash",0,'Debt Input'!Y33) -> 0 | M36: =IF(Acq_Financing_Type_Switch="All Cash",0,'Debt Input'!Z33) -> 0 | N36: =IF(Acq_Financing_Type_Switch="All Cash",0,'Debt Input'!AA33) -> 0 | ... P36: =IF(Acq_Financing_Type_Switch="All Cash",0,'Debt Input'!AC33) -> 0
E37: Loan Origination Fees | F37: =-Current_Loan_Origination_Fee-'Debt Input'!J34*'Debt Input'!J19 -> 0 | G37: =IF(Acq_Financing_Type_Switch="All Cash",0,'Debt Input'!T34) -> #VALUE! | H37: =IF(Acq_Financing_Type_Switch="All Cash",0,'Debt Input'!U34) -> 0 | I37: =IF(Acq_Financing_Type_Switch="All Cash",0,'Debt Input'!V34) -> 0 | J37: =IF(Acq_Financing_Type_Switch="All Cash",0,'Debt Input'!W34) -> 0 | K37: =IF(Acq_Financing_Type_Switch="All Cash",0,'Debt Input'!X34) -> 0 | L37: =IF(Acq_Financing_Type_Switch="All Cash",0,'Debt Input'!Y34) -> 0 | M37: =IF(Acq_Financing_Type_Switch="All Cash",0,'Debt Input'!Z34) -> 0 | N37: =IF(Acq_Financing_Type_Switch="All Cash",0,'Debt Input'!AA34) -> 0 | ... P37: =IF(Acq_Financing_Type_Switch="All Cash",0,'Debt Input'!AC34) -> 0
E38: Prepayment Penalty | G38: =IF(Acq_Financing_Type_Switch="All Cash",0,'Debt Input'!T35) -> 0 | H38: =IF(Acq_Financing_Type_Switch="All Cash",0,'Debt Input'!U35) -> 0 | I38: =IF(Acq_Financing_Type_Switch="All Cash",0,'Debt Input'!V35) -> 0 | J38: =IF(Acq_Financing_Type_Switch="All Cash",0,'Debt Input'!W35) -> 0 | K38: =IF(Acq_Financing_Type_Switch="All Cash",0,'Debt Input'!X35) -> 0 | L38: =IF(Acq_Financing_Type_Switch="All Cash",0,'Debt Input'!Y35) -> 0 | M38: =IF(Acq_Financing_Type_Switch="All Cash",0,'Debt Input'!Z35) -> 0 | N38: =IF(Acq_Financing_Type_Switch="All Cash",0,'Debt Input'!AA35) -> 0 | ... P38: =IF(Acq_Financing_Type_Switch="All Cash",0,'Debt Input'!AC35) -> 0
E39: Closing Costs | G39: 0 | H39: 0 | I39: 0 | J39: 0 | K39: 0 | L39: 0 | M39: 0 | N39: 0 | O39: 0 | P39: =IFERROR(-P32*Cost_of_Sale,0) -> 0
